Workbook

Sheet StrapScenario1 Copia
A1: Wash number | B1: ='[1]Final Data (use this)'!C11 | C1: ='[1]Final Data (use this)'!D11 | D1: ='[1]Final Data (use this)'!E3 | E1: ='[1]Final Data (use this)'!F3 | F1: ='[1]Final Data (use this)'!H3 | G1: ='[1]Final Data (use this)'!I3 | H1: ='[1]Final Data (use this)'!J3 | I1: ='[1]Final Data (use this)'!L3 | J1: ='[1]Final Data (use this)'!M3 | K1: ='[1]Final Data (use this)'!O3 | L1: ='[1]Final Data (use this)'!P3 | M1: ='[1]Final Data (use this)'!R3 | N1: ='[1]Final Data (use this)'!S3 | O1: ='[1]Final Data (use this)'!T3 | P1: Ecotoxicity [CTUe/ton resin] | Q1: CAPEX [USD] | R1: OPEX [USD/ton]
A2: Wash 1 | B2: PE | C2: sec-Butyl Acetate | D2: =[2]Process_results_C1_P1!B2+Shredder!$B$2 | F2: =M2 | I2: 1006.01 | J2: 65401.74 | K2: 7403.53 | M2: =[2]Process_results_C1_P1!C2+Shredder!$K$2 | N2: =[2]Process_results_C1_P1!H2+Shredder!$L$2 | O2: =[2]Process_results_C1_P1!I2+Shredder!$M$2 | P2: =[2]Process_results_C1_P1!J2+Shredder!$N$2 | Q2: =[2]Process_results_C1_P1!K2+Shredder!$O$2 | R2: =[2]Process_results_C1_P1!L2+Shredder!$P$2
A3: Wash 1 | B3: PE | C3: Isobutyl Acetate | D3: =[2]Process_results_C1_P1!B3+Shredder!$B$2 | F3: =M3 | I3: 994.95 | J3: 64491.6 | K3: 7463.47 | M3: =[2]Process_results_C1_P1!C3+Shredder!$K$2 | N3: =[2]Process_results_C1_P1!H3+Shredder!$L$2 | O3: =[2]Process_results_C1_P1!I3+Shredder!$M$2 | P3: =[2]Process_results_C1_P1!J3+Shredder!$N$2 | Q3: =[2]Process_results_C1_P1!K3+Shredder!$O$2 | R3: =[2]Process_results_C1_P1!L3+Shredder!$P$2
A4: Wash 1 | B4: PE | C4: Tetrachloroethylene | D4: =[2]Process_results_C1_P1!B4+Shredder!$B$2 | F4: =M4 | I4: 683.96 | J4: 38449.65 | K4: 4419.13 | M4: =[2]Process_results_C1_P1!C4+Shredder!$K$2 | N4: =[2]Process_results_C1_P1!H4+Shredder!$L$2 | O4: =[2]Process_results_C1_P1!I4+Shredder!$M$2 | P4: =[2]Process_results_C1_P1!J4+Shredder!$N$2 | Q4: =[2]Process_results_C1_P1!K4+Shredder!$O$2 | R4: =[2]Process_results_C1_P1!L4+Shredder!$P$2
A5: Wash 1 | B5: PE | C5: o-Chlorotoluene | D5: =[2]Process_results_C1_P1!B5+Shredder!$B$2 | F5: =M5 | I5: 1139.79 | J5: 76633.44 | K5: 6319.81 | M5: =[2]Process_results_C1_P1!C5+Shredder!$K$2 | N5: =[2]Process_results_C1_P1!H5+Shredder!$L$2 | O5: =[2]Process_results_C1_P1!I5+Shredder!$M$2 | P5: =[2]Process_results_C1_P1!J5+Shredder!$N$2 | Q5: =[2]Process_results_C1_P1!K5+Shredder!$O$2 | R5: =[2]Process_results_C1_P1!L5+Shredder!$P$2
A6: Wash 1 | B6: PE | C6: Methylcyclohexane | D6: =[2]Process_results_C1_P1!B6+Shredder!$B$2 | F6: =M6 | I6: 887.08 | J6: 55514.4 | K6: 8129.51 | M6: =[2]Process_results_C1_P1!C6+Shredder!$K$2 | N6: =[2]Process_results_C1_P1!H6+Shredder!$L$2 | O6: =[2]Process_results_C1_P1!I6+Shredder!$M$2 | P6: =[2]Process_results_C1_P1!J6+Shredder!$N$2 | Q6: =[2]Process_results_C1_P1!K6+Shredder!$O$2 | R6: =[2]Process_results_C1_P1!L6+Shredder!$P$2
A7: Wash 1 | B7: PE | C7: Dodecanol | D7: =[2]Process_results_C1_P1!B7+Shredder!$B$2 | F7: =M7 | I7: 2487.39 | J7: 187927.49 | K7: 8514.94 | M7: =[2]Process_results_C1_P1!C7+Shredder!$K$2 | N7: =[2]Process_results_C1_P1!H7+Shredder!$L$2 | O7: =[2]Process_results_C1_P1!I7+Shredder!$M$2 | P7: =[2]Process_results_C1_P1!J7+Shredder!$N$2 | Q7: =[2]Process_results_C1_P1!K7+Shredder!$O$2 | R7: =[2]Process_results_C1_P1!L7+Shredder!$P$2
A8: Wash 1 | B8: PE | C8: Heptane | D8: =[2]Process_results_C1_P1!B8+Shredder!$B$2 | F8: =M8 | I8: 920.27 | J8: 58179.21 | K8: 9006.42 | M8: =[2]Process_results_C1_P1!C8+Shredder!$K$2 | N8: =[2]Process_results_C1_P1!H8+Shredder!$L$2 | O8: =[2]Process_results_C1_P1!I8+Shredder!$M$2 | P8: =[2]Process_results_C1_P1!J8+Shredder!$N$2 | Q8: =[2]Process_results_C1_P1!K8+Shredder!$O$2 | R8: =[2]Process_results_C1_P1!L8+Shredder!$P$2
A9: Wash 1 | B9: PE | C9: Toluene | D9: =[2]Process_results_C1_P1!B9+Shredder!$B$2 | F9: =M9 | I9: 1040.73 | J9: 67836.93 | K9: 11871.24 | M9: =[2]Process_results_C1_P1!C9+Shredder!$K$2 | N9: =[2]Process_results_C1_P1!H9+Shredder!$L$2 | O9: =[2]Process_results_C1_P1!I9+Shredder!$M$2 | P9: =[2]Process_results_C1_P1!J9+Shredder!$N$2 | Q9: =[2]Process_results_C1_P1!K9+Shredder!$O$2 | R9: =[2]Process_results_C1_P1!L9+Shredder!$P$2
A10: Wash 1 | B10: PE | C10: Xylene | D10: =[2]Process_results_C1_P1!B10+Shredder!$B$2 | F10: =M10 | I10: 1159.2 | J10: 78331.71 | K10: 7294.56 | M10: =[2]Process_results_C1_P1!C10+Shredder!$K$2 | N10: =[2]Process_results_C1_P1!H10+Shredder!$L$2 | O10: =[2]Process_results_C1_P1!I10+Shredder!$M$2 | P10: =[2]Process_results_C1_P1!J10+Shredder!$N$2 | Q10: =[2]Process_results_C1_P1!K10+Shredder!$O$2 | R10: =[2]Process_results_C1_P1!L10+Shredder!$P$2
A11: Wash 1 | B11: EVOH | C11: =[3]Process_results_C1_E1!$A$2 | D11: =[3]Process_results_C1_E1!B2+Shredder!$B$2 | F11: =M11 | I11: 1512.92 | J11: 125060.56 | K11: 2426.35 | M11: =[3]Process_results_C1_E1!C2+Shredder!$K$2 | N11: =[3]Process_results_C1_E1!H2+Shredder!$L$2 | O11: =[3]Process_results_C1_E1!I2+Shredder!$M$2 | P11: =[3]Process_results_C1_E1!J2+Shredder!$N$2 | Q11: =[3]Process_results_C1_E1!K2+Shredder!$O$2 | R11: =[3]Process_results_C1_E1!L2+Shredder!$P$2
A12: Wash 1 | B12: EVOH | C12: =[3]Process_results_C1_E1!$A$3 | D12: =[3]Process_results_C1_E1!B3+Shredder!$B$2 | F12: =M12 | I12: 964.84 | J12: 76612.87 | K12: 2837.85 | M12: =[3]Process_results_C1_E1!C3+Shredder!$K$2 | N12: =[3]Process_results_C1_E1!H3+Shredder!$L$2 | O12: =[3]Process_results_C1_E1!I3+Shredder!$M$2 | P12: =[3]Process_results_C1_E1!J3+Shredder!$N$2 | Q12: =[3]Process_results_C1_E1!K3+Shredder!$O$2 | R12: =[3]Process_results_C1_E1!L3+Shredder!$P$2
A13: Wash 2 | B13: PE | C13: sec-Butyl Acetate | D13: 5.02 | F13: =M13 | I13: 966.49 | J13: 62262.96 | K13: 7303.6 | M13: 1.2005329 | N13: 4.5338019e-08 | O13: 2.5078508e-08 | P13: 1.2777775 | Q13: 40931215 | R13: 1047740.1
A14: Wash 2 | B14: PE | C14: Isobutyl Acetate | D14: 5.02 | F14: =M14 | I14: 958.02 | J14: 61569.48 | K14: 7363.19 | M14: 1.196813 | N14: 4.5246416e-08 | O14: 2.5090223e-08 | P14: 1.2774454 | Q14: 41185362 | R14: 1052268.2
A15: Wash 2 | B15: PE | C15: Tetrachloroethylene | D15: 4.8 | F15: =M15 | I15: 656.12 | J15: 36362.45 | K15: 4341.89 | M15: 1.0965103 | N15: 3.9866638e-08 | O15: 2.1764279e-08 | P15: 1.0740143 | Q15: 35754823 | R15: 938269.24
A16: Wash 2 | B16: PE | C16: o-Chlorotoluene | D16: 5.01 | F16: =M16 | I16: 1098.51 | J16: 73352.38 | K16: 6226.9 | M16: 1.2365479 | N16: 4.6334882e-08 | O16: 2.5177552e-08 | P16: 1.2972699 | Q16: 39697204 | R16: 1028423.1
A17: Wash 2 | B17: PE | C17: Methylcyclohexane | D17: 5.01 | F17: =M17 | I17: 846.45 | J17: 52253.34 | K17: 8025.78 | M17: 1.1562855 | N17: 4.2921731e-08 | O17: 2.2988628e-08 | P17: 1.1816403 | Q17: 41755740 | R17: 1059416.7
A18: Wash 2 | B18: PE | C18: Dodecanol | D18: 5.48 | F18: =M18 | I18: 2419.67 | J18: 182520.62 | K18: 8405.55 | M18: 1.7207436 | N18: 6.5314505e-08 | O18: 3.977586e-08 | P18: 1.9967304 | Q18: 45094364 | R18: 1186252
A19: Wash 2 | B19: PE | C19: Heptane | D19: 5.06 | F19: =M19 | I19: 880.03 | J19: 54950.96 | K19: 8897.14 | M19: 1.1688554 | N19: 4.3001802e-08 | O19: 2.2719875e-08 | P19: 1.1656356 | Q19: 43208033 | R19: 1088889.2
A20: Wash 2 | B20: PE | C20: Toluene | D20: 5.18 | F20: =M20 | I20: 993.67 | J20: 64056.57 | K20: 11716.23 | M20: 1.2141233 | N20: 4.5108743e-08 | O20: 2.3876385e-08 | P20: 1.2302914 | Q20: 46986127 | R20: 1179441.8
A21: Wash 2 | B21: PE | C21: Xylene | D21: 5.06 | F21: =M21 | I21: 1117.99 | J21: 75028.67 | K21: 7194.85 | M21: 1.2384899 | N21: 4.5663809e-08 | O21: 2.4004406e-08 | P21: 1.235194 | Q21: 41234664 | R21: 1058246.1
A22: Wash 2 | B22: EVOH | C22: butane-1,4-diol | D22: =[4]Process_results_C1_E2!B2*Shredder!$B$2 | F22: =M22 | I22: =[4]Process_results_C1_E2!F2 | J22: =[4]Process_results_C1_E2!G2 | K22: =[4]Process_results_C1_E2!D2 | M22: =[4]Process_results_C1_E2!C2+Shredder!$K$2 | N22: =[4]Process_results_C1_E2!H2+Shredder!$L$2 | O22: =[4]Process_results_C1_E2!I2+Shredder!$M$2 | P22: =[4]Process_results_C1_E2!J2+Shredder!$N$2 | Q22: =[4]Process_results_C1_E2!K2+Shredder!$O$2 | R22: =[4]Process_results_C1_E2!L2+Shredder!$P$2
A23: Wash 2 | B23: EVOH | C23: Diethanolamine | D23: =[4]Process_results_C1_E2!B3*Shredder!$B$2 | F23: =M23 | I23: =[4]Process_results_C1_E2!F3 | J23: =[4]Process_results_C1_E2!G3 | K23: =[4]Process_results_C1_E2!D3 | M23: =[4]Process_results_C1_E2!C3+Shredder!$K$2 | N23: =[4]Process_results_C1_E2!H3+Shredder!$L$2 | O23: =[4]Process_results_C1_E2!I3+Shredder!$M$2 | P23: =[4]Process_results_C1_E2!J3+Shredder!$N$2 | Q23: =[4]Process_results_C1_E2!K3+Shredder!$O$2 | R23: =[4]Process_results_C1_E2!L3+Shredder!$P$2
A24: Wash 2 | B24: EVOH | C24: Diethylene glycol | D24: =[4]Process_results_C1_E2!B4*Shredder!$B$2 | F24: =M24 | I24: =[4]Process_results_C1_E2!F4 | J24: =[4]Process_results_C1_E2!G4 | K24: =[4]Process_results_C1_E2!D4 | M24: =[4]Process_results_C1_E2!C4+Shredder!$K$2 | N24: =[4]Process_results_C1_E2!H4+Shredder!$L$2 | O24: =[4]Process_results_C1_E2!I4+Shredder!$M$2 | P24: =[4]Process_results_C1_E2!J4+Shredder!$N$2 | Q24: =[4]Process_results_C1_E2!K4+Shredder!$O$2 | R24: =[4]Process_results_C1_E2!L4+Shredder!$P$2
A25: Wash 2 | B25: EVOH | C25: Ethylene Glycol | D25: =[4]Process_results_C1_E2!B5*Shredder!$B$2 | F25: =M25 | I25: =[4]Process_results_C1_E2!F5 | J25: =[4]Process_results_C1_E2!G5 | K25: =[4]Process_results_C1_E2!D5 | M25: =[4]Process_results_C1_E2!C5+Shredder!$K$2 | N25: =[4]Process_results_C1_E2!H5+Shredder!$L$2 | O25: =[4]Process_results_C1_E2!I5+Shredder!$M$2 | P25: =[4]Process_results_C1_E2!J5+Shredder!$N$2 | Q25: =[4]Process_results_C1_E2!K5+Shredder!$O$2 | R25: =[4]Process_results_C1_E2!L5+Shredder!$P$2
A26: Wash 2 | B26: EVOH | C26: Propylene Glycol | D26: =[4]Process_results_C1_E2!B6*Shredder!$B$2 | F26: =M26 | I26: =[4]Process_results_C1_E2!F6 | J26: =[4]Process_results_C1_E2!G6 | K26: =[4]Process_results_C1_E2!D6 | M26: =[4]Process_results_C1_E2!C6+Shredder!$K$2 | N26: =[4]Process_results_C1_E2!H6+Shredder!$L$2 | O26: =[4]Process_results_C1_E2!I6+Shredder!$M$2 | P26: =[4]Process_results_C1_E2!J6+Shredder!$N$2 | Q26: =[4]Process_results_C1_E2!K6+Shredder!$O$2 | R26: =[4]Process_results_C1_E2!L6+Shredder!$P$2
A27: Wash 2 | B27: EVOH | C27: Pyridazine | D27: =[4]Process_results_C1_E2!B7*Shredder!$B$2 | F27: =M27 | I27: =[4]Process_results_C1_E2!F7 | J27: =[4]Process_results_C1_E2!G7 | K27: =[4]Process_results_C1_E2!D7 | M27: =[4]Process_results_C1_E2!C7+Shredder!$K$2 | N27: =[4]Process_results_C1_E2!H7+Shredder!$L$2 | O27: =[4]Process_results_C1_E2!I7+Shredder!$M$2 | P27: =[4]Process_results_C1_E2!J7+Shredder!$N$2 | Q27: =[4]Process_results_C1_E2!K7+Shredder!$O$2 | R27: =[4]Process_results_C1_E2!L7+Shredder!$P$2
A28: Wash 2 | B28: EVOH | C28: gamma-butyrolactone | D28: =[4]Process_results_C1_E2!B8*Shredder!$B$2 | F28: =M28 | I28: =[4]Process_results_C1_E2!F8 | J28: =[4]Process_results_C1_E2!G8 | K28: =[4]Process_results_C1_E2!D8 | M28: =[4]Process_results_C1_E2!C8+Shredder!$K$2 | N28: =[4]Process_results_C1_E2!H8+Shredder!$L$2 | O28: =[4]Process_results_C1_E2!I8+Shredder!$M$2 | P28: =[4]Process_results_C1_E2!J8+Shredder!$N$2 | Q28: =[4]Process_results_C1_E2!K8+Shredder!$O$2 | R28: =[4]Process_results_C1_E2!L8+Shredder!$P$2

Sheet StrapScenario1 Units
A1: Wash number | B1: Polymer | C1: Solvents | D1: Total Energy Consumed [MJ/yr] | E1: Total Renewable Energy Consumed [MJ/yr] | F1: Total Direct GHG emissions [Scope 1] [metric tons CO2 equivalent [tCO2e/yr]] | G1: Total Energy indirect GHG emissions (Scope 2) [metric tons CO2 equivalent (t CO2e/yr)] | H1: Water consumed/discarded [m3/yr] | I1: Water Recycled or Reused [m3/yr] | J1: Waste generated - Non Hazardous [kg/yr] | K1: Waste to Disposal[ton/yr] | L1: GWP [tonCO2e/yr] | M1: Human toxicity cancer [CTUh/yr] | N1: Human toxicity non-cancer [CTUh/yr] | O1: Ecotoxicity [CTUe/yr] | P1: CAPEX [USD/yr] | Q1: OPEX [USD/yr]
A2: =StrapScenario1!A2 | B2: =StrapScenario1!B2 | C2: =StrapScenario1!C2 | D2: =StrapScenario1!D2*'[1]New UBs'!$E$50 | E2: =StrapScenario1!E2 | F2: =L2 | G2: =StrapScenario1!G2 | H2: =StrapScenario1!H2 | I2: =StrapScenario1!I2 | J2: =StrapScenario1!J2 | K2: =StrapScenario1!K2 | L2: =StrapScenario1!L2*'[1]New UBs'!$E$50/1000 | M2: =StrapScenario1!M2*'[1]New UBs'!$E$50 | N2: =StrapScenario1!N2*'[1]New UBs'!$E$50 | O2: =StrapScenario1!O2*'[1]New UBs'!$E$50 | P2: =StrapScenario1!P2/20 | Q2: =StrapScenario1!Q2
A3: =StrapScenario1!A3 | B3: =StrapScenario1!B3 | C3: =StrapScenario1!C3 | D3: =StrapScenario1!D3*'[1]New UBs'!$E$50 | E3: =StrapScenario1!E3 | F3: =L3 | G3: =StrapScenario1!G3 | H3: =StrapScenario1!H3 | I3: =StrapScenario1!I3 | J3: =StrapScenario1!J3 | K3: =StrapScenario1!K3 | L3: =StrapScenario1!L3*'[1]New UBs'!$E$50/1000 | M3: =StrapScenario1!M3*'[1]New UBs'!$E$50 | N3: =StrapScenario1!N3*'[1]New UBs'!$E$50 | O3: =StrapScenario1!O3*'[1]New UBs'!$E$50 | P3: =StrapScenario1!P3/20 | Q3: =StrapScenario1!Q3
A4: =StrapScenario1!A4 | B4: =StrapScenario1!B4 | C4: =StrapScenario1!C4 | D4: =StrapScenario1!D4*'[1]New UBs'!$E$50 | E4: =StrapScenario1!E4 | F4: =L4 | G4: =StrapScenario1!G4 | H4: =StrapScenario1!H4 | I4: =StrapScenario1!I4 | J4: =StrapScenario1!J4 | K4: =StrapScenario1!K4 | L4: =StrapScenario1!L4*'[1]New UBs'!$E$50/1000 | M4: =StrapScenario1!M4*'[1]New UBs'!$E$50 | N4: =StrapScenario1!N4*'[1]New UBs'!$E$50 | O4: =StrapScenario1!O4*'[1]New UBs'!$E$50 | P4: =StrapScenario1!P4/20 | Q4: =StrapScenario1!Q4
A5: =StrapScenario1!A5 | B5: =StrapScenario1!B5 | C5: =StrapScenario1!C5 | D5: =StrapScenario1!D5*'[1]New UBs'!$E$50 | E5: =StrapScenario1!E5 | F5: =L5 | G5: =StrapScenario1!G5 | H5: =StrapScenario1!H5 | I5: =StrapScenario1!I5 | J5: =StrapScenario1!J5 | K5: =StrapScenario1!K5 | L5: =StrapScenario1!L5*'[1]New UBs'!$E$50/1000 | M5: =StrapScenario1!M5*'[1]New UBs'!$E$50 | N5: =StrapScenario1!N5*'[1]New UBs'!$E$50 | O5: =StrapScenario1!O5*'[1]New UBs'!$E$50 | P5: =StrapScenario1!P5/20 | Q5: =StrapScenario1!Q5
A6: =StrapScenario1!A6 | B6: =StrapScenario1!B6 | C6: =StrapScenario1!C6 | D6: =StrapScenario1!D6*'[1]New UBs'!$E$50 | E6: =StrapScenario1!E6 | F6: =L6 | G6: =StrapScenario1!G6 | H6: =StrapScenario1!H6 | I6: =StrapScenario1!I6 | J6: =StrapScenario1!J6 | K6: =StrapScenario1!K6 | L6: =StrapScenario1!L6*'[1]New UBs'!$E$50/1000 | M6: =StrapScenario1!M6*'[1]New UBs'!$E$50 | N6: =StrapScenario1!N6*'[1]New UBs'!$E$50 | O6: =StrapScenario1!O6*'[1]New UBs'!$E$50 | P6: =StrapScenario1!P6/20 | Q6: =StrapScenario1!Q6
A7: =StrapScenario1!A7 | B7: =StrapScenario1!B7 | C7: =StrapScenario1!C7 | D7: =StrapScenario1!D7*'[1]New UBs'!$E$50 | E7: =StrapScenario1!E7 | F7: =L7 | G7: =StrapScenario1!G7 | H7: =StrapScenario1!H7 | I7: =StrapScenario1!I7 | J7: =StrapScenario1!J7 | K7: =StrapScenario1!K7 | L7: =StrapScenario1!L7*'[1]New UBs'!$E$50/1000 | M7: =StrapScenario1!M7*'[1]New UBs'!$E$50 | N7: =StrapScenario1!N7*'[1]New UBs'!$E$50 | O7: =StrapScenario1!O7*'[1]New UBs'!$E$50 | P7: =StrapScenario1!P7/20 | Q7: =StrapScenario1!Q7
A8: =StrapScenario1!A8 | B8: =StrapScenario1!B8 | C8: =StrapScenario1!C8 | D8: =StrapScenario1!D8*'[1]New UBs'!$E$50 | E8: =StrapScenario1!E8 | F8: =L8 | G8: =StrapScenario1!G8 | H8: =StrapScenario1!H8 | I8: =StrapScenario1!I8 | J8: =StrapScenario1!J8 | K8: =StrapScenario1!K8 | L8: =StrapScenario1!L8*'[1]New UBs'!$E$50/1000 | M8: =StrapScenario1!M8*'[1]New UBs'!$E$50 | N8: =StrapScenario1!N8*'[1]New UBs'!$E$50 | O8: =StrapScenario1!O8*'[1]New UBs'!$E$50 | P8: =StrapScenario1!P8/20 | Q8: =StrapScenario1!Q8
A9: =StrapScenario1!A9 | B9: =StrapScenario1!B9 | C9: =StrapScenario1!C9 | D9: =StrapScenario1!D9*'[1]New UBs'!$E$50 | E9: =StrapScenario1!E9 | F9: =L9 | G9: =StrapScenario1!G9 | H9: =StrapScenario1!H9 | I9: =StrapScenario1!I9 | J9: =StrapScenario1!J9 | K9: =StrapScenario1!K9 | L9: =StrapScenario1!L9*'[1]New UBs'!$E$50/1000 | M9: =StrapScenario1!M9*'[1]New UBs'!$E$50 | N9: =StrapScenario1!N9*'[1]New UBs'!$E$50 | O9: =StrapScenario1!O9*'[1]New UBs'!$E$50 | P9: =StrapScenario1!P9/20 | Q9: =StrapScenario1!Q9
A10: =StrapScenario1!A10 | B10: =StrapScenario1!B10 | C10: =StrapScenario1!C10 | D10: =StrapScenario1!D10*'[1]New UBs'!$E$50 | E10: =StrapScenario1!E10 | F10: =L10 | G10: =StrapScenario1!G10 | H10: =StrapScenario1!H10 | I10: =StrapScenario1!I10 | J10: =StrapScenario1!J10 | K10: =StrapScenario1!K10 | L10: =StrapScenario1!L10*'[1]New UBs'!$E$50/1000 | M10: =StrapScenario1!M10*'[1]New UBs'!$E$50 | N10: =StrapScenario1!N10*'[1]New UBs'!$E$50 | O10: =StrapScenario1!O10*'[1]New UBs'!$E$50 | P10: =StrapScenario1!P10/20 | Q10: =StrapScenario1!Q10
A11: =StrapScenario1!A11 | B11: =StrapScenario1!B11 | C11: =StrapScenario1!C11 | D11: =StrapScenario1!D11*'[1]New UBs'!$E$51 | E11: =StrapScenario1!E11 | F11: =L11 | G11: =StrapScenario1!G11 | H11: =StrapScenario1!H11 | I11: =StrapScenario1!I11 | J11: =StrapScenario1!J11 | K11: =StrapScenario1!K11 | L11: =StrapScenario1!L11*'[1]New UBs'!$E$51/1000 | M11: =StrapScenario1!M11*'[1]New UBs'!$E$51 | N11: =StrapScenario1!N11*'[1]New UBs'!$E$51 | O11: =StrapScenario1!O11*'[1]New UBs'!$E$51 | P11: =StrapScenario1!P11/20 | Q11: =StrapScenario1!Q11
A12: =StrapScenario1!A12 | B12: =StrapScenario1!B12 | C12: =StrapScenario1!C12 | D12: =StrapScenario1!D12*'[1]New UBs'!$E$51 | E12: =StrapScenario1!E12 | F12: =L12 | G12: =StrapScenario1!G12 | H12: =StrapScenario1!H12 | I12: =StrapScenario1!I12 | J12: =StrapScenario1!J12 | K12: =StrapScenario1!K12 | L12: =StrapScenario1!L12*'[1]New UBs'!$E$51/1000 | M12: =StrapScenario1!M12*'[1]New UBs'!$E$51 | N12: =StrapScenario1!N12*'[1]New UBs'!$E$51 | O12: =StrapScenario1!O12*'[1]New UBs'!$E$51 | P12: =StrapScenario1!P12/20 | Q12: =StrapScenario1!Q12
A13: =StrapScenario1!A13 | B13: =StrapScenario1!B13 | C13: =StrapScenario1!C13 | D13: =StrapScenario1!D13*'[1]New UBs'!$J$51 | E13: =StrapScenario1!E13 | F13: =L13 | G13: =StrapScenario1!G13 | H13: =StrapScenario1!H13 | I13: =StrapScenario1!I13 | J13: =StrapScenario1!J13 | K13: =StrapScenario1!K13 | L13: =StrapScenario1!L13*'[1]New UBs'!$J$51/1000 | M13: =StrapScenario1!M13*'[1]New UBs'!$J$50 | N13: =StrapScenario1!N13*'[1]New UBs'!$J$51 | O13: =StrapScenario1!O13*'[1]New UBs'!$J$51 | P13: =StrapScenario1!P13/20 | Q13: =StrapScenario1!Q13
A14: =StrapScenario1!A14 | B14: =StrapScenario1!B14 | C14: =StrapScenario1!C14 | D14: =StrapScenario1!D14*'[1]New UBs'!$J$51 | E14: =StrapScenario1!E14 | F14: =L14 | G14: =StrapScenario1!G14 | H14: =StrapScenario1!H14 | I14: =StrapScenario1!I14 | J14: =StrapScenario1!J14 | K14: =StrapScenario1!K14 | L14: =StrapScenario1!L14*'[1]New UBs'!$J$51/1000 | M14: =StrapScenario1!M14*'[1]New UBs'!$J$50 | N14: =StrapScenario1!N14*'[1]New UBs'!$J$51 | O14: =StrapScenario1!O14*'[1]New UBs'!$J$51 | P14: =StrapScenario1!P14/20 | Q14: =StrapScenario1!Q14
A15: =StrapScenario1!A15 | B15: =StrapScenario1!B15 | C15: =StrapScenario1!C15 | D15: =StrapScenario1!D15*'[1]New UBs'!$J$51 | E15: =StrapScenario1!E15 | F15: =L15 | G15: =StrapScenario1!G15 | H15: =StrapScenario1!H15 | I15: =StrapScenario1!I15 | J15: =StrapScenario1!J15 | K15: =StrapScenario1!K15 | L15: =StrapScenario1!L15*'[1]New UBs'!$J$51/1000 | M15: =StrapScenario1!M15*'[1]New UBs'!$J$50 | N15: =StrapScenario1!N15*'[1]New UBs'!$J$51 | O15: =StrapScenario1!O15*'[1]New UBs'!$J$51 | P15: =StrapScenario1!P15/20 | Q15: =StrapScenario1!Q15
A16: =StrapScenario1!A16 | B16: =StrapScenario1!B16 | C16: =StrapScenario1!C16 | D16: =StrapScenario1!D16*'[1]New UBs'!$J$51 | E16: =StrapScenario1!E16 | F16: =L16 | G16: =StrapScenario1!G16 | H16: =StrapScenario1!H16 | I16: =StrapScenario1!I16 | J16: =StrapScenario1!J16 | K16: =StrapScenario1!K16 | L16: =StrapScenario1!L16*'[1]New UBs'!$J$51/1000 | M16: =StrapScenario1!M16*'[1]New UBs'!$J$50 | N16: =StrapScenario1!N16*'[1]New UBs'!$J$51 | O16: =StrapScenario1!O16*'[1]New UBs'!$J$51 | P16: =StrapScenario1!P16/20 | Q16: =StrapScenario1!Q16
A17: =StrapScenario1!A17 | B17: =StrapScenario1!B17 | C17: =StrapScenario1!C17 | D17: =StrapScenario1!D17*'[1]New UBs'!$J$51 | E17: =StrapScenario1!E17 | F17: =L17 | G17: =StrapScenario1!G17 | H17: =StrapScenario1!H17 | I17: =StrapScenario1!I17 | J17: =StrapScenario1!J17 | K17: =StrapScenario1!K17 | L17: =StrapScenario1!L17*'[1]New UBs'!$J$51/1000 | M17: =StrapScenario1!M17*'[1]New UBs'!$J$50 | N17: =StrapScenario1!N17*'[1]New UBs'!$J$51 | O17: =StrapScenario1!O17*'[1]New UBs'!$J$51 | P17: =StrapScenario1!P17/20 | Q17: =StrapScenario1!Q17
A18: =StrapScenario1!A18 | B18: =StrapScenario1!B18 | C18: =StrapScenario1!C18 | D18: =StrapScenario1!D18*'[1]New UBs'!$J$51 | E18: =StrapScenario1!E18 | F18: =L18 | G18: =StrapScenario1!G18 | H18: =StrapScenario1!H18 | I18: =StrapScenario1!I18 | J18: =StrapScenario1!J18 | K18: =StrapScenario1!K18 | L18: =StrapScenario1!L18*'[1]New UBs'!$J$51/1000 | M18: =StrapScenario1!M18*'[1]New UBs'!$J$50 | N18: =StrapScenario1!N18*'[1]New UBs'!$J$51 | O18: =StrapScenario1!O18*'[1]New UBs'!$J$51 | P18: =StrapScenario1!P18/20 | Q18: =StrapScenario1!Q18
A19: =StrapScenario1!A19 | B19: =StrapScenario1!B19 | C19: =StrapScenario1!C19 | D19: =StrapScenario1!D19*'[1]New UBs'!$J$51 | E19: =StrapScenario1!E19 | F19: =L19 | G19: =StrapScenario1!G19 | H19: =StrapScenario1!H19 | I19: =StrapScenario1!I19 | J19: =StrapScenario1!J19 | K19: =StrapScenario1!K19 | L19: =StrapScenario1!L19*'[1]New UBs'!$J$51/1000 | M19: =StrapScenario1!M19*'[1]New UBs'!$J$50 | N19: =StrapScenario1!N19*'[1]New UBs'!$J$51 | O19: =StrapScenario1!O19*'[1]New UBs'!$J$51 | P19: =StrapScenario1!P19/20 | Q19: =StrapScenario1!Q19
A20: =StrapScenario1!A20 | B20: =StrapScenario1!B20 | C20: =StrapScenario1!C20 | D20: =StrapScenario1!D20*'[1]New UBs'!$J$51 | E20: =StrapScenario1!E20 | F20: =L20 | G20: =StrapScenario1!G20 | H20: =StrapScenario1!H20 | I20: =StrapScenario1!I20 | J20: =StrapScenario1!J20 | K20: =StrapScenario1!K20 | L20: =StrapScenario1!L20*'[1]New UBs'!$J$51/1000 | M20: =StrapScenario1!M20*'[1]New UBs'!$J$50 | N20: =StrapScenario1!N20*'[1]New UBs'!$J$51 | O20: =StrapScenario1!O20*'[1]New UBs'!$J$51 | P20: =StrapScenario1!P20/20 | Q20: =StrapScenario1!Q20
A21: =StrapScenario1!A21 | B21: =StrapScenario1!B21 | C21: =StrapScenario1!C21 | D21: =StrapScenario1!D21*'[1]New UBs'!$J$51 | E21: =StrapScenario1!E21 | F21: =L21 | G21: =StrapScenario1!G21 | H21: =StrapScenario1!H21 | I21: =StrapScenario1!I21 | J21: =StrapScenario1!J21 | K21: =StrapScenario1!K21 | L21: =StrapScenario1!L21*'[1]New UBs'!$J$51/1000 | M21: =StrapScenario1!M21*'[1]New UBs'!$J$50 | N21: =StrapScenario1!N21*'[1]New UBs'!$J$51 | O21: =StrapScenario1!O21*'[1]New UBs'!$J$51 | P21: =StrapScenario1!P21/20 | Q21: =StrapScenario1!Q21
A22: =StrapScenario1!A22 | B22: =StrapScenario1!B22 | C22: =StrapScenario1!C22 | D22: =StrapScenario1!D22*'[1]New UBs'!$J$50 | E22: =StrapScenario1!E22 | F22: =L22 | G22: =StrapScenario1!G22 | H22: =StrapScenario1!H22 | I22: =StrapScenario1!I22 | J22: =StrapScenario1!J22 | K22: =StrapScenario1!K22 | L22: =StrapScenario1!L22*'[1]New UBs'!$J$50/1000 | M22: =StrapScenario1!M22*'[1]New UBs'!$J$51 | N22: =StrapScenario1!N22*'[1]New UBs'!$J$50 | O22: =StrapScenario1!O22*'[1]New UBs'!$J$50 | P22: =StrapScenario1!P22/20 | Q22: =StrapScenario1!Q22
A23: =StrapScenario1!A23 | B23: =StrapScenario1!B23 | C23: =StrapScenario1!C23 | D23: =StrapScenario1!D23*'[1]New UBs'!$J$50 | E23: =StrapScenario1!E23 | F23: =L23 | G23: =StrapScenario1!G23 | H23: =StrapScenario1!H23 | I23: =StrapScenario1!I23 | J23: =StrapScenario1!J23 | K23: =StrapScenario1!K23 | L23: =StrapScenario1!L23*'[1]New UBs'!$J$50/1000 | M23: =StrapScenario1!M23*'[1]New UBs'!$J$51 | N23: =StrapScenario1!N23*'[1]New UBs'!$J$50 | O23: =StrapScenario1!O23*'[1]New UBs'!$J$50 | P23: =StrapScenario1!P23/20 | Q23: =StrapScenario1!Q23
A24: =StrapScenario1!A24 | B24: =StrapScenario1!B24 | C24: =StrapScenario1!C24 | D24: =StrapScenario1!D24*'[1]New UBs'!$J$50 | E24: =StrapScenario1!E24 | F24: =L24 | G24: =StrapScenario1!G24 | H24: =StrapScenario1!H24 | I24: =StrapScenario1!I24 | J24: =StrapScenario1!J24 | K24: =StrapScenario1!K24 | L24: =StrapScenario1!L24*'[1]New UBs'!$J$50/1000 | M24: =StrapScenario1!M24*'[1]New UBs'!$J$51 | N24: =StrapScenario1!N24*'[1]New UBs'!$J$50 | O24: =StrapScenario1!O24*'[1]New UBs'!$J$50 | P24: =StrapScenario1!P24/20 | Q24: =StrapScenario1!Q24
A25: =StrapScenario1!A25 | B25: =StrapScenario1!B25 | C25: =StrapScenario1!C25 | D25: =StrapScenario1!D25*'[1]New UBs'!$J$50 | E25: =StrapScenario1!E25 | F25: =L25 | G25: =StrapScenario1!G25 | H25: =StrapScenario1!H25 | I25: =StrapScenario1!I25 | J25: =StrapScenario1!J25 | K25: =StrapScenario1!K25 | L25: =StrapScenario1!L25*'[1]New UBs'!$J$50/1000 | M25: =StrapScenario1!M25*'[1]New UBs'!$J$51 | N25: =StrapScenario1!N25*'[1]New UBs'!$J$50 | O25: =StrapScenario1!O25*'[1]New UBs'!$J$50 | P25: =StrapScenario1!P25/20 | Q25: =StrapScenario1!Q25
A26: =StrapScenario1!A26 | B26: =StrapScenario1!B26 | C26: =StrapScenario1!C26 | D26: =StrapScenario1!D26*'[1]New UBs'!$J$50 | E26: =StrapScenario1!E26 | F26: =L26 | G26: =StrapScenario1!G26 | H26: =StrapScenario1!H26 | I26: =StrapScenario1!I26 | J26: =StrapScenario1!J26 | K26: =StrapScenario1!K26 | L26: =StrapScenario1!L26*'[1]New UBs'!$J$50/1000 | M26: =StrapScenario1!M26*'[1]New UBs'!$J$51 | N26: =StrapScenario1!N26*'[1]New UBs'!$J$50 | O26: =StrapScenario1!O26*'[1]New UBs'!$J$50 | P26: =StrapScenario1!P26/20 | Q26: =StrapScenario1!Q26
A27: =StrapScenario1!A27 | B27: =StrapScenario1!B27 | C27: =StrapScenario1!C27 | D27: =StrapScenario1!D27*'[1]New UBs'!$J$50 | E27: =StrapScenario1!E27 | F27: =L27 | G27: =StrapScenario1!G27 | H27: =StrapScenario1!H27 | I27: =StrapScenario1!I27 | J27: =StrapScenario1!J27 | K27: =StrapScenario1!K27 | L27: =StrapScenario1!L27*'[1]New UBs'!$J$50/1000 | M27: =StrapScenario1!M27*'[1]New UBs'!$J$51 | N27: =StrapScenario1!N27*'[1]New UBs'!$J$50 | O27: =StrapScenario1!O27*'[1]New UBs'!$J$50 | P27: =StrapScenario1!P27/20 | Q27: =StrapScenario1!Q27
A28: =StrapScenario1!A28 | B28: =StrapScenario1!B28 | C28: =StrapScenario1!C28 | D28: =StrapScenario1!D28*'[1]New UBs'!$J$50 | E28: =StrapScenario1!E28 | F28: =L28 | G28: =StrapScenario1!G28 | H28: =StrapScenario1!H28 | I28: =StrapScenario1!I28 | J28: =StrapScenario1!J28 | K28: =StrapScenario1!K28 | L28: =StrapScenario1!L28*'[1]New UBs'!$J$50/1000 | M28: =StrapScenario1!M28*'[1]New UBs'!$J$51 | N28: =StrapScenario1!N28*'[1]New UBs'!$J$50 | O28: =StrapScenario1!O28*'[1]New UBs'!$J$50 | P28: =StrapScenario1!P28/20 | Q28: =StrapScenario1!Q28

Sheet Sheet3
B3: profit | C3: ce
B6: 4476300.1 | C6: 0.7236345
B7: 7876773.9 | C7: 0.71032814
B8: 8187132.3 | C8: 0.69556882

Sheet StrapScenario1
A1: Wash number | B1: ='[1]Final Data (use this)'!C11 | C1: ='[1]Final Data (use this)'!D11 | D1: Total Energy Consumed [MJ/kg resin produced ] | E1: Total Electricity [MJ/kg resin] | F1: Total Direct GHG emissions [Scope 1] [metric tons CO2 equivalent [tCO2e/ton]] | G1: Total Energy indirect GHG emissions (Scope 2) [metric tons CO2 equivalent (t CO2e)] | H1: Water consumed/discarded [m3/yr] | I1: Water Recycled or Reused [m3/yr] | J1: Waste generated - Non Hazardous [kg/yr] | K1: Waste to Disposal[ton/ton] | L1: GWP [tonCO2e/ton resin] | M1: Human toxicity cancer [CTUh/kg resin] | N1: Human toxicity non-cancer [CTUh/kg resin] | O1: Ecotoxicity [CTUe/kg resin] | P1: CAPEX [USD] | Q1: OPEX [USD/yr]
A2: Wash 1 | B2: PE | C2: sec-Butyl Acetate | D2: =[2]Process_results_C1_P1!B2+Shredder!$B$2 | E2: 0 | F2: =L2 | G2: 0 | H2: 1006.01 | I2: 65401.74 | J2: 7403.53 | K2: 0 | L2: =[2]Process_results_C1_P1!C2+Shredder!$K$2 | M2: =[2]Process_results_C1_P1!H2+Shredder!$L$2 | N2: =[2]Process_results_C1_P1!I2+Shredder!$M$2 | O2: =[2]Process_results_C1_P1!J2+Shredder!$N$2 | P2: =[2]Process_results_C1_P1!K2+Shredder!$O$2 | Q2: =[2]Process_results_C1_P1!L2+Shredder!$P$2
A3: Wash 1 | B3: PE | C3: Isobutyl Acetate | D3: =[2]Process_results_C1_P1!B3+Shredder!$B$2 | E3: 0 | F3: =L3 | G3: 0 | H3: 994.95 | I3: 64491.6 | J3: 7463.47 | K3: 0 | L3: =[2]Process_results_C1_P1!C3+Shredder!$K$2 | M3: =[2]Process_results_C1_P1!H3+Shredder!$L$2 | N3: =[2]Process_results_C1_P1!I3+Shredder!$M$2 | O3: =[2]Process_results_C1_P1!J3+Shredder!$N$2 | P3: =[2]Process_results_C1_P1!K3+Shredder!$O$2 | Q3: =[2]Process_results_C1_P1!L3+Shredder!$P$2
A4: Wash 1 | B4: PE | C4: Tetrachloroethylene | D4: =[2]Process_results_C1_P1!B4+Shredder!$B$2 | E4: 0 | F4: =L4 | G4: 0 | H4: 683.96 | I4: 38449.65 | J4: 4419.13 | K4: 0 | L4: =[2]Process_results_C1_P1!C4+Shredder!$K$2 | M4: =[2]Process_results_C1_P1!H4+Shredder!$L$2 | N4: =[2]Process_results_C1_P1!I4+Shredder!$M$2 | O4: =[2]Process_results_C1_P1!J4+Shredder!$N$2 | P4: =[2]Process_results_C1_P1!K4+Shredder!$O$2 | Q4: =[2]Process_results_C1_P1!L4+Shredder!$P$2
A5: Wash 1 | B5: PE | C5: o-Chlorotoluene | D5: =[2]Process_results_C1_P1!B5+Shredder!$B$2 | E5: 0 | F5: =L5 | G5: 0 | H5: 1139.79 | I5: 76633.44 | J5: 6319.81 | K5: 0 | L5: =[2]Process_results_C1_P1!C5+Shredder!$K$2 | M5: =[2]Process_results_C1_P1!H5+Shredder!$L$2 | N5: =[2]Process_results_C1_P1!I5+Shredder!$M$2 | O5: =[2]Process_results_C1_P1!J5+Shredder!$N$2 | P5: =[2]Process_results_C1_P1!K5+Shredder!$O$2 | Q5: =[2]Process_results_C1_P1!L5+Shredder!$P$2
A6: Wash 1 | B6: PE | C6: Methylcyclohexane | D6: =[2]Process_results_C1_P1!B6+Shredder!$B$2 | E6: 0 | F6: =L6 | G6: 0 | H6: 887.08 | I6: 55514.4 | J6: 8129.51 | K6: 0 | L6: =[2]Process_results_C1_P1!C6+Shredder!$K$2 | M6: =[2]Process_results_C1_P1!H6+Shredder!$L$2 | N6: =[2]Process_results_C1_P1!I6+Shredder!$M$2 | O6: =[2]Process_results_C1_P1!J6+Shredder!$N$2 | P6: =[2]Process_results_C1_P1!K6+Shredder!$O$2 | Q6: =[2]Process_results_C1_P1!L6+Shredder!$P$2
A7: Wash 1 | B7: PE | C7: Dodecanol | D7: =[2]Process_results_C1_P1!B7+Shredder!$B$2 | E7: 0 | F7: =L7 | G7: 0 | H7: 2487.39 | I7: 187927.49 | J7: 8514.94 | K7: 0 | L7: =[2]Process_results_C1_P1!C7+Shredder!$K$2 | M7: =[2]Process_results_C1_P1!H7+Shredder!$L$2 | N7: =[2]Process_results_C1_P1!I7+Shredder!$M$2 | O7: =[2]Process_results_C1_P1!J7+Shredder!$N$2 | P7: =[2]Process_results_C1_P1!K7+Shredder!$O$2 | Q7: =[2]Process_results_C1_P1!L7+Shredder!$P$2
A8: Wash 1 | B8: PE | C8: Heptane | D8: =[2]Process_results_C1_P1!B8+Shredder!$B$2 | E8: 0 | F8: =L8 | G8: 0 | H8: 920.27 | I8: 58179.21 | J8: 9006.42 | K8: 0 | L8: =[2]Process_results_C1_P1!C8+Shredder!$K$2 | M8: =[2]Process_results_C1_P1!H8+Shredder!$L$2 | N8: =[2]Process_results_C1_P1!I8+Shredder!$M$2 | O8: =[2]Process_results_C1_P1!J8+Shredder!$N$2 | P8: =[2]Process_results_C1_P1!K8+Shredder!$O$2 | Q8: =[2]Process_results_C1_P1!L8+Shredder!$P$2
A9: Wash 1 | B9: PE | C9: Toluene | D9: =[2]Process_results_C1_P1!B9+Shredder!$B$2 | E9: 0 | F9: =L9 | G9: 0 | H9: 1040.73 | I9: 67836.93 | J9: 11871.24 | K9: 0 | L9: =[2]Process_results_C1_P1!C9+Shredder!$K$2 | M9: =[2]Process_results_C1_P1!H9+Shredder!$L$2 | N9: =[2]Process_results_C1_P1!I9+Shredder!$M$2 | O9: =[2]Process_results_C1_P1!J9+Shredder!$N$2 | P9: =[2]Process_results_C1_P1!K9+Shredder!$O$2 | Q9: =[2]Process_results_C1_P1!L9+Shredder!$P$2
A10: Wash 1 | B10: PE | C10: Xylene | D10: =[2]Process_results_C1_P1!B10+Shredder!$B$2 | E10: 0 | F10: =L10 | G10: 0 | H10: 1159.2 | I10: 78331.71 | J10: 7294.56 | K10: 0 | L10: =[2]Process_results_C1_P1!C10+Shredder!$K$2 | M10: =[2]Process_results_C1_P1!H10+Shredder!$L$2 | N10: =[2]Process_results_C1_P1!I10+Shredder!$M$2 | O10: =[2]Process_results_C1_P1!J10+Shredder!$N$2 | P10: =[2]Process_results_C1_P1!K10+Shredder!$O$2 | Q10: =[2]Process_results_C1_P1!L10+Shredder!$P$2
A11: Wash 1 | B11: EVOH | C11: =[3]Process_results_C1_E1!$A$2 | D11: =[3]Process_results_C1_E1!B2+Shredder!$B$2 | E11: 0 | F11: =L11 | G11: 0 | H11: 1512.92 | I11: 125060.56 | J11: 2426.35 | K11: 0 | L11: =[3]Process_results_C1_E1!C2+Shredder!$K$2 | M11: =[3]Process_results_C1_E1!H2+Shredder!$L$2 | N11: =[3]Process_results_C1_E1!I2+Shredder!$M$2 | O11: =[3]Process_results_C1_E1!J2+Shredder!$N$2 | P11: =[3]Process_results_C1_E1!K2+Shredder!$O$2 | Q11: =[3]Process_results_C1_E1!L2+Shredder!$P$2
A12: Wash 1 | B12: EVOH | C12: =[3]Process_results_C1_E1!$A$3 | D12: =[3]Process_results_C1_E1!B3+Shredder!$B$2 | E12: 0 | F12: =L12 | G12: 0 | H12: 964.84 | I12: 76612.87 | J12: 2837.85 | K12: 0 | L12: =[3]Process_results_C1_E1!C3+Shredder!$K$2 | M12: =[3]Process_results_C1_E1!H3+Shredder!$L$2 | N12: =[3]Process_results_C1_E1!I3+Shredder!$M$2 | O12: =[3]Process_results_C1_E1!J3+Shredder!$N$2 | P12: =[3]Process_results_C1_E1!K3+Shredder!$O$2 | Q12: =[3]Process_results_C1_E1!L3+Shredder!$P$2
A13: Wash 2 | B13: PE | C13: sec-Butyl Acetate | D13: 5.02 | E13: 0 | F13: =L13 | G13: 0 | H13: 966.49 | I13: 62262.96 | J13: 7303.6 | K13: 0 | L13: 1.2005329 | M13: 4.5338019e-08 | N13: 2.5078508e-08 | O13: 1.2777775 | P13: 40931215 | Q13: 1047740.1
A14: Wash 2 | B14: PE | C14: Isobutyl Acetate | D14: 5.02 | E14: 0 | F14: =L14 | G14: 0 | H14: 958.02 | I14: 61569.48 | J14: 7363.19 | K14: 0 | L14: 1.196813 | M14: 4.5246416e-08 | N14: 2.5090223e-08 | O14: 1.2774454 | P14: 41185362 | Q14: 1052268.2
A15: Wash 2 | B15: PE | C15: Tetrachloroethylene | D15: 4.8 | E15: 0 | F15: =L15 | G15: 0 | H15: 656.12 | I15: 36362.45 | J15: 4341.89 | K15: 0 | L15: 1.0965103 | M15: 3.9866638e-08 | N15: 2.1764279e-08 | O15: 1.0740143 | P15: 35754823 | Q15: 938269.24
A16: Wash 2 | B16: PE | C16: o-Chlorotoluene | D16: 5.01 | E16: 0 | F16: =L16 | G16: 0 | H16: 1098.51 | I16: 73352.38 | J16: 6226.9 | K16: 0 | L16: 1.2365479 | M16: 4.6334882e-08 | N16: 2.5177552e-08 | O16: 1.2972699 | P16: 39697204 | Q16: 1028423.1
A17: Wash 2 | B17: PE | C17: Methylcyclohexane | D17: 5.01 | E17: 0 | F17: =L17 | G17: 0 | H17: 846.45 | I17: 52253.34 | J17: 8025.78 | K17: 0 | L17: 1.1562855 | M17: 4.2921731e-08 | N17: 2.2988628e-08 | O17: 1.1816403 | P17: 41755740 | Q17: 1059416.7
A18: Wash 2 | B18: PE | C18: Dodecanol | D18: 5.48 | E18: 0 | F18: =L18 | G18: 0 | H18: 2419.67 | I18: 182520.62 | J18: 8405.55 | K18: 0 | L18: 1.7207436 | M18: 6.5314505e-08 | N18: 3.977586e-08 | O18: 1.9967304 | P18: 45094364 | Q18: 1186252
A19: Wash 2 | B19: PE | C19: Heptane | D19: 5.06 | E19: 0 | F19: =L19 | G19: 0 | H19: 880.03 | I19: 54950.96 | J19: 8897.14 | K19: 0 | L19: 1.1688554 | M19: 4.3001802e-08 | N19: 2.2719875e-08 | O19: 1.1656356 | P19: 43208033 | Q19: 1088889.2
A20: Wash 2 | B20: PE | C20: Toluene | D20: 5.18 | E20: 0 | F20: =L20 | G20: 0 | H20: 993.67 | I20: 64056.57 | J20: 11716.23 | K20: 0 | L20: 1.2141233 | M20: 4.5108743e-08 | N20: 2.3876385e-08 | O20: 1.2302914 | P20: 46986127 | Q20: 1179441.8
A21: Wash 2 | B21: PE | C21: Xylene | D21: 5.06 | E21: 0 | F21: =L21 | G21: 0 | H21: 1117.99 | I21: 75028.67 | J21: 7194.85 | K21: 0 | L21: 1.2384899 | M21: 4.5663809e-08 | N21: 2.4004406e-08 | O21: 1.235194 | P21: 41234664 | Q21: 1058246.1
A22: Wash 2 | B22: EVOH | C22: butane-1,4-diol | D22: =[4]Process_results_C1_E2!B2*Shredder!$B$2 | E22: 0 | F22: =L22 | G22: 0 | H22: =[4]Process_results_C1_E2!F2 | I22: =[4]Process_results_C1_E2!G2 | J22: =[4]Process_results_C1_E2!D2 | K22: 0 | L22: =[4]Process_results_C1_E2!C2+Shredder!$K$2 | M22: =[4]Process_results_C1_E2!H2+Shredder!$L$2 | N22: =[4]Process_results_C1_E2!I2+Shredder!$M$2 | O22: =[4]Process_results_C1_E2!J2+Shredder!$N$2 | P22: =[4]Process_results_C1_E2!K2+Shredder!$O$2 | Q22: =[4]Process_results_C1_E2!L2+Shredder!$P$2
A23: Wash 2 | B23: EVOH | C23: Diethanolamine | D23: =[4]Process_results_C1_E2!B3*Shredder!$B$2 | E23: 0 | F23: =L23 | G23: 0 | H23: =[4]Process_results_C1_E2!F3 | I23: =[4]Process_results_C1_E2!G3 | J23: =[4]Process_results_C1_E2!D3 | K23: 0 | L23: =[4]Process_results_C1_E2!C3+Shredder!$K$2 | M23: =[4]Process_results_C1_E2!H3+Shredder!$L$2 | N23: =[4]Process_results_C1_E2!I3+Shredder!$M$2 | O23: =[4]Process_results_C1_E2!J3+Shredder!$N$2 | P23: =[4]Process_results_C1_E2!K3+Shredder!$O$2 | Q23: =[4]Process_results_C1_E2!L3+Shredder!$P$2
A24: Wash 2 | B24: EVOH | C24: Diethylene glycol | D24: =[4]Process_results_C1_E2!B4*Shredder!$B$2 | E24: 0 | F24: =L24 | G24: 0 | H24: =[4]Process_results_C1_E2!F4 | I24: =[4]Process_results_C1_E2!G4 | J24: =[4]Process_results_C1_E2!D4 | K24: 0 | L24: =[4]Process_results_C1_E2!C4+Shredder!$K$2 | M24: =[4]Process_results_C1_E2!H4+Shredder!$L$2 | N24: =[4]Process_results_C1_E2!I4+Shredder!$M$2 | O24: =[4]Process_results_C1_E2!J4+Shredder!$N$2 | P24: =[4]Process_results_C1_E2!K4+Shredder!$O$2 | Q24: =[4]Process_results_C1_E2!L4+Shredder!$P$2
A25: Wash 2 | B25: EVOH | C25: Ethylene Glycol | D25: =[4]Process_results_C1_E2!B5*Shredder!$B$2 | E25: 0 | F25: =L25 | G25: 0 | H25: =[4]Process_results_C1_E2!F5 | I25: =[4]Process_results_C1_E2!G5 | J25: =[4]Process_results_C1_E2!D5 | K25: 0 | L25: =[4]Process_results_C1_E2!C5+Shredder!$K$2 | M25: =[4]Process_results_C1_E2!H5+Shredder!$L$2 | N25: =[4]Process_results_C1_E2!I5+Shredder!$M$2 | O25: =[4]Process_results_C1_E2!J5+Shredder!$N$2 | P25: =[4]Process_results_C1_E2!K5+Shredder!$O$2 | Q25: =[4]Process_results_C1_E2!L5+Shredder!$P$2
A26: Wash 2 | B26: EVOH | C26: Propylene Glycol | D26: =[4]Process_results_C1_E2!B6*Shredder!$B$2 | E26: 0 | F26: =L26 | G26: 0 | H26: =[4]Process_results_C1_E2!F6 | I26: =[4]Process_results_C1_E2!G6 | J26: =[4]Process_results_C1_E2!D6 | K26: 0 | L26: =[4]Process_results_C1_E2!C6+Shredder!$K$2 | M26: =[4]Process_results_C1_E2!H6+Shredder!$L$2 | N26: =[4]Process_results_C1_E2!I6+Shredder!$M$2 | O26: =[4]Process_results_C1_E2!J6+Shredder!$N$2 | P26: =[4]Process_results_C1_E2!K6+Shredder!$O$2 | Q26: =[4]Process_results_C1_E2!L6+Shredder!$P$2
A27: Wash 2 | B27: EVOH | C27: Pyridazine | D27: =[4]Process_results_C1_E2!B7*Shredder!$B$2 | E27: 0 | F27: =L27 | G27: 0 | H27: =[4]Process_results_C1_E2!F7 | I27: =[4]Process_results_C1_E2!G7 | J27: =[4]Process_results_C1_E2!D7 | K27: 0 | L27: =[4]Process_results_C1_E2!C7+Shredder!$K$2 | M27: =[4]Process_results_C1_E2!H7+Shredder!$L$2 | N27: =[4]Process_results_C1_E2!I7+Shredder!$M$2 | O27: =[4]Process_results_C1_E2!J7+Shredder!$N$2 | P27: =[4]Process_results_C1_E2!K7+Shredder!$O$2 | Q27: =[4]Process_results_C1_E2!L7+Shredder!$P$2
A28: Wash 2 | B28: EVOH | C28: gamma-butyrolactone | D28: =[4]Process_results_C1_E2!B8*Shredder!$B$2 | E28: 0 | F28: =L28 | G28: 0 | H28: =[4]Process_results_C1_E2!F8 | I28: =[4]Process_results_C1_E2!G8 | J28: =[4]Process_results_C1_E2!D8 | K28: 0 | L28: =[4]Process_results_C1_E2!C8+Shredder!$K$2 | M28: =[4]Process_results_C1_E2!H8+Shredder!$L$2 | N28: =[4]Process_results_C1_E2!I8+Shredder!$M$2 | O28: =[4]Process_results_C1_E2!J8+Shredder!$N$2 | P28: =[4]Process_results_C1_E2!K8+Shredder!$O$2 | Q28: =[4]Process_results_C1_E2!L8+Shredder!$P$2

Sheet Shared STRAP Scenario Units
A1: Wash number | B1: Polymer | C1: Solvents | D1: Total Energy Consumed [MJ/yr] | E1: Total Renewable Energy Consumed [MJ/yr] | F1: Total Direct GHG emissions [Scope 1] [metric tons CO2 equivalent [tCO2e/yr]] | G1: Total Energy indirect GHG emissions (Scope 2) [metric tons CO2 equivalent (t CO2e/yr)] | H1: Water consumed/discarded [m3/yr] | I1: Water Recycled or Reused [m3/yr] | J1: Waste generated - Non Hazardous [kg/yr] | K1: Waste to Disposal[ton/yr] | L1: GWP [tonCO2e/yr] | M1: Human toxicity cancer [CTUh/yr] | N1: Human toxicity non-cancer [CTUh/yr] | O1: Ecotoxicity [CTUe/yr] | P1: CAPEX [USD/yr] | Q1: OPEX [USD/yr]
A2: Wash 1 | B2: PE | C2: sec-Butyl Acetate | D2: ='Shared STRAP Scenario'!D2*'[1]New UBs'!$E$57 | E2: ='Shared STRAP Scenario'!E2*'[1]New UBs'!$E$57*0.12 | F2: ='Shared STRAP Scenario'!F2*'[1]New UBs'!$E$57/1000 | G2: ='Shared STRAP Scenario'!G2 | H2: ='Shared STRAP Scenario'!H2 | I2: ='Shared STRAP Scenario'!I2 | J2: ='Shared STRAP Scenario'!J2 | K2: ='Shared STRAP Scenario'!K2 | L2: =F2 | M2: ='Shared STRAP Scenario'!M2*'[1]New UBs'!$E$57 | N2: ='Shared STRAP Scenario'!N2*'[1]New UBs'!$E$57 | O2: ='Shared STRAP Scenario'!O2*'[1]New UBs'!$E$57 | P2: ='Shared STRAP Scenario'!P2/20 | Q2: ='Shared STRAP Scenario'!Q2
A3: Wash 1 | B3: PE | C3: Isobutyl Acetate | D3: ='Shared STRAP Scenario'!D3*'[1]New UBs'!$E$57 | E3: ='Shared STRAP Scenario'!E3*'[1]New UBs'!$E$57*0.12 | F3: ='Shared STRAP Scenario'!F3*'[1]New UBs'!$E$57/1000 | G3: ='Shared STRAP Scenario'!G3 | H3: ='Shared STRAP Scenario'!H3 | I3: ='Shared STRAP Scenario'!I3 | J3: ='Shared STRAP Scenario'!J3 | K3: ='Shared STRAP Scenario'!K3 | L3: =F3 | M3: ='Shared STRAP Scenario'!M3*'[1]New UBs'!$E$57 | N3: ='Shared STRAP Scenario'!N3*'[1]New UBs'!$E$57 | O3: ='Shared STRAP Scenario'!O3*'[1]New UBs'!$E$57 | P3: ='Shared STRAP Scenario'!P3/20 | Q3: ='Shared STRAP Scenario'!Q3
A4: Wash 1 | B4: PE | C4: Tetrachloroethylene | D4: ='Shared STRAP Scenario'!D4*'[1]New UBs'!$E$57 | E4: ='Shared STRAP Scenario'!E4*'[1]New UBs'!$E$57*0.12 | F4: ='Shared STRAP Scenario'!F4*'[1]New UBs'!$E$57/1000 | G4: ='Shared STRAP Scenario'!G4 | H4: ='Shared STRAP Scenario'!H4 | I4: ='Shared STRAP Scenario'!I4 | J4: ='Shared STRAP Scenario'!J4 | K4: ='Shared STRAP Scenario'!K4 | L4: =F4 | M4: ='Shared STRAP Scenario'!M4*'[1]New UBs'!$E$57 | N4: ='Shared STRAP Scenario'!N4*'[1]New UBs'!$E$57 | O4: ='Shared STRAP Scenario'!O4*'[1]New UBs'!$E$57 | P4: ='Shared STRAP Scenario'!P4/20 | Q4: ='Shared STRAP Scenario'!Q4
A5: Wash 1 | B5: PE | C5: o-Chlorotoluene | D5: ='Shared STRAP Scenario'!D5*'[1]New UBs'!$E$57 | E5: ='Shared STRAP Scenario'!E5*'[1]New UBs'!$E$57*0.12 | F5: ='Shared STRAP Scenario'!F5*'[1]New UBs'!$E$57/1000 | G5: ='Shared STRAP Scenario'!G5 | H5: ='Shared STRAP Scenario'!H5 | I5: ='Shared STRAP Scenario'!I5 | J5: ='Shared STRAP Scenario'!J5 | K5: ='Shared STRAP Scenario'!K5 | L5: =F5 | M5: ='Shared STRAP Scenario'!M5*'[1]New UBs'!$E$57 | N5: ='Shared STRAP Scenario'!N5*'[1]New UBs'!$E$57 | O5: ='Shared STRAP Scenario'!O5*'[1]New UBs'!$E$57 | P5: ='Shared STRAP Scenario'!P5/20 | Q5: ='Shared STRAP Scenario'!Q5
A6: Wash 1 | B6: PE | C6: Methylcyclohexane | D6: ='Shared STRAP Scenario'!D6*'[1]New UBs'!$E$57 | E6: ='Shared STRAP Scenario'!E6*'[1]New UBs'!$E$57*0.12 | F6: ='Shared STRAP Scenario'!F6*'[1]New UBs'!$E$57/1000 | G6: ='Shared STRAP Scenario'!G6 | H6: ='Shared STRAP Scenario'!H6 | I6: ='Shared STRAP Scenario'!I6 | J6: ='Shared STRAP Scenario'!J6 | K6: ='Shared STRAP Scenario'!K6 | L6: =F6 | M6: ='Shared STRAP Scenario'!M6*'[1]New UBs'!$E$57 | N6: ='Shared STRAP Scenario'!N6*'[1]New UBs'!$E$57 | O6: ='Shared STRAP Scenario'!O6*'[1]New UBs'!$E$57 | P6: ='Shared STRAP Scenario'!P6/20 | Q6: ='Shared STRAP Scenario'!Q6
A7: Wash 1 | B7: PE | C7: Dodecanol | D7: ='Shared STRAP Scenario'!D7*'[1]New UBs'!$E$57 | E7: ='Shared STRAP Scenario'!E7*'[1]New UBs'!$E$57*0.12 | F7: ='Shared STRAP Scenario'!F7*'[1]New UBs'!$E$57/1000 | G7: ='Shared STRAP Scenario'!G7 | H7: ='Shared STRAP Scenario'!H7 | I7: ='Shared STRAP Scenario'!I7 | J7: ='Shared STRAP Scenario'!J7 | K7: ='Shared STRAP Scenario'!K7 | L7: =F7 | M7: ='Shared STRAP Scenario'!M7*'[1]New UBs'!$E$57 | N7: ='Shared STRAP Scenario'!N7*'[1]New UBs'!$E$57 | O7: ='Shared STRAP Scenario'!O7*'[1]New UBs'!$E$57 | P7: ='Shared STRAP Scenario'!P7/20 | Q7: ='Shared STRAP Scenario'!Q7
A8: Wash 1 | B8: PE | C8: Heptane | D8: ='Shared STRAP Scenario'!D8*'[1]New UBs'!$E$57 | E8: ='Shared STRAP Scenario'!E8*'[1]New UBs'!$E$57*0.12 | F8: ='Shared STRAP Scenario'!F8*'[1]New UBs'!$E$57/1000 | G8: ='Shared STRAP Scenario'!G8 | H8: ='Shared STRAP Scenario'!H8 | I8: ='Shared STRAP Scenario'!I8 | J8: ='Shared STRAP Scenario'!J8 | K8: ='Shared STRAP Scenario'!K8 | L8: =F8 | M8: ='Shared STRAP Scenario'!M8*'[1]New UBs'!$E$57 | N8: ='Shared STRAP Scenario'!N8*'[1]New UBs'!$E$57 | O8: ='Shared STRAP Scenario'!O8*'[1]New UBs'!$E$57 | P8: ='Shared STRAP Scenario'!P8/20 | Q8: ='Shared STRAP Scenario'!Q8
A9: Wash 1 | B9: PE | C9: Toluene | D9: ='Shared STRAP Scenario'!D9*'[1]New UBs'!$E$57 | E9: ='Shared STRAP Scenario'!E9*'[1]New UBs'!$E$57*0.12 | F9: ='Shared STRAP Scenario'!F9*'[1]New UBs'!$E$57/1000 | G9: ='Shared STRAP Scenario'!G9 | H9: ='Shared STRAP Scenario'!H9 | I9: ='Shared STRAP Scenario'!I9 | J9: ='Shared STRAP Scenario'!J9 | K9: ='Shared STRAP Scenario'!K9 | L9: =F9 | M9: ='Shared STRAP Scenario'!M9*'[1]New UBs'!$E$57 | N9: ='Shared STRAP Scenario'!N9*'[1]New UBs'!$E$57 | O9: ='Shared STRAP Scenario'!O9*'[1]New UBs'!$E$57 | P9: ='Shared STRAP Scenario'!P9/20 | Q9: ='Shared STRAP Scenario'!Q9
A10: Wash 1 | B10: PE | C10: Xylene | D10: ='Shared STRAP Scenario'!D10*'[1]New UBs'!$E$57 | E10: ='Shared STRAP Scenario'!E10*'[1]New UBs'!$E$57*0.12 | F10: ='Shared STRAP Scenario'!F10*'[1]New UBs'!$E$57/1000 | G10: ='Shared STRAP Scenario'!G10 | H10: ='Shared STRAP Scenario'!H10 | I10: ='Shared STRAP Scenario'!I10 | J10: ='Shared STRAP Scenario'!J10 | K10: ='Shared STRAP Scenario'!K10 | L10: =F10 | M10: ='Shared STRAP Scenario'!M10*'[1]New UBs'!$E$57 | N10: ='Shared STRAP Scenario'!N10*'[1]New UBs'!$E$57 | O10: ='Shared STRAP Scenario'!O10*'[1]New UBs'!$E$57 | P10: ='Shared STRAP Scenario'!P10/20 | Q10: ='Shared STRAP Scenario'!Q10
A11: Wash 1 | B11: EVOH | C11: =[5]Process_results_C2_E1!$A$2 | D11: ='Shared STRAP Scenario'!D11*'[1]New UBs'!$E$58 | E11: ='Shared STRAP Scenario'!E11*'[1]New UBs'!$E$58*0.12 | F11: ='Shared STRAP Scenario'!F11*'[1]New UBs'!$E$58/1000 | G11: ='Shared STRAP Scenario'!G11 | H11: ='Shared STRAP Scenario'!H11 | I11: ='Shared STRAP Scenario'!I11 | J11: ='Shared STRAP Scenario'!J11 | K11: ='Shared STRAP Scenario'!K11 | L11: =F11 | M11: ='Shared STRAP Scenario'!M11*'[1]New UBs'!$E$58 | N11: ='Shared STRAP Scenario'!N11*'[1]New UBs'!$E$58 | O11: ='Shared STRAP Scenario'!O11*'[1]New UBs'!$E$58 | P11: ='Shared STRAP Scenario'!P11/20 | Q11: ='Shared STRAP Scenario'!Q11
A12: Wash 1 | B12: EVOH | C12: Pyridazine | D12: ='Shared STRAP Scenario'!D12*'[1]New UBs'!$E$58 | E12: ='Shared STRAP Scenario'!E12*'[1]New UBs'!$E$58*0.12 | F12: ='Shared STRAP Scenario'!F12*'[1]New UBs'!$E$58/1000 | G12: ='Shared STRAP Scenario'!G12 | H12: ='Shared STRAP Scenario'!H12 | I12: ='Shared STRAP Scenario'!I12 | J12: ='Shared STRAP Scenario'!J12 | K12: ='Shared STRAP Scenario'!K12 | L12: =F12 | M12: ='Shared STRAP Scenario'!M12*'[1]New UBs'!$E$58 | N12: ='Shared STRAP Scenario'!N12*'[1]New UBs'!$E$58 | O12: ='Shared STRAP Scenario'!O12*'[1]New UBs'!$E$58 | P12: ='Shared STRAP Scenario'!P12/20 | Q12: ='Shared STRAP Scenario'!Q12
A13: Wash 2 | B13: PE | C13: sec-Butyl Acetate | D13: ='Shared STRAP Scenario'!D13*'[1]New UBs'!$J$58 | E13: ='Shared STRAP Scenario'!E13*'[1]New UBs'!$J$58*0.12 | F13: ='Shared STRAP Scenario'!F13*'[1]New UBs'!$J$58/1000 | G13: ='Shared STRAP Scenario'!G13 | H13: ='Shared STRAP Scenario'!H13 | I13: ='Shared STRAP Scenario'!I13 | J13: ='Shared STRAP Scenario'!J13 | K13: ='Shared STRAP Scenario'!K13 | L13: =F13 | M13: ='Shared STRAP Scenario'!M13*'[1]New UBs'!$J$58 | N13: ='Shared STRAP Scenario'!N13*'[1]New UBs'!$J$58 | O13: ='Shared STRAP Scenario'!O13*'[1]New UBs'!$J$58 | P13: ='Shared STRAP Scenario'!P13/20 | Q13: ='Shared STRAP Scenario'!Q13
A14: Wash 2 | B14: PE | C14: Isobutyl Acetate | D14: ='Shared STRAP Scenario'!D14*'[1]New UBs'!$J$58 | E14: ='Shared STRAP Scenario'!E14*'[1]New UBs'!$J$58*0.12 | F14: ='Shared STRAP Scenario'!F14*'[1]New UBs'!$J$58/1000 | G14: ='Shared STRAP Scenario'!G14 | H14: ='Shared STRAP Scenario'!H14 | I14: ='Shared STRAP Scenario'!I14 | J14: ='Shared STRAP Scenario'!J14 | K14: ='Shared STRAP Scenario'!K14 | L14: =F14 | M14: ='Shared STRAP Scenario'!M14*'[1]New UBs'!$J$58 | N14: ='Shared STRAP Scenario'!N14*'[1]New UBs'!$J$58 | O14: ='Shared STRAP Scenario'!O14*'[1]New UBs'!$J$58 | P14: ='Shared STRAP Scenario'!P14/20 | Q14: ='Shared STRAP Scenario'!Q14
A15: Wash 2 | B15: PE | C15: Tetrachloroethylene | D15: ='Shared STRAP Scenario'!D15*'[1]New UBs'!$J$58 | E15: ='Shared STRAP Scenario'!E15*'[1]New UBs'!$J$58*0.12 | F15: ='Shared STRAP Scenario'!F15*'[1]New UBs'!$J$58/1000 | G15: ='Shared STRAP Scenario'!G15 | H15: ='Shared STRAP Scenario'!H15 | I15: ='Shared STRAP Scenario'!I15 | J15: ='Shared STRAP Scenario'!J15 | K15: ='Shared STRAP Scenario'!K15 | L15: =F15 | M15: ='Shared STRAP Scenario'!M15*'[1]New UBs'!$J$58 | N15: ='Shared STRAP Scenario'!N15*'[1]New UBs'!$J$58 | O15: ='Shared STRAP Scenario'!O15*'[1]New UBs'!$J$58 | P15: ='Shared STRAP Scenario'!P15/20 | Q15: ='Shared STRAP Scenario'!Q15
A16: Wash 2 | B16: PE | C16: o-Chlorotoluene | D16: ='Shared STRAP Scenario'!D16*'[1]New UBs'!$J$58 | E16: ='Shared STRAP Scenario'!E16*'[1]New UBs'!$J$58*0.12 | F16: ='Shared STRAP Scenario'!F16*'[1]New UBs'!$J$58/1000 | G16: ='Shared STRAP Scenario'!G16 | H16: ='Shared STRAP Scenario'!H16 | I16: ='Shared STRAP Scenario'!I16 | J16: ='Shared STRAP Scenario'!J16 | K16: ='Shared STRAP Scenario'!K16 | L16: =F16 | M16: ='Shared STRAP Scenario'!M16*'[1]New UBs'!$J$58 | N16: ='Shared STRAP Scenario'!N16*'[1]New UBs'!$J$58 | O16: ='Shared STRAP Scenario'!O16*'[1]New UBs'!$J$58 | P16: ='Shared STRAP Scenario'!P16/20 | Q16: ='Shared STRAP Scenario'!Q16
A17: Wash 2 | B17: PE | C17: Methylcyclohexane | D17: ='Shared STRAP Scenario'!D17*'[1]New UBs'!$J$58 | E17: ='Shared STRAP Scenario'!E17*'[1]New UBs'!$J$58*0.12 | F17: ='Shared STRAP Scenario'!F17*'[1]New UBs'!$J$58/1000 | G17: ='Shared STRAP Scenario'!G17 | H17: ='Shared STRAP Scenario'!H17 | I17: ='Shared STRAP Scenario'!I17 | J17: ='Shared STRAP Scenario'!J17 | K17: ='Shared STRAP Scenario'!K17 | L17: =F17 | M17: ='Shared STRAP Scenario'!M17*'[1]New UBs'!$J$58 | N17: ='Shared STRAP Scenario'!N17*'[1]New UBs'!$J$58 | O17: ='Shared STRAP Scenario'!O17*'[1]New UBs'!$J$58 | P17: ='Shared STRAP Scenario'!P17/20 | Q17: ='Shared STRAP Scenario'!Q17
A18: Wash 2 | B18: PE | C18: Dodecanol | D18: ='Shared STRAP Scenario'!D18*'[1]New UBs'!$J$58 | E18: ='Shared STRAP Scenario'!E18*'[1]New UBs'!$J$58*0.12 | F18: ='Shared STRAP Scenario'!F18*'[1]New UBs'!$J$58/1000 | G18: ='Shared STRAP Scenario'!G18 | H18: ='Shared STRAP Scenario'!H18 | I18: ='Shared STRAP Scenario'!I18 | J18: ='Shared STRAP Scenario'!J18 | K18: ='Shared STRAP Scenario'!K18 | L18: =F18 | M18: ='Shared STRAP Scenario'!M18*'[1]New UBs'!$J$58 | N18: ='Shared STRAP Scenario'!N18*'[1]New UBs'!$J$58 | O18: ='Shared STRAP Scenario'!O18*'[1]New UBs'!$J$58 | P18: ='Shared STRAP Scenario'!P18/20 | Q18: ='Shared STRAP Scenario'!Q18
A19: Wash 2 | B19: PE | C19: Heptane | D19: ='Shared STRAP Scenario'!D19*'[1]New UBs'!$J$58 | E19: ='Shared STRAP Scenario'!E19*'[1]New UBs'!$J$58*0.12 | F19: ='Shared STRAP Scenario'!F19*'[1]New UBs'!$J$58/1000 | G19: ='Shared STRAP Scenario'!G19 | H19: ='Shared STRAP Scenario'!H19 | I19: ='Shared STRAP Scenario'!I19 | J19: ='Shared STRAP Scenario'!J19 | K19: ='Shared STRAP Scenario'!K19 | L19: =F19 | M19: ='Shared STRAP Scenario'!M19*'[1]New UBs'!$J$58 | N19: ='Shared STRAP Scenario'!N19*'[1]New UBs'!$J$58 | O19: ='Shared STRAP Scenario'!O19*'[1]New UBs'!$J$58 | P19: ='Shared STRAP Scenario'!P19/20 | Q19: ='Shared STRAP Scenario'!Q19
A20: Wash 2 | B20: PE | C20: Toluene | D20: ='Shared STRAP Scenario'!D20*'[1]New UBs'!$J$58 | E20: ='Shared STRAP Scenario'!E20*'[1]New UBs'!$J$58*0.12 | F20: ='Shared STRAP Scenario'!F20*'[1]New UBs'!$J$58/1000 | G20: ='Shared STRAP Scenario'!G20 | H20: ='Shared STRAP Scenario'!H20 | I20: ='Shared STRAP Scenario'!I20 | J20: ='Shared STRAP Scenario'!J20 | K20: ='Shared STRAP Scenario'!K20 | L20: =F20 | M20: ='Shared STRAP Scenario'!M20*'[1]New UBs'!$J$58 | N20: ='Shared STRAP Scenario'!N20*'[1]New UBs'!$J$58 | O20: ='Shared STRAP Scenario'!O20*'[1]New UBs'!$J$58 | P20: ='Shared STRAP Scenario'!P20/20 | Q20: ='Shared STRAP Scenario'!Q20
A21: Wash 2 | B21: PE | C21: Xylene | D21: ='Shared STRAP Scenario'!D21*'[1]New UBs'!$J$58 | E21: ='Shared STRAP Scenario'!E21*'[1]New UBs'!$J$58*0.12 | F21: ='Shared STRAP Scenario'!F21*'[1]New UBs'!$J$58/1000 | G21: ='Shared STRAP Scenario'!G21 | H21: ='Shared STRAP Scenario'!H21 | I21: ='Shared STRAP Scenario'!I21 | J21: ='Shared STRAP Scenario'!J21 | K21: ='Shared STRAP Scenario'!K21 | L21: =F21 | M21: ='Shared STRAP Scenario'!M21*'[1]New UBs'!$J$58 | N21: ='Shared STRAP Scenario'!N21*'[1]New UBs'!$J$58 | O21: ='Shared STRAP Scenario'!O21*'[1]New UBs'!$J$58 | P21: ='Shared STRAP Scenario'!P21/20 | Q21: ='Shared STRAP Scenario'!Q21
A22: Wash 2 | B22: EVOH | C22: butane-1,4-diol | D22: ='Shared STRAP Scenario'!D22*'[1]New UBs'!$J$57 | E22: ='Shared STRAP Scenario'!E22*'[1]New UBs'!$J$57*0.12 | F22: ='Shared STRAP Scenario'!F22*'[1]New UBs'!$J$57/1000 | G22: ='Shared STRAP Scenario'!G22 | H22: ='Shared STRAP Scenario'!H22 | I22: ='Shared STRAP Scenario'!I22 | J22: ='Shared STRAP Scenario'!J22 | K22: ='Shared STRAP Scenario'!K22 | L22: =F22 | M22: ='Shared STRAP Scenario'!M22*'[1]New UBs'!$J$57 | N22: ='Shared STRAP Scenario'!N22*'[1]New UBs'!$J$57 | O22: ='Shared STRAP Scenario'!O22*'[1]New UBs'!$J$57 | P22: ='Shared STRAP Scenario'!P22/20 | Q22: ='Shared STRAP Scenario'!Q22
A23: Wash 2 | B23: EVOH | C23: Diethanolamine | D23: ='Shared STRAP Scenario'!D23*'[1]New UBs'!$J$57 | E23: ='Shared STRAP Scenario'!E23*'[1]New UBs'!$J$57*0.12 | F23: ='Shared STRAP Scenario'!F23*'[1]New UBs'!$J$57/1000 | G23: ='Shared STRAP Scenario'!G23 | H23: ='Shared STRAP Scenario'!H23 | I23: ='Shared STRAP Scenario'!I23 | J23: ='Shared STRAP Scenario'!J23 | K23: ='Shared STRAP Scenario'!K23 | L23: =F23 | M23: ='Shared STRAP Scenario'!M23*'[1]New UBs'!$J$57 | N23: ='Shared STRAP Scenario'!N23*'[1]New UBs'!$J$57 | O23: ='Shared STRAP Scenario'!O23*'[1]New UBs'!$J$57 | P23: ='Shared STRAP Scenario'!P23/20 | Q23: ='Shared STRAP Scenario'!Q23
A24: Wash 2 | B24: EVOH | C24: Diethylene glycol | D24: ='Shared STRAP Scenario'!D24*'[1]New UBs'!$J$57 | E24: ='Shared STRAP Scenario'!E24*'[1]New UBs'!$J$57*0.12 | F24: ='Shared STRAP Scenario'!F24*'[1]New UBs'!$J$57/1000 | G24: ='Shared STRAP Scenario'!G24 | H24: ='Shared STRAP Scenario'!H24 | I24: ='Shared STRAP Scenario'!I24 | J24: ='Shared STRAP Scenario'!J24 | K24: ='Shared STRAP Scenario'!K24 | L24: =F24 | M24: ='Shared STRAP Scenario'!M24*'[1]New UBs'!$J$57 | N24: ='Shared STRAP Scenario'!N24*'[1]New UBs'!$J$57 | O24: ='Shared STRAP Scenario'!O24*'[1]New UBs'!$J$57 | P24: ='Shared STRAP Scenario'!P24/20 | Q24: ='Shared STRAP Scenario'!Q24
A25: Wash 2 | B25: EVOH | C25: Ethylene Glycol | D25: ='Shared STRAP Scenario'!D25*'[1]New UBs'!$J$57 | E25: ='Shared STRAP Scenario'!E25*'[1]New UBs'!$J$57*0.12 | F25: ='Shared STRAP Scenario'!F25*'[1]New UBs'!$J$57/1000 | G25: ='Shared STRAP Scenario'!G25 | H25: ='Shared STRAP Scenario'!H25 | I25: ='Shared STRAP Scenario'!I25 | J25: ='Shared STRAP Scenario'!J25 | K25: ='Shared STRAP Scenario'!K25 | L25: =F25 | M25: ='Shared STRAP Scenario'!M25*'[1]New UBs'!$J$57 | N25: ='Shared STRAP Scenario'!N25*'[1]New UBs'!$J$57 | O25: ='Shared STRAP Scenario'!O25*'[1]New UBs'!$J$57 | P25: ='Shared STRAP Scenario'!P25/20 | Q25: ='Shared STRAP Scenario'!Q25
A26: Wash 2 | B26: EVOH | C26: Propylene Glycol | D26: ='Shared STRAP Scenario'!D26*'[1]New UBs'!$J$57 | E26: ='Shared STRAP Scenario'!E26*'[1]New UBs'!$J$57*0.12 | F26: ='Shared STRAP Scenario'!F26*'[1]New UBs'!$J$57/1000 | G26: ='Shared STRAP Scenario'!G26 | H26: ='Shared STRAP Scenario'!H26 | I26: ='Shared STRAP Scenario'!I26 | J26: ='Shared STRAP Scenario'!J26 | K26: ='Shared STRAP Scenario'!K26 | L26: =F26 | M26: ='Shared STRAP Scenario'!M26*'[1]New UBs'!$J$57 | N26: ='Shared STRAP Scenario'!N26*'[1]New UBs'!$J$57 | O26: ='Shared STRAP Scenario'!O26*'[1]New UBs'!$J$57 | P26: ='Shared STRAP Scenario'!P26/20 | Q26: ='Shared STRAP Scenario'!Q26
A27: Wash 2 | B27: EVOH | C27: Pyridazine | D27: ='Shared STRAP Scenario'!D27*'[1]New UBs'!$J$57 | E27: ='Shared STRAP Scenario'!E27*'[1]New UBs'!$J$57*0.12 | F27: ='Shared STRAP Scenario'!F27*'[1]New UBs'!$J$57/1000 | G27: ='Shared STRAP Scenario'!G27 | H27: ='Shared STRAP Scenario'!H27 | I27: ='Shared STRAP Scenario'!I27 | J27: ='Shared STRAP Scenario'!J27 | K27: ='Shared STRAP Scenario'!K27 | L27: =F27 | M27: ='Shared STRAP Scenario'!M27*'[1]New UBs'!$J$57 | N27: ='Shared STRAP Scenario'!N27*'[1]New UBs'!$J$57 | O27: ='Shared STRAP Scenario'!O27*'[1]New UBs'!$J$57 | P27: ='Shared STRAP Scenario'!P27/20 | Q27: ='Shared STRAP Scenario'!Q27
A28: Wash 2 | B28: EVOH | C28: gamma-butyrolactone | D28: ='Shared STRAP Scenario'!D28*'[1]New UBs'!$J$57 | E28: ='Shared STRAP Scenario'!E28*'[1]New UBs'!$J$57*0.12 | F28: ='Shared STRAP Scenario'!F28*'[1]New UBs'!$J$57/1000 | G28: ='Shared STRAP Scenario'!G28 | H28: ='Shared STRAP Scenario'!H28 | I28: ='Shared STRAP Scenario'!I28 | J28: ='Shared STRAP Scenario'!J28 | K28: ='Shared STRAP Scenario'!K28 | L28: =F28 | M28: ='Shared STRAP Scenario'!M28*'[1]New UBs'!$J$57 | N28: ='Shared STRAP Scenario'!N28*'[1]New UBs'!$J$57 | O28: ='Shared STRAP Scenario'!O28*'[1]New UBs'!$J$57 | P28: ='Shared STRAP Scenario'!P28/20 | Q28: ='Shared STRAP Scenario'!Q28

Sheet Shared STRAP Scenario
A1: Wash number | B1: ='[1]Final Data (use this)'!C11 | C1: ='[1]Final Data (use this)'!D11 | D1: Total Energy Consumed [MJ/kg resin produced ] | E1: Total Electricity [MJ/kg resin] | F1: Total Direct GHG emissions [Scope 1] [metric tons CO2 equivalent [tCO2e/ton]] | G1: Total Energy indirect GHG emissions (Scope 2) [metric tons CO2 equivalent (t CO2e)] | H1: Water consumed/discarded [m3/yr] | I1: Water Recycled or Reused [m3/yr] | J1: Waste generated - Non Hazardous [kg/yr] | K1: Waste to Disposal[ton/ton] | L1: GWP [tonCO2e/ton resin] | M1: Human toxicity cancer [CTUh/kg resin] | N1: Human toxicity non-cancer [CTUh/kg resin] | O1: Ecotoxicity [CTUe/kg resin] | P1: CAPEX [USD] | Q1: OPEX [USD/yr]
A2: Wash 1 | B2: PE | C2: sec-Butyl Acetate | D2: =[6]Process_results20_C2_P1!B2+[7]Process_results_shredderC2!$B$2 | E2: =[6]Process_results20_C2_P1!C2+[7]Process_results_shredderC2!$C$2 | F2: =[6]Process_results20_C2_P1!D2+[7]Process_results_shredderC2!$D$2 | G2: 0 | H2: 1383.74 | I2: 125794.99 | J2: 18508.81 | K2: 0 | L2: =F2 | M2: =[6]Process_results20_C2_P1!$I$2+[7]Process_results_shredderC2!$E$2 | N2: =[6]Process_results20_C2_P1!$J$2+[7]Process_results_shredderC2!$F$2 | O2: =[6]Process_results20_C2_P1!$K$2+[7]Process_results_shredderC2!$G$2 | P2: =[6]Process_results20_C2_P1!$L$2+[7]Process_results_shredderC2!$H$2 | Q2: =[6]Process_results20_C2_P1!$M$2+[7]Process_results_shredderC2!$I$2
A3: Wash 1 | B3: PE | C3: Isobutyl Acetate | D3: =[6]Process_results20_C2_P1!B3+[7]Process_results_shredderC2!$B$2 | E3: =[6]Process_results20_C2_P1!C3+[7]Process_results_shredderC2!$C$2 | F3: =[6]Process_results20_C2_P1!D3+[7]Process_results_shredderC2!$D$2 | G3: 0 | H3: 1360.23 | I3: 123657.44 | J3: 18658.68 | K3: 0 | L3: =F3 | M3: =[6]Process_results20_C2_P1!$I$2+[7]Process_results_shredderC2!$E$2 | N3: =[6]Process_results20_C2_P1!$J$2+[7]Process_results_shredderC2!$F$2 | O3: =[6]Process_results20_C2_P1!$K$2+[7]Process_results_shredderC2!$G$2 | P3: =[6]Process_results20_C2_P1!$L$2+[7]Process_results_shredderC2!$H$2 | Q3: =[6]Process_results20_C2_P1!$M$2+[7]Process_results_shredderC2!$I$2
A4: Wash 1 | B4: PE | C4: Tetrachloroethylene | D4: =[6]Process_results20_C2_P1!B4+[7]Process_results_shredderC2!$B$2 | E4: =[6]Process_results20_C2_P1!C4+[7]Process_results_shredderC2!$C$2 | F4: =[6]Process_results20_C2_P1!D4+[7]Process_results_shredderC2!$D$2 | G4: 0 | H4: 679.58 | I4: 61779.89 | J4: 11047.83 | K4: 0 | L4: =F4 | M4: =[6]Process_results20_C2_P1!$I$2+[7]Process_results_shredderC2!$E$2 | N4: =[6]Process_results20_C2_P1!$J$2+[7]Process_results_shredderC2!$F$2 | O4: =[6]Process_results20_C2_P1!$K$2+[7]Process_results_shredderC2!$G$2 | P4: =[6]Process_results20_C2_P1!$L$2+[7]Process_results_shredderC2!$H$2 | Q4: =[6]Process_results20_C2_P1!$M$2+[7]Process_results_shredderC2!$I$2
A5: Wash 1 | B5: PE | C5: o-Chlorotoluene | D5: =[6]Process_results20_C2_P1!B5+[7]Process_results_shredderC2!$B$2 | E5: =[6]Process_results20_C2_P1!C5+[7]Process_results_shredderC2!$C$2 | F5: =[6]Process_results20_C2_P1!D5+[7]Process_results_shredderC2!$D$2 | G5: 0 | H5: 1677.81 | I5: 152528.39 | J5: 15799.53 | K5: 0 | L5: =F5 | M5: =[6]Process_results20_C2_P1!$I$2+[7]Process_results_shredderC2!$E$2 | N5: =[6]Process_results20_C2_P1!$J$2+[7]Process_results_shredderC2!$F$2 | O5: =[6]Process_results20_C2_P1!$K$2+[7]Process_results_shredderC2!$G$2 | P5: =[6]Process_results20_C2_P1!$L$2+[7]Process_results_shredderC2!$H$2 | Q5: =[6]Process_results20_C2_P1!$M$2+[7]Process_results_shredderC2!$I$2
A6: Wash 1 | B6: PE | C6: Methylcyclohexane | D6: =[6]Process_results20_C2_P1!B6+[7]Process_results_shredderC2!$B$2 | E6: =[6]Process_results20_C2_P1!C6+[7]Process_results_shredderC2!$C$2 | F6: =[6]Process_results20_C2_P1!D6+[7]Process_results_shredderC2!$D$2 | G6: 0 | H6: 1126.57 | I6: 102415.18 | J6: 20323.77 | K6: 0 | L6: =F6 | M6: =[6]Process_results20_C2_P1!$I$2+[7]Process_results_shredderC2!$E$2 | N6: =[6]Process_results20_C2_P1!$J$2+[7]Process_results_shredderC2!$F$2 | O6: =[6]Process_results20_C2_P1!$K$2+[7]Process_results_shredderC2!$G$2 | P6: =[6]Process_results20_C2_P1!$L$2+[7]Process_results_shredderC2!$H$2 | Q6: =[6]Process_results20_C2_P1!$M$2+[7]Process_results_shredderC2!$I$2
A7: Wash 1 | B7: PE | C7: Dodecanol | D7: =[6]Process_results20_C2_P1!B7+[7]Process_results_shredderC2!$B$2 | E7: =[6]Process_results20_C2_P1!C7+[7]Process_results_shredderC2!$C$2 | F7: =[6]Process_results20_C2_P1!D7+[7]Process_results_shredderC2!$D$2 | G7: 0 | H7: 4559.84 | I7: 414531.28 | J7: 21287.35 | K7: 0 | L7: =F7 | M7: =[6]Process_results20_C2_P1!$I$2+[7]Process_results_shredderC2!$E$2 | N7: =[6]Process_results20_C2_P1!$J$2+[7]Process_results_shredderC2!$F$2 | O7: =[6]Process_results20_C2_P1!$K$2+[7]Process_results_shredderC2!$G$2 | P7: =[6]Process_results20_C2_P1!$L$2+[7]Process_results_shredderC2!$H$2 | Q7: =[6]Process_results20_C2_P1!$M$2+[7]Process_results_shredderC2!$I$2
A8: Wash 1 | B8: PE | C8: Heptane | D8: =[6]Process_results20_C2_P1!B8+[7]Process_results_shredderC2!$B$2 | E8: =[6]Process_results20_C2_P1!C8+[7]Process_results_shredderC2!$C$2 | F8: =[6]Process_results20_C2_P1!D8+[7]Process_results_shredderC2!$D$2 | G8: 0 | H8: 1194.23 | I8: 108566.55 | J8: 22516.04 | K8: 0 | L8: =F8 | M8: =[6]Process_results20_C2_P1!$I$2+[7]Process_results_shredderC2!$E$2 | N8: =[6]Process_results20_C2_P1!$J$2+[7]Process_results_shredderC2!$F$2 | O8: =[6]Process_results20_C2_P1!$K$2+[7]Process_results_shredderC2!$G$2 | P8: =[6]Process_results20_C2_P1!$L$2+[7]Process_results_shredderC2!$H$2 | Q8: =[6]Process_results20_C2_P1!$M$2+[7]Process_results_shredderC2!$I$2
A9: Wash 1 | B9: PE | C9: Toluene | D9: =[6]Process_results20_C2_P1!B9+[7]Process_results_shredderC2!$B$2 | E9: =[6]Process_results20_C2_P1!C9+[7]Process_results_shredderC2!$C$2 | F9: =[6]Process_results20_C2_P1!D9+[7]Process_results_shredderC2!$D$2 | G9: 0 | H9: 1439.23 | I9: 130838.78 | J9: 29678.1 | K9: 0 | L9: =F9 | M9: =[6]Process_results20_C2_P1!$I$2+[7]Process_results_shredderC2!$E$2 | N9: =[6]Process_results20_C2_P1!$J$2+[7]Process_results_shredderC2!$F$2 | O9: =[6]Process_results20_C2_P1!$K$2+[7]Process_results_shredderC2!$G$2 | P9: =[6]Process_results20_C2_P1!$L$2+[7]Process_results_shredderC2!$H$2 | Q9: =[6]Process_results20_C2_P1!$M$2+[7]Process_results_shredderC2!$I$2
A10: Wash 1 | B10: PE | C10: Xylene | D10: =[6]Process_results20_C2_P1!B10+[7]Process_results_shredderC2!$B$2 | E10: =[6]Process_results20_C2_P1!C10+[7]Process_results_shredderC2!$C$2 | F10: =[6]Process_results20_C2_P1!D10+[7]Process_results_shredderC2!$D$2 | G10: 0 | H10: 1723.46 | I10: 156677.84 | J10: 18236.41 | K10: 0 | L10: =F10 | M10: =[6]Process_results20_C2_P1!$I$2+[7]Process_results_shredderC2!$E$2 | N10: =[6]Process_results20_C2_P1!$J$2+[7]Process_results_shredderC2!$F$2 | O10: =[6]Process_results20_C2_P1!$K$2+[7]Process_results_shredderC2!$G$2 | P10: =[6]Process_results20_C2_P1!$L$2+[7]Process_results_shredderC2!$H$2 | Q10: =[6]Process_results20_C2_P1!$M$2+[7]Process_results_shredderC2!$I$2
A11: Wash 1 | B11: EVOH | C11: =[5]Process_results_C2_E1!$A$2 | D11: =[8]Process_results20_C2_E1!B2+[7]Process_results_shredderC2!$B$2 | E11: =[8]Process_results20_C2_E1!C2+[7]Process_results_shredderC2!$C$2 | F11: =[8]Process_results20_C2_E1!D2+[7]Process_results_shredderC2!$D$2 | G11: 0 | H11: 3240.51 | I11: 294592.24 | J11: 6065.88 | K11: 0 | L11: =F11 | M11: =[8]Process_results20_C2_E1!I2+[7]Process_results_shredderC2!$E$2 | N11: =[8]Process_results20_C2_E1!J2+[7]Process_results_shredderC2!$F$2 | O11: =[8]Process_results20_C2_E1!K2+[7]Process_results_shredderC2!$G$2 | P11: =[8]Process_results20_C2_E1!L2+[7]Process_results_shredderC2!$H$2 | Q11: =[8]Process_results20_C2_E1!M2+[7]Process_results_shredderC2!$I$2
A12: Wash 1 | B12: EVOH | C12: Pyridazine | D12: =[8]Process_results20_C2_E1!B3+[7]Process_results_shredderC2!$B$2 | E12: =[8]Process_results20_C2_E1!C3+[7]Process_results_shredderC2!$C$2 | F12: =[8]Process_results20_C2_E1!D3+[7]Process_results_shredderC2!$D$2 | G12: 0 | H12: 1930.13 | I12: 175466.5 | J12: 7094.61 | K12: 0 | L12: =F12 | M12: =[8]Process_results20_C2_E1!I3+[7]Process_results_shredderC2!$E$2 | N12: =[8]Process_results20_C2_E1!J3+[7]Process_results_shredderC2!$F$2 | O12: =[8]Process_results20_C2_E1!K3+[7]Process_results_shredderC2!$G$2 | P12: =[8]Process_results20_C2_E1!L3+[7]Process_results_shredderC2!$H$2 | Q12: =[8]Process_results20_C2_E1!M3+[7]Process_results_shredderC2!$I$2
A13: Wash 2 | B13: PE | C13: sec-Butyl Acetate | D13: 4.83 | E13: 4.01 | F13: 0.93257406 | G13: 0 | H13: 1304.65 | I13: 118604.5 | J13: 18259 | K13: 0 | L13: =F13 | M13: 2.93e-08 | N13: 9.83e-07 | O13: 21.283545 | P13: 51247983 | Q13: 2365869.4
A14: Wash 2 | B14: PE | C14: Isobutyl Acetate | D14: 4.81 | E14: 4.01 | F14: 0.93078611 | G14: 0 | H14: 1286.81 | I14: 116982.78 | J14: 18407.97 | K14: 0 | L14: =F14 | M14: 2.89e-08 | N14: 9.84e-07 | O14: 21.297057 | P14: 51606554 | Q14: 2372999
A15: Wash 2 | B15: PE | C15: Tetrachloroethylene | D15: 4.26 | E15: 3.84 | F15: 0.86331611 | G15: 0 | H15: 629.24 | I15: 57203.79 | J15: 10854.73 | K15: 0 | L15: =F15 | M15: 2.03e-08 | N15: 9.41e-07 | O15: 20.235953 | P15: 41748489 | Q15: 2138088.3
A16: Wash 2 | B16: PE | C16: o-Chlorotoluene | D16: 5.07 | E16: 4 | F16: 0.94829341 | G16: 0 | H16: 1595.09 | I16: 145008.63 | J16: 15567.25 | K16: 0 | L16: =F16 | M16: 3.3e-08 | N16: 9.81e-07 | O16: 21.26534 | P16: 48176166 | Q16: 2309225.7
A17: Wash 2 | B17: PE | C17: Methylcyclohexane | D17: 4.59 | E17: 4 | F17: 0.90727707 | G17: 0 | H17: 1043.76 | I17: 94887.58 | J17: 20064.46 | K17: 0 | L17: =F17 | M17: 2.44e-08 | N17: 9.81e-07 | O17: 21.161669 | P17: 53369264 | Q17: 2401793.1
A18: Wash 2 | B18: PE | C18: Dodecanol | D18: 7.9 | E18: 4.37 | F18: 1.2321448 | G18: 0 | H18: 4423.08 | I18: 402098.17 | J18: 21013.87 | K18: 0 | L18: =F18 | M18: 7.66e-08 | N18: 1.08e-06 | O18: 23.839876 | P18: 55246416 | Q18: 2604628.9
A19: Wash 2 | B19: PE | C19: Heptane | D19: 4.68 | E19: 4.04 | F19: 0.91602653 | G19: 0 | H19: 1112.3 | I19: 101118.33 | J19: 22242.85 | K19: 0 | L19: =F19 | M19: 2.48e-08 | N19: 9.9e-07 | O19: 21.348662 | P19: 56046040 | Q19: 2463387.9
A20: Wash 2 | B20: PE | C20: Toluene | D20: 4.92 | E20: 4.15 | F20: 0.95121159 | G20: 0 | H20: 1343.2 | I20: 122109.4 | J20: 29290.58 | K20: 0 | L20: =F20 | M20: 2.81e-08 | N20: 1.02e-06 | O20: 21.928792 | P20: 63309202 | Q20: 2670225.7
A21: Wash 2 | B21: PE | C21: Xylene | D21: 5.09 | E21: 4.04 | F21: 0.95185106 | G21: 0 | H21: 1639.68 | I21: 149061.63 | J21: 17987.13 | K21: 0 | L21: =F21 | M21: 3.19e-08 | N21: 9.89e-07 | O21: 21.39959 | P21: 51159780 | Q21: 2375168.9
A22: Wash 2 | B22: EVOH | C22: butane-1,4-diol | D22: 8.65 | E22: 4.61 | F22: 1.4570856 | G22: 0 | H22: 1109.22 | I22: 100837.82 | J22: 3250.8 | K22: 0 | L22: =F22 | M22: 8.8127759e-08 | N22: 1.135736e-06 | O22: 25.036672 | P22: 16107740 | Q22: 788338.9
A23: Wash 2 | B23: EVOH | C23: Diethanolamine | D23: 10.87 | E23: 4.81 | F23: 1.664125 | G23: 0 | H23: 1442.19 | I23: 131107.9 | J23: 2899 | K23: 0 | L23: =F23 | M23: 1.2218717e-07 | N23: 1.1854925e-06 | O23: 26.41872 | P23: 15561769 | Q23: 793517.72
A24: Wash 2 | B24: EVOH | C24: Diethylene glycol | D24: 9.55 | E24: 4.68 | F24: 1.5363017 | G24: 0 | H24: 1177.79 | I24: 107071.49 | J24: 2847.02 | K24: 0 | L24: =F24 | M24: 1.01753e-07 | N24: 1.1517104e-06 | O24: 25.495437 | P24: 15469988 | Q24: 781218.91
... A28: Wash 2 | B28: EVOH | C28: gamma-butyrolactone | D28: 7.17 | E28: 4.43 | F28: 1.3129951 | G28: 0 | H28: 820.52 | I28: 74592.63 | J28: 2886.53 | K28: 0 | L28: =F28 | M28: 6.6085587e-08 | N28: 1.0918539e-06 | O28: 23.911213 | P28: 15430391 | Q28: 763240.91

Sheet StrapScenario2
A1: Wash number | B1: ='[1]Final Data (use this)'!C11 | C1: ='[1]Final Data (use this)'!D11 | D1: Total Energy Consumed [MJ/kg resin produced ] | E1: Total Electricity [MJ/kg resin] | F1: Total Direct GHG emissions [Scope 1] [metric tons CO2 equivalent [tCO2e/ton]] | G1: Total Energy indirect GHG emissions (Scope 2) [metric tons CO2 equivalent (t CO2e)] | H1: Water consumed/discarded [m3/yr] | I1: Water Recycled or Reused [m3/yr] | J1: Waste generated - Non Hazardous [kg/yr] | K1: Waste to Disposal[ton/ton] | L1: GWP [tonCO2e/ton resin] | M1: Human toxicity cancer [CTUh/kg resin] | N1: Human toxicity non-cancer [CTUh/kg resin] | O1: Ecotoxicity [CTUe/kg resin] | P1: CAPEX [USD] | Q1: OPEX [USD/yr]
A2: Wash 1 | B2: PE | C2: sec-Butyl Acetate | D2: =[9]Process_results_C2_P1!B2+[10]Process_results_shredderC2!$B$2 | E2: =[9]Process_results_C2_P1!C2+[10]Process_results_shredderC2!$C$2 | F2: =L2 | G2: 0 | H2: 553.5 | I2: 50318 | J2: 7403.53 | K2: 0 | L2: =[9]Process_results_C2_P1!D2+[10]Process_results_shredderC2!$D$2 | M2: =[9]Process_results_C2_P1!I2+[10]Process_results_shredderC2!$E$2 | N2: =[9]Process_results_C2_P1!J2+[10]Process_results_shredderC2!$F$2 | O2: =[9]Process_results_C2_P1!K2+[10]Process_results_shredderC2!$G$2 | P2: =[9]Process_results_C2_P1!L2+[10]Process_results_shredderC2!$H$2 | Q2: =[9]Process_results_C2_P1!M2+[10]Process_results_shredderC2!$I$2
A3: Wash 1 | B3: PE | C3: Isobutyl Acetate | D3: =[9]Process_results_C2_P1!B3+[10]Process_results_shredderC2!$B$2 | E3: =[9]Process_results_C2_P1!C3+[10]Process_results_shredderC2!$C$2 | F3: =L3 | G3: 0 | H3: 544.09 | I3: 49462.98 | J3: 7463.47 | K3: 0 | L3: =[9]Process_results_C2_P1!D3+[10]Process_results_shredderC2!$D$2 | M3: =[9]Process_results_C2_P1!I3+[10]Process_results_shredderC2!$E$2 | N3: =[9]Process_results_C2_P1!J3+[10]Process_results_shredderC2!$F$2 | O3: =[9]Process_results_C2_P1!K3+[10]Process_results_shredderC2!$G$2 | P3: =[9]Process_results_C2_P1!L3+[10]Process_results_shredderC2!$H$2 | Q3: =[9]Process_results_C2_P1!M3+[10]Process_results_shredderC2!$I$2
A4: Wash 1 | B4: PE | C4: Tetrachloroethylene | D4: =[9]Process_results_C2_P1!B4+[10]Process_results_shredderC2!$B$2 | E4: =[9]Process_results_C2_P1!C4+[10]Process_results_shredderC2!$C$2 | F4: =L4 | G4: 0 | H4: 271.83 | I4: 24711.96 | J4: 4419.13 | K4: 0 | L4: =[9]Process_results_C2_P1!D4+[10]Process_results_shredderC2!$D$2 | M4: =[9]Process_results_C2_P1!I4+[10]Process_results_shredderC2!$E$2 | N4: =[9]Process_results_C2_P1!J4+[10]Process_results_shredderC2!$F$2 | O4: =[9]Process_results_C2_P1!K4+[10]Process_results_shredderC2!$G$2 | P4: =[9]Process_results_C2_P1!L4+[10]Process_results_shredderC2!$H$2 | Q4: =[9]Process_results_C2_P1!M4+[10]Process_results_shredderC2!$I$2
A5: Wash 1 | B5: PE | C5: o-Chlorotoluene | D5: =[9]Process_results_C2_P1!B5+[10]Process_results_shredderC2!$B$2 | E5: =[9]Process_results_C2_P1!C5+[10]Process_results_shredderC2!$C$2 | F5: =L5 | G5: 0 | H5: 671.12 | I5: 61011.36 | J5: 6319.81 | K5: 0 | L5: =[9]Process_results_C2_P1!D5+[10]Process_results_shredderC2!$D$2 | M5: =[9]Process_results_C2_P1!I5+[10]Process_results_shredderC2!$E$2 | N5: =[9]Process_results_C2_P1!J5+[10]Process_results_shredderC2!$F$2 | O5: =[9]Process_results_C2_P1!K5+[10]Process_results_shredderC2!$G$2 | P5: =[9]Process_results_C2_P1!L5+[10]Process_results_shredderC2!$H$2 | Q5: =[9]Process_results_C2_P1!M5+[10]Process_results_shredderC2!$I$2
A6: Wash 1 | B6: PE | C6: Methylcyclohexane | D6: =[9]Process_results_C2_P1!B6+[10]Process_results_shredderC2!$B$2 | E6: =[9]Process_results_C2_P1!C6+[10]Process_results_shredderC2!$C$2 | F6: =L6 | G6: 0 | H6: 450.63 | I6: 40966.07 | J6: 8129.51 | K6: 0 | L6: =[9]Process_results_C2_P1!D6+[10]Process_results_shredderC2!$D$2 | M6: =[9]Process_results_C2_P1!I6+[10]Process_results_shredderC2!$E$2 | N6: =[9]Process_results_C2_P1!J6+[10]Process_results_shredderC2!$F$2 | O6: =[9]Process_results_C2_P1!K6+[10]Process_results_shredderC2!$G$2 | P6: =[9]Process_results_C2_P1!L6+[10]Process_results_shredderC2!$H$2 | Q6: =[9]Process_results_C2_P1!M6+[10]Process_results_shredderC2!$I$2
A7: Wash 1 | B7: PE | C7: Dodecanol | D7: =[9]Process_results_C2_P1!B7+[10]Process_results_shredderC2!$B$2 | E7: =[9]Process_results_C2_P1!C7+[10]Process_results_shredderC2!$C$2 | F7: =L7 | G7: 0 | H7: 1823.94 | I7: 165812.51 | J7: 8514.94 | K7: 0 | L7: =[9]Process_results_C2_P1!D7+[10]Process_results_shredderC2!$D$2 | M7: =[9]Process_results_C2_P1!I7+[10]Process_results_shredderC2!$E$2 | N7: =[9]Process_results_C2_P1!J7+[10]Process_results_shredderC2!$F$2 | O7: =[9]Process_results_C2_P1!K7+[10]Process_results_shredderC2!$G$2 | P7: =[9]Process_results_C2_P1!L7+[10]Process_results_shredderC2!$H$2 | Q7: =[9]Process_results_C2_P1!M7+[10]Process_results_shredderC2!$I$2
A8: Wash 1 | B8: PE | C8: Heptane | D8: =[9]Process_results_C2_P1!B8+[10]Process_results_shredderC2!$B$2 | E8: =[9]Process_results_C2_P1!C8+[10]Process_results_shredderC2!$C$2 | F8: =L8 | G8: 0 | H8: 477.69 | I8: 43426.62 | J8: 9006.42 | K8: 0 | L8: =[9]Process_results_C2_P1!D8+[10]Process_results_shredderC2!$D$2 | M8: =[9]Process_results_C2_P1!I8+[10]Process_results_shredderC2!$E$2 | N8: =[9]Process_results_C2_P1!J8+[10]Process_results_shredderC2!$F$2 | O8: =[9]Process_results_C2_P1!K8+[10]Process_results_shredderC2!$G$2 | P8: =[9]Process_results_C2_P1!L8+[10]Process_results_shredderC2!$H$2 | Q8: =[9]Process_results_C2_P1!M8+[10]Process_results_shredderC2!$I$2
A9: Wash 1 | B9: PE | C9: Toluene | D9: =[9]Process_results_C2_P1!B9+[10]Process_results_shredderC2!$B$2 | E9: =[9]Process_results_C2_P1!C9+[10]Process_results_shredderC2!$C$2 | F9: =L9 | G9: 0 | H9: 575.69 | I9: 52335.51 | J9: 11871.24 | K9: 0 | L9: =[9]Process_results_C2_P1!D9+[10]Process_results_shredderC2!$D$2 | M9: =[9]Process_results_C2_P1!I9+[10]Process_results_shredderC2!$E$2 | N9: =[9]Process_results_C2_P1!J9+[10]Process_results_shredderC2!$F$2 | O9: =[9]Process_results_C2_P1!K9+[10]Process_results_shredderC2!$G$2 | P9: =[9]Process_results_C2_P1!L9+[10]Process_results_shredderC2!$H$2 | Q9: =[9]Process_results_C2_P1!M9+[10]Process_results_shredderC2!$I$2
A10: Wash 1 | B10: PE | C10: Xylene | D10: =[9]Process_results_C2_P1!B10+[10]Process_results_shredderC2!$B$2 | E10: =[9]Process_results_C2_P1!C10+[10]Process_results_shredderC2!$C$2 | F10: =L10 | G10: 0 | H10: 689.38 | I10: 62671.13 | J10: 7294.56 | K10: 0 | L10: =[9]Process_results_C2_P1!D10+[10]Process_results_shredderC2!$D$2 | M10: =[9]Process_results_C2_P1!I10+[10]Process_results_shredderC2!$E$2 | N10: =[9]Process_results_C2_P1!J10+[10]Process_results_shredderC2!$F$2 | O10: =[9]Process_results_C2_P1!K10+[10]Process_results_shredderC2!$G$2 | P10: =[9]Process_results_C2_P1!L10+[10]Process_results_shredderC2!$H$2 | Q10: =[9]Process_results_C2_P1!M10+[10]Process_results_shredderC2!$I$2
A11: Wash 1 | B11: EVOH | C11: =[5]Process_results_C2_E1!$A$2 | D11: =[5]Process_results_C2_E1!B2+[10]Process_results_shredderC2!$B$2 | E11: =[5]Process_results_C2_E1!C2+[10]Process_results_shredderC2!$C$2 | F11: =L11 | G11: 0 | H11: =[5]Process_results_C2_E1!G2 | I11: =[5]Process_results_C2_E1!H2 | J11: =[5]Process_results_C2_E1!E2 | K11: 0 | L11: =[5]Process_results_C2_E1!D2+[10]Process_results_shredderC2!$D$2 | M11: =[5]Process_results_C2_E1!I2+[10]Process_results_shredderC2!$E$2 | N11: =[5]Process_results_C2_E1!J2+[10]Process_results_shredderC2!$F$2 | O11: =[5]Process_results_C2_E1!K2+[10]Process_results_shredderC2!$G$2 | P11: =[5]Process_results_C2_E1!L2+[10]Process_results_shredderC2!$H$2 | Q11: =[5]Process_results_C2_E1!M2+[10]Process_results_shredderC2!$I$2
A12: Wash 1 | B12: EVOH | C12: Pyridazine | D12: =[5]Process_results_C2_E1!B3+[10]Process_results_shredderC2!$B$2 | E12: =[5]Process_results_C2_E1!C3+[10]Process_results_shredderC2!$C$2 | F12: =L12 | G12: 0 | H12: =[5]Process_results_C2_E1!G3 | I12: =[5]Process_results_C2_E1!H3 | J12: =[5]Process_results_C2_E1!E3 | K12: 0 | L12: =[5]Process_results_C2_E1!D3+[10]Process_results_shredderC2!$D$2 | M12: =[5]Process_results_C2_E1!I3+[10]Process_results_shredderC2!$E$2 | N12: =[5]Process_results_C2_E1!J3+[10]Process_results_shredderC2!$F$2 | O12: =[5]Process_results_C2_E1!K3+[10]Process_results_shredderC2!$G$2 | P12: =[5]Process_results_C2_E1!L3+[10]Process_results_shredderC2!$H$2 | Q12: =[5]Process_results_C2_E1!M3+[10]Process_results_shredderC2!$I$2
A13: Wash 2 | B13: PE | C13: sec-Butyl Acetate | D13: 4.87 | E13: 4.05 | F13: =L13 | G13: 0 | H13: 521.86 | I13: 47441.8 | J13: 7303.6 | K13: 0 | L13: 0.94051939 | M13: 2.9399649e-08 | N13: 9.9307611e-07 | O13: 21.494883 | P13: 28113759 | Q13: 1231283
A14: Wash 2 | B14: PE | C14: Isobutyl Acetate | D14: 4.85 | E14: 4.05 | F14: =L14 | G14: 0 | H14: 514.72 | I14: 46793.11 | J14: 7363.19 | K14: 0 | L14: 0.93874498 | M14: 2.9041987e-08 | N14: 9.9383046e-07 | O14: 21.508755 | P14: 28381281 | Q14: 1236554.1
A15: Wash 2 | B15: PE | C15: Tetrachloroethylene | D15: 4.29 | E15: 3.87 | F15: =L15 | G15: 0 | H15: 251.7 | I15: 22881.52 | J15: 4341.89 | K15: 0 | L15: 0.86913192 | M15: 2.0388342e-08 | N15: 9.4791715e-07 | O15: 20.390648 | P15: 23489730 | Q15: 1123773.8
A16: Wash 2 | B16: PE | C16: o-Chlorotoluene | D16: 5.11 | E16: 4.04 | F16: =L16 | G16: 0 | H16: 638.04 | I16: 58003.45 | J16: 6226.9 | K16: 0 | L16: 0.95597823 | M16: 3.312222e-08 | N16: 9.9035715e-07 | O16: 21.469748 | P16: 26710194 | Q16: 1205102.6
A17: Wash 2 | B17: PE | C17: Methylcyclohexane | D17: 4.63 | E17: 4.05 | F17: =L17 | G17: 0 | H17: 417.51 | I17: 37955.03 | J17: 8025.78 | K17: 0 | L17: 0.91535435 | M17: 2.4504692e-08 | N17: 9.905667e-07 | O17: 21.376517 | P17: 29115891 | Q17: 1248756.5
A18: Wash 2 | B18: PE | C18: Dodecanol | D18: 7.94 | E18: 4.41 | F18: =L18 | G18: 0 | H18: 1769.23 | I18: 160839.27 | J18: 8405.55 | K18: 0 | L18: 1.2402875 | M18: 7.6724636e-08 | N18: 1.0882427e-06 | O18: 24.056466 | P18: 29972514 | Q18: 1330792.6
A19: Wash 2 | B19: PE | C19: Heptane | D19: 4.72 | E19: 4.09 | F19: =L19 | G19: 0 | H19: 444.92 | I19: 40447.33 | J19: 8897.14 | K19: 0 | L19: 0.92426045 | M19: 2.4896176e-08 | N19: 1.0000538e-06 | O19: 21.567676 | P19: 30476717 | Q19: 1278994.2
A20: Wash 2 | B20: PE | C20: Toluene | D20: 4.97 | E20: 4.19 | F20: =L20 | G20: 0 | H20: 537.28 | I20: 48843.76 | J20: 11716.23 | K20: 0 | L20: 0.95976798 | M20: 2.818811e-08 | N20: 1.0257474e-06 | O20: 22.156384 | P20: 33940450 | Q20: 1372490.1
A21: Wash 2 | B21: PE | C21: Xylene | D21: 5.13 | E21: 4.08 | F21: =L21 | G21: 0 | H21: 655.87 | I21: 59624.65 | J21: 7194.85 | K21: 0 | L21: 0.95977725 | M21: 3.2043822e-08 | N21: 9.9891449e-07 | O21: 21.610418 | P21: 28207696 | Q21: 1237391.2
A22: Wash 2 | B22: EVOH | C22: butane-1,4-diol | D22: 8.81 | E22: 4.77 | F22: =L22 | G22: 0 | H22: 443.69 | I22: 40335.13 | J22: 1300.32 | K22: 0 | L22: 1.4880864 | M22: 8.8618736e-08 | N22: 1.1741329e-06 | O22: 25.861262 | P22: 9482279.5 | Q22: 510615.89
A23: Wash 2 | B23: EVOH | C23: Diethanolamine | D23: 11.02 | E23: 4.97 | F23: =L23 | G23: 0 | H23: 576.87 | I23: 52443.16 | J23: 1159.6 | K23: 0 | L23: 1.6950809 | M23: 1.2267744e-07 | N23: 1.2238338e-06 | O23: 27.242116 | P23: 9160224.6 | Q23: 510549.5
A24: Wash 2 | B24: EVOH | C24: Diethylene glycol | D24: 9.71 | E24: 4.83 | F24: =L24 | G24: 0 | H24: 471.11 | I24: 42828.59 | J24: 1138.81 | K24: 0 | L24: 1.5672509 | M24: 1.0224316e-07 | N24: 1.1900434e-06 | O24: 26.318655 | P24: 9283735.1 | Q24: 508837.06
... A28: Wash 2 | B28: EVOH | C28: gamma-butyrolactone | D28: 7.32 | E28: 4.58 | F28: =L28 | G28: 0 | H28: 328.21 | I28: 29837.05 | J28: 1154.61 | K28: 0 | L28: 1.3439494 | M28: 6.6575828e-08 | N28: 1.1301932e-06 | O28: 24.734566 | P28: 9094194 | Q28: 498435.54

Sheet StrapScenario2 Units
A1: Wash number | B1: Polymer | C1: Solvents | D1: Total Energy Consumed [MJ/yr] | E1: Total Renewable Energy Consumed [MJ/yr] | F1: Total Direct GHG emissions [Scope 1] [metric tons CO2 equivalent [tCO2e/yr]] | G1: Total Energy indirect GHG emissions (Scope 2) [metric tons CO2 equivalent (t CO2e/yr)] | H1: Water consumed/discarded [m3/yr] | I1: Water Recycled or Reused [m3/yr] | J1: Waste generated - Non Hazardous [kg/yr] | K1: Waste to Disposal[ton/yr] | L1: GWP [tonCO2e/yr] | M1: Human toxicity cancer [CTUh/yr] | N1: Human toxicity non-cancer [CTUh/yr] | O1: Ecotoxicity [CTUe/yr] | P1: CAPEX [USD/yr] | Q1: OPEX [USD/yr]
A2: =StrapScenario2!A2 | B2: =StrapScenario2!B2 | C2: =StrapScenario2!C2 | D2: =StrapScenario2!D2*'[1]New UBs'!$E$50 | E2: ='StrapScenario2 Units elec'!E2*0.12 | F2: =L2 | G2: =StrapScenario2!G2 | H2: =StrapScenario2!H2 | I2: =StrapScenario2!I2 | J2: =StrapScenario2!J2 | K2: =StrapScenario2!K2 | L2: =StrapScenario2!L2*'[1]New UBs'!$E$50/1000 | M2: =StrapScenario2!M2*'[1]New UBs'!$E$50 | N2: =StrapScenario2!N2*'[1]New UBs'!$E$50 | O2: =StrapScenario2!O2*'[1]New UBs'!$E$50 | P2: =StrapScenario2!P2/20 | Q2: =StrapScenario2!Q2
A3: =StrapScenario2!A3 | B3: =StrapScenario2!B3 | C3: =StrapScenario2!C3 | D3: =StrapScenario2!D3*'[1]New UBs'!$E$50 | E3: ='StrapScenario2 Units elec'!E3*0.12 | F3: =L3 | G3: =StrapScenario2!G3 | H3: =StrapScenario2!H3 | I3: =StrapScenario2!I3 | J3: =StrapScenario2!J3 | K3: =StrapScenario2!K3 | L3: =StrapScenario2!L3*'[1]New UBs'!$E$50/1000 | M3: =StrapScenario2!M3*'[1]New UBs'!$E$50 | N3: =StrapScenario2!N3*'[1]New UBs'!$E$50 | O3: =StrapScenario2!O3*'[1]New UBs'!$E$50 | P3: =StrapScenario2!P3/20 | Q3: =StrapScenario2!Q3
A4: =StrapScenario2!A4 | B4: =StrapScenario2!B4 | C4: =StrapScenario2!C4 | D4: =StrapScenario2!D4*'[1]New UBs'!$E$50 | E4: ='StrapScenario2 Units elec'!E4*0.12 | F4: =L4 | G4: =StrapScenario2!G4 | H4: =StrapScenario2!H4 | I4: =StrapScenario2!I4 | J4: =StrapScenario2!J4 | K4: =StrapScenario2!K4 | L4: =StrapScenario2!L4*'[1]New UBs'!$E$50/1000 | M4: =StrapScenario2!M4*'[1]New UBs'!$E$50 | N4: =StrapScenario2!N4*'[1]New UBs'!$E$50 | O4: =StrapScenario2!O4*'[1]New UBs'!$E$50 | P4: =StrapScenario2!P4/20 | Q4: =StrapScenario2!Q4
A5: =StrapScenario2!A5 | B5: =StrapScenario2!B5 | C5: =StrapScenario2!C5 | D5: =StrapScenario2!D5*'[1]New UBs'!$E$50 | E5: ='StrapScenario2 Units elec'!E5*0.12 | F5: =L5 | G5: =StrapScenario2!G5 | H5: =StrapScenario2!H5 | I5: =StrapScenario2!I5 | J5: =StrapScenario2!J5 | K5: =StrapScenario2!K5 | L5: =StrapScenario2!L5*'[1]New UBs'!$E$50/1000 | M5: =StrapScenario2!M5*'[1]New UBs'!$E$50 | N5: =StrapScenario2!N5*'[1]New UBs'!$E$50 | O5: =StrapScenario2!O5*'[1]New UBs'!$E$50 | P5: =StrapScenario2!P5/20 | Q5: =StrapScenario2!Q5
A6: =StrapScenario2!A6 | B6: =StrapScenario2!B6 | C6: =StrapScenario2!C6 | D6: =StrapScenario2!D6*'[1]New UBs'!$E$50 | E6: ='StrapScenario2 Units elec'!E6*0.12 | F6: =L6 | G6: =StrapScenario2!G6 | H6: =StrapScenario2!H6 | I6: =StrapScenario2!I6 | J6: =StrapScenario2!J6 | K6: =StrapScenario2!K6 | L6: =StrapScenario2!L6*'[1]New UBs'!$E$50/1000 | M6: =StrapScenario2!M6*'[1]New UBs'!$E$50 | N6: =StrapScenario2!N6*'[1]New UBs'!$E$50 | O6: =StrapScenario2!O6*'[1]New UBs'!$E$50 | P6: =StrapScenario2!P6/20 | Q6: =StrapScenario2!Q6
A7: =StrapScenario2!A7 | B7: =StrapScenario2!B7 | C7: =StrapScenario2!C7 | D7: =StrapScenario2!D7*'[1]New UBs'!$E$50 | E7: ='StrapScenario2 Units elec'!E7*0.12 | F7: =L7 | G7: =StrapScenario2!G7 | H7: =StrapScenario2!H7 | I7: =StrapScenario2!I7 | J7: =StrapScenario2!J7 | K7: =StrapScenario2!K7 | L7: =StrapScenario2!L7*'[1]New UBs'!$E$50/1000 | M7: =StrapScenario2!M7*'[1]New UBs'!$E$50 | N7: =StrapScenario2!N7*'[1]New UBs'!$E$50 | O7: =StrapScenario2!O7*'[1]New UBs'!$E$50 | P7: =StrapScenario2!P7/20 | Q7: =StrapScenario2!Q7
A8: =StrapScenario2!A8 | B8: =StrapScenario2!B8 | C8: =StrapScenario2!C8 | D8: =StrapScenario2!D8*'[1]New UBs'!$E$50 | E8: ='StrapScenario2 Units elec'!E8*0.12 | F8: =L8 | G8: =StrapScenario2!G8 | H8: =StrapScenario2!H8 | I8: =StrapScenario2!I8 | J8: =StrapScenario2!J8 | K8: =StrapScenario2!K8 | L8: =StrapScenario2!L8*'[1]New UBs'!$E$50/1000 | M8: =StrapScenario2!M8*'[1]New UBs'!$E$50 | N8: =StrapScenario2!N8*'[1]New UBs'!$E$50 | O8: =StrapScenario2!O8*'[1]New UBs'!$E$50 | P8: =StrapScenario2!P8/20 | Q8: =StrapScenario2!Q8
A9: =StrapScenario2!A9 | B9: =StrapScenario2!B9 | C9: =StrapScenario2!C9 | D9: =StrapScenario2!D9*'[1]New UBs'!$E$50 | E9: ='StrapScenario2 Units elec'!E9*0.12 | F9: =L9 | G9: =StrapScenario2!G9 | H9: =StrapScenario2!H9 | I9: =StrapScenario2!I9 | J9: =StrapScenario2!J9 | K9: =StrapScenario2!K9 | L9: =StrapScenario2!L9*'[1]New UBs'!$E$50/1000 | M9: =StrapScenario2!M9*'[1]New UBs'!$E$50 | N9: =StrapScenario2!N9*'[1]New UBs'!$E$50 | O9: =StrapScenario2!O9*'[1]New UBs'!$E$50 | P9: =StrapScenario2!P9/20 | Q9: =StrapScenario2!Q9
A10: =StrapScenario2!A10 | B10: =StrapScenario2!B10 | C10: =StrapScenario2!C10 | D10: =StrapScenario2!D10*'[1]New UBs'!$E$50 | E10: ='StrapScenario2 Units elec'!E10*0.12 | F10: =L10 | G10: =StrapScenario2!G10 | H10: =StrapScenario2!H10 | I10: =StrapScenario2!I10 | J10: =StrapScenario2!J10 | K10: =StrapScenario2!K10 | L10: =StrapScenario2!L10*'[1]New UBs'!$E$50/1000 | M10: =StrapScenario2!M10*'[1]New UBs'!$E$50 | N10: =StrapScenario2!N10*'[1]New UBs'!$E$50 | O10: =StrapScenario2!O10*'[1]New UBs'!$E$50 | P10: =StrapScenario2!P10/20 | Q10: =StrapScenario2!Q10
A11: =StrapScenario2!A11 | B11: =StrapScenario2!B11 | C11: =StrapScenario2!C11 | D11: =StrapScenario2!D11*'[1]New UBs'!$E$51 | E11: ='StrapScenario2 Units elec'!E11*0.12 | F11: =L11 | G11: =StrapScenario2!G11 | H11: =StrapScenario2!H11 | I11: =StrapScenario2!I11 | J11: =StrapScenario2!J11 | K11: =StrapScenario2!K11 | L11: =StrapScenario2!L11*'[1]New UBs'!$E$51/1000 | M11: =StrapScenario2!M11*'[1]New UBs'!$E$51 | N11: =StrapScenario2!N11*'[1]New UBs'!$E$51 | O11: =StrapScenario2!O11*'[1]New UBs'!$E$51 | P11: =StrapScenario2!P11/20 | Q11: =StrapScenario2!Q11
A12: =StrapScenario2!A12 | B12: =StrapScenario2!B12 | C12: =StrapScenario2!C12 | D12: =StrapScenario2!D12*'[1]New UBs'!$E$51 | E12: ='StrapScenario2 Units elec'!E12*0.12 | F12: =L12 | G12: =StrapScenario2!G12 | H12: =StrapScenario2!H12 | I12: =StrapScenario2!I12 | J12: =StrapScenario2!J12 | K12: =StrapScenario2!K12 | L12: =StrapScenario2!L12*'[1]New UBs'!$E$51/1000 | M12: =StrapScenario2!M12*'[1]New UBs'!$E$51 | N12: =StrapScenario2!N12*'[1]New UBs'!$E$51 | O12: =StrapScenario2!O12*'[1]New UBs'!$E$51 | P12: =StrapScenario2!P12/20 | Q12: =StrapScenario2!Q12
A13: =StrapScenario2!A13 | B13: =StrapScenario2!B13 | C13: =StrapScenario2!C13 | D13: =StrapScenario2!D13*'[1]New UBs'!$J$51 | E13: ='StrapScenario2 Units elec'!E13*0.12 | F13: =L13 | G13: =StrapScenario2!G13 | H13: =StrapScenario2!H13 | I13: =StrapScenario2!I13 | J13: =StrapScenario2!J13 | K13: =StrapScenario2!K13 | L13: =StrapScenario2!L13*'[1]New UBs'!$J$51/1000 | M13: =StrapScenario2!M13*'[1]New UBs'!$J$51 | N13: =StrapScenario2!N13*'[1]New UBs'!$J$51 | O13: =StrapScenario2!O13*'[1]New UBs'!$J$51 | P13: =StrapScenario2!P13/20 | Q13: =StrapScenario2!Q13
A14: =StrapScenario2!A14 | B14: =StrapScenario2!B14 | C14: =StrapScenario2!C14 | D14: =StrapScenario2!D14*'[1]New UBs'!$J$51 | E14: ='StrapScenario2 Units elec'!E14*0.12 | F14: =L14 | G14: =StrapScenario2!G14 | H14: =StrapScenario2!H14 | I14: =StrapScenario2!I14 | J14: =StrapScenario2!J14 | K14: =StrapScenario2!K14 | L14: =StrapScenario2!L14*'[1]New UBs'!$J$51/1000 | M14: =StrapScenario2!M14*'[1]New UBs'!$J$51 | N14: =StrapScenario2!N14*'[1]New UBs'!$J$51 | O14: =StrapScenario2!O14*'[1]New UBs'!$J$51 | P14: =StrapScenario2!P14/20 | Q14: =StrapScenario2!Q14
A15: =StrapScenario2!A15 | B15: =StrapScenario2!B15 | C15: =StrapScenario2!C15 | D15: =StrapScenario2!D15*'[1]New UBs'!$J$51 | E15: ='StrapScenario2 Units elec'!E15*0.12 | F15: =L15 | G15: =StrapScenario2!G15 | H15: =StrapScenario2!H15 | I15: =StrapScenario2!I15 | J15: =StrapScenario2!J15 | K15: =StrapScenario2!K15 | L15: =StrapScenario2!L15*'[1]New UBs'!$J$51/1000 | M15: =StrapScenario2!M15*'[1]New UBs'!$J$51 | N15: =StrapScenario2!N15*'[1]New UBs'!$J$51 | O15: =StrapScenario2!O15*'[1]New UBs'!$J$51 | P15: =StrapScenario2!P15/20 | Q15: =StrapScenario2!Q15
A16: =StrapScenario2!A16 | B16: =StrapScenario2!B16 | C16: =StrapScenario2!C16 | D16: =StrapScenario2!D16*'[1]New UBs'!$J$51 | E16: ='StrapScenario2 Units elec'!E16*0.12 | F16: =L16 | G16: =StrapScenario2!G16 | H16: =StrapScenario2!H16 | I16: =StrapScenario2!I16 | J16: =StrapScenario2!J16 | K16: =StrapScenario2!K16 | L16: =StrapScenario2!L16*'[1]New UBs'!$J$51/1000 | M16: =StrapScenario2!M16*'[1]New UBs'!$J$51 | N16: =StrapScenario2!N16*'[1]New UBs'!$J$51 | O16: =StrapScenario2!O16*'[1]New UBs'!$J$51 | P16: =StrapScenario2!P16/20 | Q16: =StrapScenario2!Q16
A17: =StrapScenario2!A17 | B17: =StrapScenario2!B17 | C17: =StrapScenario2!C17 | D17: =StrapScenario2!D17*'[1]New UBs'!$J$51 | E17: ='StrapScenario2 Units elec'!E17*0.12 | F17: =L17 | G17: =StrapScenario2!G17 | H17: =StrapScenario2!H17 | I17: =StrapScenario2!I17 | J17: =StrapScenario2!J17 | K17: =StrapScenario2!K17 | L17: =StrapScenario2!L17*'[1]New UBs'!$J$51/1000 | M17: =StrapScenario2!M17*'[1]New UBs'!$J$51 | N17: =StrapScenario2!N17*'[1]New UBs'!$J$51 | O17: =StrapScenario2!O17*'[1]New UBs'!$J$51 | P17: =StrapScenario2!P17/20 | Q17: =StrapScenario2!Q17
A18: =StrapScenario2!A18 | B18: =StrapScenario2!B18 | C18: =StrapScenario2!C18 | D18: =StrapScenario2!D18*'[1]New UBs'!$J$51 | E18: ='StrapScenario2 Units elec'!E18*0.12 | F18: =L18 | G18: =StrapScenario2!G18 | H18: =StrapScenario2!H18 | I18: =StrapScenario2!I18 | J18: =StrapScenario2!J18 | K18: =StrapScenario2!K18 | L18: =StrapScenario2!L18*'[1]New UBs'!$J$51/1000 | M18: =StrapScenario2!M18*'[1]New UBs'!$J$51 | N18: =StrapScenario2!N18*'[1]New UBs'!$J$51 | O18: =StrapScenario2!O18*'[1]New UBs'!$J$51 | P18: =StrapScenario2!P18/20 | Q18: =StrapScenario2!Q18
A19: =StrapScenario2!A19 | B19: =StrapScenario2!B19 | C19: =StrapScenario2!C19 | D19: =StrapScenario2!D19*'[1]New UBs'!$J$51 | E19: ='StrapScenario2 Units elec'!E19*0.12 | F19: =L19 | G19: =StrapScenario2!G19 | H19: =StrapScenario2!H19 | I19: =StrapScenario2!I19 | J19: =StrapScenario2!J19 | K19: =StrapScenario2!K19 | L19: =StrapScenario2!L19*'[1]New UBs'!$J$51/1000 | M19: =StrapScenario2!M19*'[1]New UBs'!$J$51 | N19: =StrapScenario2!N19*'[1]New UBs'!$J$51 | O19: =StrapScenario2!O19*'[1]New UBs'!$J$51 | P19: =StrapScenario2!P19/20 | Q19: =StrapScenario2!Q19
A20: =StrapScenario2!A20 | B20: =StrapScenario2!B20 | C20: =StrapScenario2!C20 | D20: =StrapScenario2!D20*'[1]New UBs'!$J$51 | E20: ='StrapScenario2 Units elec'!E20*0.12 | F20: =L20 | G20: =StrapScenario2!G20 | H20: =StrapScenario2!H20 | I20: =StrapScenario2!I20 | J20: =StrapScenario2!J20 | K20: =StrapScenario2!K20 | L20: =StrapScenario2!L20*'[1]New UBs'!$J$51/1000 | M20: =StrapScenario2!M20*'[1]New UBs'!$J$51 | N20: =StrapScenario2!N20*'[1]New UBs'!$J$51 | O20: =StrapScenario2!O20*'[1]New UBs'!$J$51 | P20: =StrapScenario2!P20/20 | Q20: =StrapScenario2!Q20
A21: =StrapScenario2!A21 | B21: =StrapScenario2!B21 | C21: =StrapScenario2!C21 | D21: =StrapScenario2!D21*'[1]New UBs'!$J$51 | E21: ='StrapScenario2 Units elec'!E21*0.12 | F21: =L21 | G21: =StrapScenario2!G21 | H21: =StrapScenario2!H21 | I21: =StrapScenario2!I21 | J21: =StrapScenario2!J21 | K21: =StrapScenario2!K21 | L21: =StrapScenario2!L21*'[1]New UBs'!$J$51/1000 | M21: =StrapScenario2!M21*'[1]New UBs'!$J$51 | N21: =StrapScenario2!N21*'[1]New UBs'!$J$51 | O21: =StrapScenario2!O21*'[1]New UBs'!$J$51 | P21: =StrapScenario2!P21/20 | Q21: =StrapScenario2!Q21
A22: =StrapScenario2!A22 | B22: =StrapScenario2!B22 | C22: =StrapScenario2!C22 | D22: =StrapScenario2!D22*'[1]New UBs'!$J$50 | E22: ='StrapScenario2 Units elec'!E22*0.12 | F22: =L22 | G22: =StrapScenario2!G22 | H22: =StrapScenario2!H22 | I22: =StrapScenario2!I22 | J22: =StrapScenario2!J22 | K22: =StrapScenario2!K22 | L22: =StrapScenario2!L22*'[1]New UBs'!$J$50/1000 | M22: =StrapScenario2!M22*'[1]New UBs'!$J$50 | N22: =StrapScenario2!N22*'[1]New UBs'!$J$50 | O22: =StrapScenario2!O22*'[1]New UBs'!$J$50 | P22: =StrapScenario2!P22/20 | Q22: =StrapScenario2!Q22
A23: =StrapScenario2!A23 | B23: =StrapScenario2!B23 | C23: =StrapScenario2!C23 | D23: =StrapScenario2!D23*'[1]New UBs'!$J$50 | E23: ='StrapScenario2 Units elec'!E23*0.12 | F23: =L23 | G23: =StrapScenario2!G23 | H23: =StrapScenario2!H23 | I23: =StrapScenario2!I23 | J23: =StrapScenario2!J23 | K23: =StrapScenario2!K23 | L23: =StrapScenario2!L23*'[1]New UBs'!$J$50/1000 | M23: =StrapScenario2!M23*'[1]New UBs'!$J$50 | N23: =StrapScenario2!N23*'[1]New UBs'!$J$50 | O23: =StrapScenario2!O23*'[1]New UBs'!$J$50 | P23: =StrapScenario2!P23/20 | Q23: =StrapScenario2!Q23
A24: =StrapScenario2!A24 | B24: =StrapScenario2!B24 | C24: =StrapScenario2!C24 | D24: =StrapScenario2!D24*'[1]New UBs'!$J$50 | E24: ='StrapScenario2 Units elec'!E24*0.12 | F24: =L24 | G24: =StrapScenario2!G24 | H24: =StrapScenario2!H24 | I24: =StrapScenario2!I24 | J24: =StrapScenario2!J24 | K24: =StrapScenario2!K24 | L24: =StrapScenario2!L24*'[1]New UBs'!$J$50/1000 | M24: =StrapScenario2!M24*'[1]New UBs'!$J$50 | N24: =StrapScenario2!N24*'[1]New UBs'!$J$50 | O24: =StrapScenario2!O24*'[1]New UBs'!$J$50 | P24: =StrapScenario2!P24/20 | Q24: =StrapScenario2!Q24
A25: =StrapScenario2!A25 | B25: =StrapScenario2!B25 | C25: =StrapScenario2!C25 | D25: =StrapScenario2!D25*'[1]New UBs'!$J$50 | E25: ='StrapScenario2 Units elec'!E25*0.12 | F25: =L25 | G25: =StrapScenario2!G25 | H25: =StrapScenario2!H25 | I25: =StrapScenario2!I25 | J25: =StrapScenario2!J25 | K25: =StrapScenario2!K25 | L25: =StrapScenario2!L25*'[1]New UBs'!$J$50/1000 | M25: =StrapScenario2!M25*'[1]New UBs'!$J$50 | N25: =StrapScenario2!N25*'[1]New UBs'!$J$50 | O25: =StrapScenario2!O25*'[1]New UBs'!$J$50 | P25: =StrapScenario2!P25/20 | Q25: =StrapScenario2!Q25
A26: =StrapScenario2!A26 | B26: =StrapScenario2!B26 | C26: =StrapScenario2!C26 | D26: =StrapScenario2!D26*'[1]New UBs'!$J$50 | E26: ='StrapScenario2 Units elec'!E26*0.12 | F26: =L26 | G26: =StrapScenario2!G26 | H26: =StrapScenario2!H26 | I26: =StrapScenario2!I26 | J26: =StrapScenario2!J26 | K26: =StrapScenario2!K26 | L26: =StrapScenario2!L26*'[1]New UBs'!$J$50/1000 | M26: =StrapScenario2!M26*'[1]New UBs'!$J$50 | N26: =StrapScenario2!N26*'[1]New UBs'!$J$50 | O26: =StrapScenario2!O26*'[1]New UBs'!$J$50 | P26: =StrapScenario2!P26/20 | Q26: =StrapScenario2!Q26
A27: =StrapScenario2!A27 | B27: =StrapScenario2!B27 | C27: =StrapScenario2!C27 | D27: =StrapScenario2!D27*'[1]New UBs'!$J$50 | E27: ='StrapScenario2 Units elec'!E27*0.12 | F27: =L27 | G27: =StrapScenario2!G27 | H27: =StrapScenario2!H27 | I27: =StrapScenario2!I27 | J27: =StrapScenario2!J27 | K27: =StrapScenario2!K27 | L27: =StrapScenario2!L27*'[1]New UBs'!$J$50/1000 | M27: =StrapScenario2!M27*'[1]New UBs'!$J$50 | N27: =StrapScenario2!N27*'[1]New UBs'!$J$50 | O27: =StrapScenario2!O27*'[1]New UBs'!$J$50 | P27: =StrapScenario2!P27/20 | Q27: =StrapScenario2!Q27
A28: =StrapScenario2!A28 | B28: =StrapScenario2!B28 | C28: =StrapScenario2!C28 | D28: =StrapScenario2!D28*'[1]New UBs'!$J$50 | E28: ='StrapScenario2 Units elec'!E28*0.12 | F28: =L28 | G28: =StrapScenario2!G28 | H28: =StrapScenario2!H28 | I28: =StrapScenario2!I28 | J28: =StrapScenario2!J28 | K28: =StrapScenario2!K28 | L28: =StrapScenario2!L28*'[1]New UBs'!$J$50/1000 | M28: =StrapScenario2!M28*'[1]New UBs'!$J$50 | N28: =StrapScenario2!N28*'[1]New UBs'!$J$50 | O28: =StrapScenario2!O28*'[1]New UBs'!$J$50 | P28: =StrapScenario2!P28/20 | Q28: =StrapScenario2!Q28

Sheet StrapScenario2 Units elec
A1: Wash number | B1: Polymer | C1: Solvents | D1: Total Energy Consumed [MJ/yr] | E1: Total Electricity Energy Consumed [MJ/yr] | F1: Total Direct GHG emissions [Scope 1] [metric tons CO2 equivalent [tCO2e/yr]] | G1: Total Energy indirect GHG emissions (Scope 2) [metric tons CO2 equivalent (t CO2e/yr)] | H1: Water consumed/discarded [m3/yr] | I1: Water Recycled or Reused [m3/yr] | J1: Waste generated - Non Hazardous [kg/yr] | K1: Waste to Disposal[ton/yr] | L1: GWP [tonCO2e/yr] | M1: Human toxicity cancer [CTUh/yr] | N1: Human toxicity non-cancer [CTUh/yr] | O1: Ecotoxicity [CTUe/yr] | P1: CAPEX [USD] | Q1: OPEX [USD/yr]
A2: =StrapScenario2!A2 | B2: =StrapScenario2!B2 | C2: =StrapScenario2!C2 | D2: =StrapScenario2!D2*'[1]New UBs'!$E$50 | E2: =StrapScenario2!E2*'[1]New UBs'!$E$50 | F2: =StrapScenario2!F2 | G2: =StrapScenario2!G2 | H2: =StrapScenario2!H2 | I2: =StrapScenario2!I2 | J2: =StrapScenario2!J2 | K2: =StrapScenario2!K2 | L2: =StrapScenario2!L2*'[1]New UBs'!$E$50/1000 | M2: =StrapScenario2!M2*'[1]New UBs'!$E$50 | N2: =StrapScenario2!N2*'[1]New UBs'!$E$50 | O2: =StrapScenario2!O2*'[1]New UBs'!$E$50 | P2: =StrapScenario2!P2 | Q2: =StrapScenario2!Q2
A3: =StrapScenario2!A3 | B3: =StrapScenario2!B3 | C3: =StrapScenario2!C3 | D3: =StrapScenario2!D3*'[1]New UBs'!$E$50 | E3: =StrapScenario2!E3*'[1]New UBs'!$E$50 | F3: =StrapScenario2!F3 | G3: =StrapScenario2!G3 | H3: =StrapScenario2!H3 | I3: =StrapScenario2!I3 | J3: =StrapScenario2!J3 | K3: =StrapScenario2!K3 | L3: =StrapScenario2!L3*'[1]New UBs'!$E$50/1000 | M3: =StrapScenario2!M3*'[1]New UBs'!$E$50 | N3: =StrapScenario2!N3*'[1]New UBs'!$E$50 | O3: =StrapScenario2!O3*'[1]New UBs'!$E$50 | P3: =StrapScenario2!P3 | Q3: =StrapScenario2!Q3
A4: =StrapScenario2!A4 | B4: =StrapScenario2!B4 | C4: =StrapScenario2!C4 | D4: =StrapScenario2!D4*'[1]New UBs'!$E$50 | E4: =StrapScenario2!E4*'[1]New UBs'!$E$50 | F4: =StrapScenario2!F4 | G4: =StrapScenario2!G4 | H4: =StrapScenario2!H4 | I4: =StrapScenario2!I4 | J4: =StrapScenario2!J4 | K4: =StrapScenario2!K4 | L4: =StrapScenario2!L4*'[1]New UBs'!$E$50/1000 | M4: =StrapScenario2!M4*'[1]New UBs'!$E$50 | N4: =StrapScenario2!N4*'[1]New UBs'!$E$50 | O4: =StrapScenario2!O4*'[1]New UBs'!$E$50 | P4: =StrapScenario2!P4 | Q4: =StrapScenario2!Q4
A5: =StrapScenario2!A5 | B5: =StrapScenario2!B5 | C5: =StrapScenario2!C5 | D5: =StrapScenario2!D5*'[1]New UBs'!$E$50 | E5: =StrapScenario2!E5*'[1]New UBs'!$E$50 | F5: =StrapScenario2!F5 | G5: =StrapScenario2!G5 | H5: =StrapScenario2!H5 | I5: =StrapScenario2!I5 | J5: =StrapScenario2!J5 | K5: =StrapScenario2!K5 | L5: =StrapScenario2!L5*'[1]New UBs'!$E$50/1000 | M5: =StrapScenario2!M5*'[1]New UBs'!$E$50 | N5: =StrapScenario2!N5*'[1]New UBs'!$E$50 | O5: =StrapScenario2!O5*'[1]New UBs'!$E$50 | P5: =StrapScenario2!P5 | Q5: =StrapScenario2!Q5
A6: =StrapScenario2!A6 | B6: =StrapScenario2!B6 | C6: =StrapScenario2!C6 | D6: =StrapScenario2!D6*'[1]New UBs'!$E$50 | E6: =StrapScenario2!E6*'[1]New UBs'!$E$50 | F6: =StrapScenario2!F6 | G6: =StrapScenario2!G6 | H6: =StrapScenario2!H6 | I6: =StrapScenario2!I6 | J6: =StrapScenario2!J6 | K6: =StrapScenario2!K6 | L6: =StrapScenario2!L6*'[1]New UBs'!$E$50/1000 | M6: =StrapScenario2!M6*'[1]New UBs'!$E$50 | N6: =StrapScenario2!N6*'[1]New UBs'!$E$50 | O6: =StrapScenario2!O6*'[1]New UBs'!$E$50 | P6: =StrapScenario2!P6 | Q6: =StrapScenario2!Q6
A7: =StrapScenario2!A7 | B7: =StrapScenario2!B7 | C7: =StrapScenario2!C7 | D7: =StrapScenario2!D7*'[1]New UBs'!$E$50 | E7: =StrapScenario2!E7*'[1]New UBs'!$E$50 | F7: =StrapScenario2!F7 | G7: =StrapScenario2!G7 | H7: =StrapScenario2!H7 | I7: =StrapScenario2!I7 | J7: =StrapScenario2!J7 | K7: =StrapScenario2!K7 | L7: =StrapScenario2!L7*'[1]New UBs'!$E$50/1000 | M7: =StrapScenario2!M7*'[1]New UBs'!$E$50 | N7: =StrapScenario2!N7*'[1]New UBs'!$E$50 | O7: =StrapScenario2!O7*'[1]New UBs'!$E$50 | P7: =StrapScenario2!P7 | Q7: =StrapScenario2!Q7
A8: =StrapScenario2!A8 | B8: =StrapScenario2!B8 | C8: =StrapScenario2!C8 | D8: =StrapScenario2!D8*'[1]New UBs'!$E$50 | E8: =StrapScenario2!E8*'[1]New UBs'!$E$50 | F8: =StrapScenario2!F8 | G8: =StrapScenario2!G8 | H8: =StrapScenario2!H8 | I8: =StrapScenario2!I8 | J8: =StrapScenario2!J8 | K8: =StrapScenario2!K8 | L8: =StrapScenario2!L8*'[1]New UBs'!$E$50/1000 | M8: =StrapScenario2!M8*'[1]New UBs'!$E$50 | N8: =StrapScenario2!N8*'[1]New UBs'!$E$50 | O8: =StrapScenario2!O8*'[1]New UBs'!$E$50 | P8: =StrapScenario2!P8 | Q8: =StrapScenario2!Q8
A9: =StrapScenario2!A9 | B9: =StrapScenario2!B9 | C9: =StrapScenario2!C9 | D9: =StrapScenario2!D9*'[1]New UBs'!$E$50 | E9: =StrapScenario2!E9*'[1]New UBs'!$E$50 | F9: =StrapScenario2!F9 | G9: =StrapScenario2!G9 | H9: =StrapScenario2!H9 | I9: =StrapScenario2!I9 | J9: =StrapScenario2!J9 | K9: =StrapScenario2!K9 | L9: =StrapScenario2!L9*'[1]New UBs'!$E$50/1000 | M9: =StrapScenario2!M9*'[1]New UBs'!$E$50 | N9: =StrapScenario2!N9*'[1]New UBs'!$E$50 | O9: =StrapScenario2!O9*'[1]New UBs'!$E$50 | P9: =StrapScenario2!P9 | Q9: =StrapScenario2!Q9
A10: =StrapScenario2!A10 | B10: =StrapScenario2!B10 | C10: =StrapScenario2!C10 | D10: =StrapScenario2!D10*'[1]New UBs'!$E$50 | E10: =StrapScenario2!E10*'[1]New UBs'!$E$50 | F10: =StrapScenario2!F10 | G10: =StrapScenario2!G10 | H10: =StrapScenario2!H10 | I10: =StrapScenario2!I10 | J10: =StrapScenario2!J10 | K10: =StrapScenario2!K10 | L10: =StrapScenario2!L10*'[1]New UBs'!$E$50/1000 | M10: =StrapScenario2!M10*'[1]New UBs'!$E$50 | N10: =StrapScenario2!N10*'[1]New UBs'!$E$50 | O10: =StrapScenario2!O10*'[1]New UBs'!$E$50 | P10: =StrapScenario2!P10 | Q10: =StrapScenario2!Q10
A11: =StrapScenario2!A11 | B11: =StrapScenario2!B11 | C11: =StrapScenario2!C11 | D11: =StrapScenario2!D11*'[1]New UBs'!$E$51 | E11: =StrapScenario2!E11*'[1]New UBs'!$E$51 | F11: =StrapScenario2!F11 | G11: =StrapScenario2!G11 | H11: =StrapScenario2!H11 | I11: =StrapScenario2!I11 | J11: =StrapScenario2!J11 | K11: =StrapScenario2!K11 | L11: =StrapScenario2!L11*'[1]New UBs'!$E$51/1000 | M11: =StrapScenario2!M11*'[1]New UBs'!$E$51 | N11: =StrapScenario2!N11*'[1]New UBs'!$E$51 | O11: =StrapScenario2!O11*'[1]New UBs'!$E$51 | P11: =StrapScenario2!P11 | Q11: =StrapScenario2!Q11
A12: =StrapScenario2!A12 | B12: =StrapScenario2!B12 | C12: =StrapScenario2!C12 | D12: =StrapScenario2!D12*'[1]New UBs'!$E$51 | E12: =StrapScenario2!E12*'[1]New UBs'!$E$51 | F12: =StrapScenario2!F12 | G12: =StrapScenario2!G12 | H12: =StrapScenario2!H12 | I12: =StrapScenario2!I12 | J12: =StrapScenario2!J12 | K12: =StrapScenario2!K12 | L12: =StrapScenario2!L12*'[1]New UBs'!$E$51/1000 | M12: =StrapScenario2!M12*'[1]New UBs'!$E$51 | N12: =StrapScenario2!N12*'[1]New UBs'!$E$51 | O12: =StrapScenario2!O12*'[1]New UBs'!$E$51 | P12: =StrapScenario2!P12 | Q12: =StrapScenario2!Q12
A13: =StrapScenario2!A13 | B13: =StrapScenario2!B13 | C13: =StrapScenario2!C13 | D13: =StrapScenario2!D13*'[1]New UBs'!$J$51 | E13: =StrapScenario2!E13*'[1]New UBs'!$J$51 | F13: =StrapScenario2!F13 | G13: =StrapScenario2!G13 | H13: =StrapScenario2!H13 | I13: =StrapScenario2!I13 | J13: =StrapScenario2!J13 | K13: =StrapScenario2!K13 | L13: =StrapScenario2!L13*'[1]New UBs'!$J$51/1000 | M13: =StrapScenario2!M13*'[1]New UBs'!$J$51 | N13: =StrapScenario2!N13*'[1]New UBs'!$J$51 | O13: =StrapScenario2!O13*'[1]New UBs'!$J$51 | P13: =StrapScenario2!P13 | Q13: =StrapScenario2!Q13
A14: =StrapScenario2!A14 | B14: =StrapScenario2!B14 | C14: =StrapScenario2!C14 | D14: =StrapScenario2!D14*'[1]New UBs'!$J$51 | E14: =StrapScenario2!E14*'[1]New UBs'!$J$51 | F14: =StrapScenario2!F14 | G14: =StrapScenario2!G14 | H14: =StrapScenario2!H14 | I14: =StrapScenario2!I14 | J14: =StrapScenario2!J14 | K14: =StrapScenario2!K14 | L14: =StrapScenario2!L14*'[1]New UBs'!$J$51/1000 | M14: =StrapScenario2!M14*'[1]New UBs'!$J$51 | N14: =StrapScenario2!N14*'[1]New UBs'!$J$51 | O14: =StrapScenario2!O14*'[1]New UBs'!$J$51 | P14: =StrapScenario2!P14 | Q14: =StrapScenario2!Q14
A15: =StrapScenario2!A15 | B15: =StrapScenario2!B15 | C15: =StrapScenario2!C15 | D15: =StrapScenario2!D15*'[1]New UBs'!$J$51 | E15: =StrapScenario2!E15*'[1]New UBs'!$J$51 | F15: =StrapScenario2!F15 | G15: =StrapScenario2!G15 | H15: =StrapScenario2!H15 | I15: =StrapScenario2!I15 | J15: =StrapScenario2!J15 | K15: =StrapScenario2!K15 | L15: =StrapScenario2!L15*'[1]New UBs'!$J$51/1000 | M15: =StrapScenario2!M15*'[1]New UBs'!$J$51 | N15: =StrapScenario2!N15*'[1]New UBs'!$J$51 | O15: =StrapScenario2!O15*'[1]New UBs'!$J$51 | P15: =StrapScenario2!P15 | Q15: =StrapScenario2!Q15
A16: =StrapScenario2!A16 | B16: =StrapScenario2!B16 | C16: =StrapScenario2!C16 | D16: =StrapScenario2!D16*'[1]New UBs'!$J$51 | E16: =StrapScenario2!E16*'[1]New UBs'!$J$51 | F16: =StrapScenario2!F16 | G16: =StrapScenario2!G16 | H16: =StrapScenario2!H16 | I16: =StrapScenario2!I16 | J16: =StrapScenario2!J16 | K16: =StrapScenario2!K16 | L16: =StrapScenario2!L16*'[1]New UBs'!$J$51/1000 | M16: =StrapScenario2!M16*'[1]New UBs'!$J$51 | N16: =StrapScenario2!N16*'[1]New UBs'!$J$51 | O16: =StrapScenario2!O16*'[1]New UBs'!$J$51 | P16: =StrapScenario2!P16 | Q16: =StrapScenario2!Q16
A17: =StrapScenario2!A17 | B17: =StrapScenario2!B17 | C17: =StrapScenario2!C17 | D17: =StrapScenario2!D17*'[1]New UBs'!$J$51 | E17: =StrapScenario2!E17*'[1]New UBs'!$J$51 | F17: =StrapScenario2!F17 | G17: =StrapScenario2!G17 | H17: =StrapScenario2!H17 | I17: =StrapScenario2!I17 | J17: =StrapScenario2!J17 | K17: =StrapScenario2!K17 | L17: =StrapScenario2!L17*'[1]New UBs'!$J$51/1000 | M17: =StrapScenario2!M17*'[1]New UBs'!$J$51 | N17: =StrapScenario2!N17*'[1]New UBs'!$J$51 | O17: =StrapScenario2!O17*'[1]New UBs'!$J$51 | P17: =StrapScenario2!P17 | Q17: =StrapScenario2!Q17
A18: =StrapScenario2!A18 | B18: =StrapScenario2!B18 | C18: =StrapScenario2!C18 | D18: =StrapScenario2!D18*'[1]New UBs'!$J$51 | E18: =StrapScenario2!E18*'[1]New UBs'!$J$51 | F18: =StrapScenario2!F18 | G18: =StrapScenario2!G18 | H18: =StrapScenario2!H18 | I18: =StrapScenario2!I18 | J18: =StrapScenario2!J18 | K18: =StrapScenario2!K18 | L18: =StrapScenario2!L18*'[1]New UBs'!$J$51/1000 | M18: =StrapScenario2!M18*'[1]New UBs'!$J$51 | N18: =StrapScenario2!N18*'[1]New UBs'!$J$51 | O18: =StrapScenario2!O18*'[1]New UBs'!$J$51 | P18: =StrapScenario2!P18 | Q18: =StrapScenario2!Q18
A19: =StrapScenario2!A19 | B19: =StrapScenario2!B19 | C19: =StrapScenario2!C19 | D19: =StrapScenario2!D19*'[1]New UBs'!$J$51 | E19: =StrapScenario2!E19*'[1]New UBs'!$J$51 | F19: =StrapScenario2!F19 | G19: =StrapScenario2!G19 | H19: =StrapScenario2!H19 | I19: =StrapScenario2!I19 | J19: =StrapScenario2!J19 | K19: =StrapScenario2!K19 | L19: =StrapScenario2!L19*'[1]New UBs'!$J$51/1000 | M19: =StrapScenario2!M19*'[1]New UBs'!$J$51 | N19: =StrapScenario2!N19*'[1]New UBs'!$J$51 | O19: =StrapScenario2!O19*'[1]New UBs'!$J$51 | P19: =StrapScenario2!P19 | Q19: =StrapScenario2!Q19
A20: =StrapScenario2!A20 | B20: =StrapScenario2!B20 | C20: =StrapScenario2!C20 | D20: =StrapScenario2!D20*'[1]New UBs'!$J$51 | E20: =StrapScenario2!E20*'[1]New UBs'!$J$51 | F20: =StrapScenario2!F20 | G20: =StrapScenario2!G20 | H20: =StrapScenario2!H20 | I20: =StrapScenario2!I20 | J20: =StrapScenario2!J20 | K20: =StrapScenario2!K20 | L20: =StrapScenario2!L20*'[1]New UBs'!$J$51/1000 | M20: =StrapScenario2!M20*'[1]New UBs'!$J$51 | N20: =StrapScenario2!N20*'[1]New UBs'!$J$51 | O20: =StrapScenario2!O20*'[1]New UBs'!$J$51 | P20: =StrapScenario2!P20 | Q20: =StrapScenario2!Q20
A21: =StrapScenario2!A21 | B21: =StrapScenario2!B21 | C21: =StrapScenario2!C21 | D21: =StrapScenario2!D21*'[1]New UBs'!$J$51 | E21: =StrapScenario2!E21*'[1]New UBs'!$J$51 | F21: =StrapScenario2!F21 | G21: =StrapScenario2!G21 | H21: =StrapScenario2!H21 | I21: =StrapScenario2!I21 | J21: =StrapScenario2!J21 | K21: =StrapScenario2!K21 | L21: =StrapScenario2!L21*'[1]New UBs'!$J$51/1000 | M21: =StrapScenario2!M21*'[1]New UBs'!$J$51 | N21: =StrapScenario2!N21*'[1]New UBs'!$J$51 | O21: =StrapScenario2!O21*'[1]New UBs'!$J$51 | P21: =StrapScenario2!P21 | Q21: =StrapScenario2!Q21
A22: =StrapScenario2!A22 | B22: =StrapScenario2!B22 | C22: =StrapScenario2!C22 | D22: =StrapScenario2!D22*'[1]New UBs'!$J$50 | E22: =StrapScenario2!E22*'[1]New UBs'!$J$50 | F22: =StrapScenario2!F22 | G22: =StrapScenario2!G22 | H22: =StrapScenario2!H22 | I22: =StrapScenario2!I22 | J22: =StrapScenario2!J22 | K22: =StrapScenario2!K22 | L22: =StrapScenario2!L22*'[1]New UBs'!$J$50/1000 | M22: =StrapScenario2!M22*'[1]New UBs'!$J$50 | N22: =StrapScenario2!N22*'[1]New UBs'!$J$50 | O22: =StrapScenario2!O22*'[1]New UBs'!$J$50 | P22: =StrapScenario2!P22 | Q22: =StrapScenario2!Q22
A23: =StrapScenario2!A23 | B23: =StrapScenario2!B23 | C23: =StrapScenario2!C23 | D23: =StrapScenario2!D23*'[1]New UBs'!$J$50 | E23: =StrapScenario2!E23*'[1]New UBs'!$J$50 | F23: =StrapScenario2!F23 | G23: =StrapScenario2!G23 | H23: =StrapScenario2!H23 | I23: =StrapScenario2!I23 | J23: =StrapScenario2!J23 | K23: =StrapScenario2!K23 | L23: =StrapScenario2!L23*'[1]New UBs'!$J$50/1000 | M23: =StrapScenario2!M23*'[1]New UBs'!$J$50 | N23: =StrapScenario2!N23*'[1]New UBs'!$J$50 | O23: =StrapScenario2!O23*'[1]New UBs'!$J$50 | P23: =StrapScenario2!P23 | Q23: =StrapScenario2!Q23
A24: =StrapScenario2!A24 | B24: =StrapScenario2!B24 | C24: =StrapScenario2!C24 | D24: =StrapScenario2!D24*'[1]New UBs'!$J$50 | E24: =StrapScenario2!E24*'[1]New UBs'!$J$50 | F24: =StrapScenario2!F24 | G24: =StrapScenario2!G24 | H24: =StrapScenario2!H24 | I24: =StrapScenario2!I24 | J24: =StrapScenario2!J24 | K24: =StrapScenario2!K24 | L24: =StrapScenario2!L24*'[1]New UBs'!$J$50/1000 | M24: =StrapScenario2!M24*'[1]New UBs'!$J$50 | N24: =StrapScenario2!N24*'[1]New UBs'!$J$50 | O24: =StrapScenario2!O24*'[1]New UBs'!$J$50 | P24: =StrapScenario2!P24 | Q24: =StrapScenario2!Q24
A25: =StrapScenario2!A25 | B25: =StrapScenario2!B25 | C25: =StrapScenario2!C25 | D25: =StrapScenario2!D25*'[1]New UBs'!$J$50 | E25: =StrapScenario2!E25*'[1]New UBs'!$J$50 | F25: =StrapScenario2!F25 | G25: =StrapScenario2!G25 | H25: =StrapScenario2!H25 | I25: =StrapScenario2!I25 | J25: =StrapScenario2!J25 | K25: =StrapScenario2!K25 | L25: =StrapScenario2!L25*'[1]New UBs'!$J$50/1000 | M25: =StrapScenario2!M25*'[1]New UBs'!$J$50 | N25: =StrapScenario2!N25*'[1]New UBs'!$J$50 | O25: =StrapScenario2!O25*'[1]New UBs'!$J$50 | P25: =StrapScenario2!P25 | Q25: =StrapScenario2!Q25
A26: =StrapScenario2!A26 | B26: =StrapScenario2!B26 | C26: =StrapScenario2!C26 | D26: =StrapScenario2!D26*'[1]New UBs'!$J$50 | E26: =StrapScenario2!E26*'[1]New UBs'!$J$50 | F26: =StrapScenario2!F26 | G26: =StrapScenario2!G26 | H26: =StrapScenario2!H26 | I26: =StrapScenario2!I26 | J26: =StrapScenario2!J26 | K26: =StrapScenario2!K26 | L26: =StrapScenario2!L26*'[1]New UBs'!$J$50/1000 | M26: =StrapScenario2!M26*'[1]New UBs'!$J$50 | N26: =StrapScenario2!N26*'[1]New UBs'!$J$50 | O26: =StrapScenario2!O26*'[1]New UBs'!$J$50 | P26: =StrapScenario2!P26 | Q26: =StrapScenario2!Q26
A27: =StrapScenario2!A27 | B27: =StrapScenario2!B27 | C27: =StrapScenario2!C27 | D27: =StrapScenario2!D27*'[1]New UBs'!$J$50 | E27: =StrapScenario2!E27*'[1]New UBs'!$J$50 | F27: =StrapScenario2!F27 | G27: =StrapScenario2!G27 | H27: =StrapScenario2!H27 | I27: =StrapScenario2!I27 | J27: =StrapScenario2!J27 | K27: =StrapScenario2!K27 | L27: =StrapScenario2!L27*'[1]New UBs'!$J$50/1000 | M27: =StrapScenario2!M27*'[1]New UBs'!$J$50 | N27: =StrapScenario2!N27*'[1]New UBs'!$J$50 | O27: =StrapScenario2!O27*'[1]New UBs'!$J$50 | P27: =StrapScenario2!P27 | Q27: =StrapScenario2!Q27
A28: =StrapScenario2!A28 | B28: =StrapScenario2!B28 | C28: =StrapScenario2!C28 | D28: =StrapScenario2!D28*'[1]New UBs'!$J$50 | E28: =StrapScenario2!E28*'[1]New UBs'!$J$50 | F28: =StrapScenario2!F28 | G28: =StrapScenario2!G28 | H28: =StrapScenario2!H28 | I28: =StrapScenario2!I28 | J28: =StrapScenario2!J28 | K28: =StrapScenario2!K28 | L28: =StrapScenario2!L28*'[1]New UBs'!$J$50/1000 | M28: =StrapScenario2!M28*'[1]New UBs'!$J$50 | N28: =StrapScenario2!N28*'[1]New UBs'!$J$50 | O28: =StrapScenario2!O28*'[1]New UBs'!$J$50 | P28: =StrapScenario2!P28 | Q28: =StrapScenario2!Q28

Sheet StrapScenario3 Units
A1: Wash number | B1: Polymer | C1: Solvents | D1: Total Energy Consumed [MJ/yr] | E1: Total Renewable Energy Consumed [MJ/yr] | F1: Total Direct GHG emissions [Scope 1] [metric tons CO2 equivalent [tCO2e/yr]] | G1: Total Energy indirect GHG emissions (Scope 2) [metric tons CO2 equivalent (t CO2e/yr)] | H1: Water consumed/discarded [m3/yr] | I1: Water Recycled or Reused [m3/yr] | J1: Waste generated - Non Hazardous [kg/yr] | K1: Waste to Disposal[ton/yr] | L1: GWP [tonCO2e/yr] | M1: Human toxicity cancer [CTUh/yr] | N1: Human toxicity non-cancer [CTUh/yr] | O1: Ecotoxicity [CTUe/yr] | P1: CAPEX [USD/yr] | Q1: OPEX [USD/yr]
A2: Wash 1 | B2: PE | C2: sec-Butyl Acetate | D2: 6.6521825e+11 | E2: 2642745.6 | F2: 15666.63 | G2: 0 | H2: 0 | I2: 52120.53 | J2: 0 | K2: 0 | L2: 15666.63 | M2: 0.59015726 | N2: 0.28498136 | O2: 15918579 | P2: 1645223.1 | Q2: 2275162.4
A3: Wash 1 | B3: PE | C3: Isobutyl Acetate | D3: 6.6652583e+11 | E3: 2642745.6 | F3: 15662.4 | G3: 0 | H3: 0 | I3: 51205.64 | J3: 0 | K3: 0 | L3: 15662.4 | M3: 0.590005 | N3: 0.28491598 | O3: 15914784 | P3: 1649512.2 | Q3: 2276812.1
A4: Wash 1 | B4: PE | C4: Tetrachloroethylene | D4: 6.2523212e+11 | E4: 2536588.8 | F4: 13455.959 | G4: 0 | H4: 0 | I4: 25637.89 | J4: 0 | K4: 0 | L4: 13455.959 | M4: 0.50657794 | N4: 0.24454396 | O4: 13656017 | P4: 1376265.7 | Q4: 2154028.1
A5: Wash 1 | B5: PE | C5: o-Chlorotoluene | D5: 6.5992671e+11 | E5: 2637158.4 | F5: 16057.665 | G5: 0 | H5: 0 | I5: 63368.91 | J5: 0 | K5: 0 | L5: 16057.665 | M5: 0.60486122 | N5: 0.29202407 | O5: 16314268 | P5: 1588570.2 | Q5: 2254600.6
A6: Wash 1 | B6: PE | C6: Methylcyclohexane | D6: 6.6691264e+11 | E6: 2637158.4 | F6: 15152.843 | G6: 0 | H6: 0 | I6: 42251.83 | J6: 0 | K6: 0 | L6: 15152.843 | M6: 0.57066354 | N6: 0.27543784 | O6: 15388133 | P6: 1674069.7 | Q6: 2284592.1
A7: Wash 1 | B7: PE | C7: Dodecanol | D7: 7.2781895e+11 | E7: 2866233.6 | F7: 23554.245 | G7: 0 | H7: 0 | I7: 173624.6 | J7: 0 | K7: 0 | L7: 23554.245 | M7: 0.88764102 | N7: 0.42929682 | O7: 23969106 | P7: 1894036.4 | Q7: 2442006.5
A8: Wash 1 | B8: PE | C8: Heptane | D8: 6.7721357e+11 | E8: 2659507.2 | F8: 15568.819 | G8: 0 | H8: 0 | I8: 44810.07 | J8: 0 | K8: 0 | L8: 15568.819 | M8: 0.58628609 | N8: 0.2829332 | O8: 15806839 | P8: 1746245.1 | Q8: 2316306.6
A9: Wash 1 | B9: PE | C9: Toluene | D9: 6.5999002e+11 | E9: 2720966.4 | F9: 15074.547 | G9: 0 | H9: 0 | I9: 54056.42 | J9: 0 | K9: 0 | L9: 15074.547 | M9: 0.56767017 | N9: 0.27395049 | O9: 15304639 | P9: 1935089.6 | Q9: 2416886.2
A10: Wash 1 | B10: PE | C10: Xylene | D10: 6.7072532e+11 | E10: 2659507.2 | F10: 16369.414 | G10: 0 | H10: 0 | I10: 64966.4 | J10: 0 | K10: 0 | L10: 16369.414 | M10: 0.61650573 | N10: 0.29752124 | O10: 16621969 | P10: 1661215.8 | Q10: 2285841
A11: Wash 1 | B11: EVOH | C11: Ethylene Glycol | D11: 8.9342761e+10 | E11: 616454.4 | F11: 2529.7734 | G11: 0 | H11: 0 | I11: 120119.92 | J11: 0 | K11: 0 | L11: 2529.7734 | M11: 0.095309956 | N11: 0.046009105 | O11: 2570524 | P11: 827574.62 | Q11: 1652694.1
A12: Wash 1 | B12: EVOH | C12: Pyridazine | D12: 8.8149477e+10 | E12: 586656 | F12: 2253.3804 | G12: 0 | H12: 0 | I12: 71782.02 | J12: 0 | K12: 0 | L12: 2253.3804 | M12: 0.084943522 | N12: 0.041079847 | O12: 2297013.6 | P12: 831337.12 | Q12: 1648470.3
A13: Wash 2 | B13: PE | C13: sec-Butyl Acetate | D13: 6.6521825e+11 | E13: 2637158.4 | F13: 15666.63 | G13: 0 | H13: 0 | I13: 49212.73 | J13: 0 | K13: 0 | L13: 15666.63 | M13: 0.59015726 | N13: 0.28498136 | O13: 15918579 | P13: 1640984.4 | Q13: 2267582.9
... A28: Wash 2 | B28: EVOH | C28: gamma-butyrolactone | D28: 8.7293359e+10 | E28: 490742.4 | F28: 2273.9629 | G28: 0 | H28: 0 | I28: 30701.09 | J28: 0 | K28: 0 | L28: 2273.9629 | M28: 0.085678462 | N28: 0.041383928 | O28: 2311690.7 | P28: 650094.78 | Q28: 1520227.7

Sheet Othertech w TransportA
A1: Technology | B1: ='[1]Final Data (use this)'!E3 | C1: ='[1]Final Data (use this)'!F3 | D1: ='[1]Final Data (use this)'!H3 | E1: ='[1]Final Data (use this)'!I3 | F1: ='[1]Final Data (use this)'!L3 | G1: ='[1]Final Data (use this)'!M3 | H1: ='[1]Final Data (use this)'!O3 | I1: ='[1]Final Data (use this)'!P3 | J1: ='[1]Final Data (use this)'!R3 | K1: Human toxicity cancer [CTUh/ton resin] | L1: Human toxicity non-cancer [CTUh/ton resin] | M1: Ecotoxicity [CTUe/ton resin] | N1: CAPEX [USD/yr] | O1: OPEX [USD/ton]
A2: ='[1]Final Data (use this)'!D7 | B2: ='[1]Final Data (use this)'!E7+'[12]CE Index Scenarios COMPLETE)'!$J$2*9.2 | C2: ='[1]Final Data (use this)'!F7 | D2: =J2 | E2: ='[1]Final Data (use this)'!I7 | F2: ='[1]Final Data (use this)'!J7 | G2: ='[1]Final Data (use this)'!K7 | H2: 0 | I2: 1 | J2: =0.0816+0.328/(1000*0.621371)*9.2 | K2: =0.00000000612*1000 | L2: =0.000000808*1000 | M2: =45*1000 | N2: 0 | O2: 7.83599
A3: ='[1]Final Data (use this)'!D8 | B3: ='[1]Final Data (use this)'!E8+'[12]CE Index Scenarios COMPLETE)'!$J$2*151 | C3: =252*0.12 | D3: =J3 | E3: ='[1]Final Data (use this)'!I8 | F3: 1.81 | G3: 1.81 | H3: 0.1 | I3: ='[1]Final Data (use this)'!M8 | J3: =2.38+0.328/(1000*0.621371)*151 | K3: =0.0000000794*1000 | L3: =0.000000367*1000 | M3: =44.7*1000 | N3: 0 | O3: 0
A4: ='[1]Final Data (use this)'!D9 | B4: ='[1]Final Data (use this)'!E9+'[12]CE Index Scenarios COMPLETE)'!$J$2*1034 | C4: ='[1]Final Data (use this)'!F9+C5 | D4: =J4 | E4: ='[1]Final Data (use this)'!I9 | F4: ='[1]Final Data (use this)'!J9+F5 | G4: ='[1]Final Data (use this)'!K9+G5 | H4: 250 | I4: ='[1]Final Data (use this)'!M9+I5 | J4: ='[1]Final Data (use this)'!N9+0.41/(1000*0.621371)*1034 | K4: ='[1]Final Data (use this)'!O9 | L4: ='[1]Final Data (use this)'!P9 | M4: ='[1]Final Data (use this)'!Q9 | N4: ='[1]Final Data (use this)'!T9 | O4: 153.4067
A5: Gasif. For Energy Recovery | B5: =4976.445044+'[12]CE Index Scenarios COMPLETE)'!$J$2*0 | C5: =[13]Gasification_Technologies!$D$2 | D5: =J5 | E5: 0 | F5: =[13]Gasification_Technologies!H2 | G5: =[13]Gasification_Technologies!I2 | H5: 387.663 | I5: 0 | J5: =[13]Gasification_Technologies!M2+0.328/(1000*0.621371)*0 | K5: =[13]Gasification_Technologies!N2 | L5: =[13]Gasification_Technologies!O2 | M5: =[13]Gasification_Technologies!P2 | N5: =[13]Gasification_Technologies!$T$2*1000000 | O5: =[13]Gasification_Technologies!$X$2
A6: Gasif. For H2 | B6: =6182.35294117647+'[12]CE Index Scenarios COMPLETE)'!$J$2*2036 | C6: =[13]Gasification_Technologies!$D$3 | D6: =J6 | E6: 0 | F6: =[13]Gasification_Technologies!H3 | G6: =[13]Gasification_Technologies!I3 | H6: 820.91503 | I6: 0 | J6: =[13]Gasification_Technologies!M3+0.41/(1000*0.621371)*2036 | K6: =[13]Gasification_Technologies!N3 | L6: =[13]Gasification_Technologies!O3 | M6: =[13]Gasification_Technologies!P3 | N6: 0 | O6: 0
A7: Gasif. For H2 + CCS | B7: =7557.64705882353+'[12]CE Index Scenarios COMPLETE)'!$J$2*2036 | C7: =[13]Gasification_Technologies!$D$4 | D7: =J7 | E7: 0 | F7: =[13]Gasification_Technologies!H4 | G7: =[13]Gasification_Technologies!I4 | H7: 1046.4052 | I7: 0 | J7: =[13]Gasification_Technologies!M4+0.41/(1000*0.621371)*2036 | K7: =[13]Gasification_Technologies!N4 | L7: =[13]Gasification_Technologies!O4 | M7: =[13]Gasification_Technologies!P4 | N7: 0 | O7: 0

Sheet Othertech w TransportB
A1: Technology | B1: ='[1]Final Data (use this)'!E3 | C1: ='[1]Final Data (use this)'!F3 | D1: ='[1]Final Data (use this)'!H3 | E1: ='[1]Final Data (use this)'!I3 | F1: ='[1]Final Data (use this)'!L3 | G1: ='[1]Final Data (use this)'!M3 | H1: ='[1]Final Data (use this)'!O3 | I1: ='[1]Final Data (use this)'!P3 | J1: ='[1]Final Data (use this)'!R3 | K1: Human toxicity cancer [CTUh/ton resin] | L1: Human toxicity non-cancer [CTUh/ton resin] | M1: Ecotoxicity [CTUe/ton resin] | N1: CAPEX [USD/yr] | O1: OPEX [USD/ton]
A2: ='[1]Final Data (use this)'!D7 | B2: ='[1]Final Data (use this)'!E7+'[12]CE Index Scenarios COMPLETE)'!$J$2*9.2 | C2: ='[1]Final Data (use this)'!F7 | D2: =J2 | E2: ='[1]Final Data (use this)'!I7 | F2: ='[1]Final Data (use this)'!J7 | G2: ='[1]Final Data (use this)'!K7 | H2: 0 | I2: 1 | J2: =0.0816+0.328/(1000*0.621371)*9.2 | K2: =0.00000000612*1000 | L2: =0.000000808*1000 | M2: =45*1000 | N2: 0 | O2: 7.83599
A3: ='[1]Final Data (use this)'!D8 | B3: ='[1]Final Data (use this)'!E8+'[12]CE Index Scenarios COMPLETE)'!$J$2*151 | C3: =252*0.12 | D3: =J3 | E3: ='[1]Final Data (use this)'!I8 | F3: 1.81 | G3: 1.81 | H3: 0.1 | I3: ='[1]Final Data (use this)'!M8 | J3: =2.38+0.328/(1000*0.621371)*151 | K3: =0.0000000794*1000 | L3: =0.000000367*1000 | M3: =44.7*1000 | N3: 0 | O3: 0
A4: ='[1]Final Data (use this)'!D9 | B4: ='[1]Final Data (use this)'!E9+'[12]CE Index Scenarios COMPLETE)'!$J$2*76.1 | C4: ='[1]Final Data (use this)'!F9+C5 | D4: =J4 | E4: ='[1]Final Data (use this)'!I9 | F4: ='[1]Final Data (use this)'!J9+F5 | G4: ='[1]Final Data (use this)'!K9+G5 | H4: 250 | I4: ='[1]Final Data (use this)'!M9+I5 | J4: ='[1]Final Data (use this)'!N9+0.41/(1000*0.621371)*76.1 | K4: ='[1]Final Data (use this)'!O9 | L4: ='[1]Final Data (use this)'!P9 | M4: ='[1]Final Data (use this)'!Q9 | N4: ='[1]Final Data (use this)'!T9 | O4: 153.4067
A5: Gasif. For Energy Recovery | B5: =4976.445044+'[12]CE Index Scenarios COMPLETE)'!$J$2*0 | C5: =[13]Gasification_Technologies!$D$2 | D5: =J5 | E5: 0 | F5: =[13]Gasification_Technologies!H2 | G5: =[13]Gasification_Technologies!I2 | H5: 387.663 | I5: 0 | J5: =[13]Gasification_Technologies!M2+0.328/(1000*0.621371)*0 | K5: =[13]Gasification_Technologies!N2 | L5: =[13]Gasification_Technologies!O2 | M5: =[13]Gasification_Technologies!P2 | N5: =[13]Gasification_Technologies!$T$2*1000000 | O5: =[13]Gasification_Technologies!$X$2
A6: Gasif. For H2 | B6: =6182.35294117647+'[12]CE Index Scenarios COMPLETE)'!$J$2*76.1 | C6: =[13]Gasification_Technologies!$D$3 | D6: =J6 | E6: 0 | F6: =[13]Gasification_Technologies!H3 | G6: =[13]Gasification_Technologies!I3 | H6: 820.91503 | I6: 0 | J6: =[13]Gasification_Technologies!M3+0.41/(1000*0.621371)*76.1 | K6: =[13]Gasification_Technologies!N3 | L6: =[13]Gasification_Technologies!O3 | M6: =[13]Gasification_Technologies!P3 | N6: 0 | O6: 0
A7: Gasif. For H2 + CCS | B7: =7557.64705882353+'[12]CE Index Scenarios COMPLETE)'!$J$2*76.1 | C7: =[13]Gasification_Technologies!$D$4 | D7: =J7 | E7: 0 | F7: =[13]Gasification_Technologies!H4 | G7: =[13]Gasification_Technologies!I4 | H7: 1046.4052 | I7: 0 | J7: =[13]Gasification_Technologies!M4+0.41/(1000*0.621371)*76.1 | K7: =[13]Gasification_Technologies!N4 | L7: =[13]Gasification_Technologies!O4 | M7: =[13]Gasification_Technologies!P4 | N7: 0 | O7: 0

Sheet Othertech
A1: Technology | B1: ='[1]Final Data (use this)'!E3 | C1: ='[1]Final Data (use this)'!F3 | D1: ='[1]Final Data (use this)'!H3 | E1: ='[1]Final Data (use this)'!I3 | F1: ='[1]Final Data (use this)'!L3 | G1: ='[1]Final Data (use this)'!M3 | H1: ='[1]Final Data (use this)'!O3 | I1: ='[1]Final Data (use this)'!P3 | J1: ='[1]Final Data (use this)'!R3 | K1: Human toxicity cancer [CTUh/ton resin] | L1: Human toxicity non-cancer [CTUh/ton resin] | M1: Ecotoxicity [CTUe/ton resin] | N1: CAPEX [USD/yr] | O1: OPEX [USD/ton]
A2: ='[1]Final Data (use this)'!D7 | B2: ='[1]Final Data (use this)'!E7 | C2: ='[1]Final Data (use this)'!F7 | D2: =J2 | E2: ='[1]Final Data (use this)'!I7 | F2: ='[1]Final Data (use this)'!J7 | G2: ='[1]Final Data (use this)'!K7 | H2: 0 | I2: 1 | J2: 0.0816 | K2: =0.00000000612*1000 | L2: =0.000000808*1000 | M2: =45*1000 | N2: 0 | O2: 7.83599
A3: ='[1]Final Data (use this)'!D8 | B3: ='[1]Final Data (use this)'!E8 | C3: =252*0.12 | D3: =J3 | E3: ='[1]Final Data (use this)'!I8 | F3: 1.81 | G3: 1.81 | H3: 0.1 | I3: ='[1]Final Data (use this)'!M8 | J3: 2.38 | K3: =0.0000000794*1000 | L3: =0.000000367*1000 | M3: =44.7*1000 | N3: 0 | O3: 0
A4: ='[1]Final Data (use this)'!D9 | B4: ='[1]Final Data (use this)'!E9+B5 | C4: ='[1]Final Data (use this)'!F9+C5 | D4: =J4 | E4: ='[1]Final Data (use this)'!I9 | F4: ='[1]Final Data (use this)'!J9+F5 | G4: ='[1]Final Data (use this)'!K9+G5 | H4: 250 | I4: ='[1]Final Data (use this)'!M9+I5 | J4: ='[1]Final Data (use this)'!N9 | K4: ='[1]Final Data (use this)'!O9 | L4: ='[1]Final Data (use this)'!P9 | M4: ='[1]Final Data (use this)'!Q9 | N4: ='[1]Final Data (use this)'!T9 | O4: 153.4067
A5: Gasif. For Energy Recovery | B5: 4976.445 | C5: =[13]Gasification_Technologies!$D$2 | D5: =J5 | E5: 0 | F5: =[13]Gasification_Technologies!H2 | G5: =[13]Gasification_Technologies!I2 | H5: 387.663 | I5: 0 | J5: =[13]Gasification_Technologies!M2 | K5: =[13]Gasification_Technologies!N2 | L5: =[13]Gasification_Technologies!O2 | M5: =[13]Gasification_Technologies!P2 | N5: =[13]Gasification_Technologies!$T$2*1000000 | O5: =[13]Gasification_Technologies!$X$2
A6: Gasif. For H2 | B6: 6182.3529 | C6: =[13]Gasification_Technologies!$D$3 | D6: =J6 | E6: 0 | F6: =[13]Gasification_Technologies!H3 | G6: =[13]Gasification_Technologies!I3 | H6: 820.91503 | I6: 0 | J6: =[13]Gasification_Technologies!M3 | K6: =[13]Gasification_Technologies!N3 | L6: =[13]Gasification_Technologies!O3 | M6: =[13]Gasification_Technologies!P3 | N6: 0 | O6: 0
A7: Gasif. For H2 + CCS | B7: 7557.6471 | C7: =[13]Gasification_Technologies!$D$4 | D7: =J7 | E7: 0 | F7: =[13]Gasification_Technologies!H4 | G7: =[13]Gasification_Technologies!I4 | H7: 1046.4052 | I7: 0 | J7: =[13]Gasification_Technologies!M4 | K7: =[13]Gasification_Technologies!N4 | L7: =[13]Gasification_Technologies!O4 | M7: =[13]Gasification_Technologies!P4 | N7: 0 | O7: 0

Sheet New REsults
B1: 45958 | V1: case 1 | AF1: case 1
B2: CASE 1 | I2: CASE 2 | J2: values for CE changed | O2: CASE 3
B3: Max Profit | C3: Min Emissions | D3: Max CE | I3: Max Profit | J3: Min Emissions | K3: Max CE (w Emissions and Profit) | O3: Max Profit | P3: Min Emissions | Q3: Max CE (w Emissions and Profit) | W3: Max Profit | X3: Min Emissions | Y3: Min CE | AG3: Max Profit | AH3: Min Emissions | AI3: Max CE
A4: Profit | B4: 7453663.4 | C4: -62687.92 | D4: 7162118.4 | E4: New values with 1.5* mean for UB | H4: Profit | I4: 8455106.8 | J4: -62687.92 | N4: Profit | O4: 8159580.3 | P4: -62687.92 | V4: Profit | W4: 2860480 | X4: -53190402 | Y4: 971840 | AB4: =Y4/8000 | AF4: Profit | AG4: 971840 | AH4: -53190402 | AI4: 971840
A5: Emissions | B5: 14871.767 | C5: 652.8 | D5: 9031.0549 | E5: obtained using: Final model with circularity-Modified scenarios-Copy1_Scenario1w_Circularity | H5: Emissions | I5: 11702.977 | J5: 652.8 | N5: Emissions | O5: 12913.304 | P5: 652.8 | V5: Emissions | W5: 78022.007 | X5: 74620.523 | Y5: 87362.661 | AF5: Emissions | AG5: 87362.661 | AH5: 74620.523 | AI5: 87362.661
A6: CE | B6: 0.54640051 | C6: 0.60668302 | D6: 0.67486237 | E6: I used fixed UB defined by worst of 3 cases | H6: CE | N6: CE | V6: CE | W6: 0.41780527 | X6: 0.39975089 | Y6: 0.72104468 | AF6: CE | AG6: 0.72104468 | AH6: 0.39975089 | AI6: 0.72104468
B7: Strap1+2 +we | C7: landfill | D7: st1+st2+lf | I7: Strap1(evoh ethylene glycol)+Strap2(pe tetrachloroethylene) +we | J7: landfill | K7: Strap1(pe tetrachloroethylene)+Strap2(EVOH Pyridazine)+landfill | O7: Strap1(EVOH Pyridazine)+Strap2(PE Tetrachloroethylene) +Incineration | P7: landfill | W7: Stage 1: Gas_H2cc | X7: stage 3: strap1+2+gas_er | Y7: stage 1: we | AG7: Stage 1: we | AH7: stage 3: strap1+2+gas_er | AI7: stage 1: we
B8: it could be gas_h2 but emissions too high and gas_h2cc ce too low | D8: evoh pyri
B9: evoh ethylene glycol | D9: PE tetra | O9: evoh pyrid
B10: pe tetrachloroethylene | D10: lf | O10: PE tetra | V10: emissions/ton | W10: =W5/8000 | X10: =X5/8000 | Y10: =Y5/8000 | AB10: even with 100362.6607 , it starts with emission value of 81106 | AF10: emissions/ton | AG10: we | AH10: =AH5/8000 | AI10: =AI5/8000
B11: we | N11: Human Toxicity Cancer[CTUh]: | O11: 0.33261078 | P11: 0.04896
A12: Human Toxicity Cancer[CTUh]: | B12: 0.35612396 | C12: 0.04896 | D12: 0.17471795 | H12: Human Toxicity Cancer[CTUh]: | I12: 0.41410563 | J12: 0.04896 | N12: Human Toxicity Non-Cancer[CTUh]: | O12: 7.2864224 | P12: 6.464 | AD12: =81106/8000
A13: Human Toxicity Non-Cancer[CTUh]: | B13: 1.0587002 | C13: 6.464 | D13: 2.1224547 | H13: Human Toxicity Non-Cancer[CTUh]: | I13: 6.5526518 | J13: 6.464 | N13: Ecotoxicity[CTUe]: | O13: 2.4584109e+08 | P13: 360000000 | V13: case 2 | AD13: -15092562
A14: Ecotoxicity[CTUe]: | B14: 1.1584845e+08 | C14: 360000000 | D14: 1.1708396e+08 | H14: Ecotoxicity[CTUe]: | I14: 2.3013642e+08 | J14: 360000000 | AD14: =AD13/8000
W15: Max Profit | X15: Min Emissions | Y15: Min CE | AD15: strap 1+gash2cc
A16: if gas_h2 | B16: 18963.689 | I16: 0.41410563 | V16: Profit
B17: 0.33203847 | I17: 6.5526518 | K17: 0.17273042 | V17: Emissions
I18: 2.3013642e+08 | K18: 7.997188 | V18: CE
A19: if gas_h2cc | B19: 12069.571 | K19: 2.3882498e+08
B20: 0.39350316 | I20: Pareto: emissions vs cost | O20: Pareto: emissions vs cost
A22: cost | B22: emissions | C22: Point | D22: Solution | I22: Cost | J22: Emissions | K22: Solutions | L22: Calculated circularity | O22: Cost | P22: Emissions | Q22: Solutions | R22: Calculated circularity | V22: case 3
A23: 7453663.4 | B23: 12069.571 | C23: A | D23: Landfill | I23: 8482658.8 | J23: 11702.977 | K23: st1 (evoh, ethyle gly)+st2 (Pe tetra) +we | L23: 0.69040811 | O23: 8187132.3 | P23: 12913.304 | Q23: st1(evoh pyri)+st2(pe tetra)+we | R23: 0.69556882 | AD23: if the price for post-consumer ldpe film is around $0.109/lb, do you think is a good assumption for us to say the mixed waste is $0.05 (this is said to be price for grade b film) ?
A24: 7444924.8 | B24: 11745.019 | C24: B | D24: Strap1(EVOH Pyridazine)+landfill | I24: 8455106.8 | J24: 8900.7807 | K24: =K25 | L24: 0.53042298 | O24: 8159580.3 | P24: 10111.108 | W24: Max Profit | X24: Min Emissions | Y24: Min CE
A25: 7170857 | B25: 9355.6074 | C25: C | D25: Strap1(EVOH Ethylene glycol)+landfill | I25: 8455106.8 | J25: 8900.7807 | K25: st1 (evoh, ethyle gly)+st2 (Pe tetra) +gas_h2cc | O25: 8159580.3 | P25: 10111.108 | Q25: st1(evoh pyri)+st2(pe tetra)+gas_h2cc | R25: 0.53473913 | V25: Profit | AD25: =0.05*2.2*1000 | AE25: given 5 cents/lb | AF25: https://resource-recycling.com/plastics/2025/09/17/plastic-bale-prices-continue-to-fall/
A26: 3459497.4 | B26: 4641.9354 | C26: D | D26: Strap1(EVOH Ethylene glycol)+Strap 2( PE Tetrachloroethylene)+landfill | I26: 8172300.4 | J26: 6186.8168 | K26: =K27 | L26: 0.70713473 | O26: 7876773.9 | P26: 7397.1438 | V26: Emissions
A27: 3450758.8 | B27: 4317.3828 | C27: E | D27: Strap1(EVOH Pyridazine)+Strap2(PE Tetrachloroethylene)+Gasification (Hydrogen w/Carbon Capture) | I27: 8172300.4 | J27: 6186.8168 | K27: st1 (evoh, ethyle gly)+st2 (Pe tetra) +lf | O27: 7876773.9 | P27: 7397.1438 | Q27: st1(evoh pyri)+st2(pe tetra)+lf | R27: 0.71032814 | V27: CE
A28: -62687.92 | B28: 652.8 | C28: F | D28: Strap1(EVOH Ethylene glycol)+Strap 2( PE Tetrachloroethylene)+gas_h2cc | I28: 3847686.2 | J28: 2531.8185 | K28: =K29 | L28: 0.64836853 | O28: 3749373.5 | P28: 2747.173
I29: 3847686.2 | J29: 2531.8185 | K29: =K30 | O29: 3749373.5 | P29: 2747.173
I30: 3847686.2 | J30: 2531.8185 | K30: st1 (evoh, ethyle gly) +lf | O30: 3749373.5 | P30: 2747.173 | Q30: st1(evoh pyri)+lf | R30: 0.66453099
A31: cost | B31: ce | I31: -62687.92 | J31: 652.8 | K31: lf | L31: 0.6060231 | O31: -62687.92 | P31: 652.8 | Q31: lf
I32: -62687.92 | J32: 652.8 | K32: lf | O32: -62687.92 | P32: 652.8 | R32: 0.6060231
A33: 7453663.4 | B33: 0.64640051 | C33: st1(evoh ethylene glycol)+st2(Pe tetra)+we | E33: A | F33: Strap 1(EVOH Pyridazine)+Strap2(PE Tetrachloroethylene)+Landfill
A34: 7444924.8 | B34: 0.65443589 | C34: st1(evoh pyridazine)+st2(Pe tetra)+we | E34: B | F34: Strap 1(EVOH Ethylene glycol)+Strap 2(PE Tetrachloroethylene)+Landfill
E35: C | F35: Strap 1(EVOH Pyridazine)+Strap 2(PE Tetrachloroethylene)+Incineration | U35: Scenario 1 | V35: Scenario 2 | W35: Scenario 3
A36: 7170857 | B36: 0.66682888 | C36: st1(evoh ethylene glycol)+st2(Pe tetra)+lf | E36: D | F36: Strap 1(EVOH Ethylene glycol)+Strap 2(PE Tetrachloroethylene)+Incineration | T36: UB_energy | U36: 59042878 | V36: 62345860 | W36: 54868324
T37: UB_ghg | U37: 20157.841 | V37: 16149.482 | W37: 17297.112
A38: 7162118.4 | B38: 0.67486237 | C38: st1(evoh pyridazine)+st2(pe tetra)+lf | T38: UB_withdrawal | U38: 12843.796 | V38: 12259.545 | W38: 12369.209
T39: UB_waste | U39: 1916345.7 | V39: 1916345.7 | W39: 1916345.7
A41: ce | B41: emis
A42: 0.60668302 | B42: 652.8 | C42: lf | D42: A | E42: Landfill
A43: 0.63803225 | B43: 4317.3828 | C43: st1(evoh pyridazine)+lf | D43: B | E43: Strap 1(EVOH Pyridazine) + Landfill
D44: C | E44: Strap 1(EVOH Pyridazine) +Strap 2(PE Tetrachloroethylene) + Landfill
A45: 0.67486237 | B45: 9031.0549
A46: 0.67486237 | B46: 9031.0549 | C46: st1(evoh pyridazine)+st2(pe tetra)+lf
A56: scenario 2 forced | C56: scenario 1
H57: Original Profit vs CE Pareto front | N57: Original Profit vs CE Pareto front
A58: E_score:0.5625 | C58: E_score:0.5657995794430775
A59: GHG_score:0.967615513597714 | C59: GHG_score:0.9676155135977162 | I59: Cost | J59: CE | K59: Solution | N59: Cost | O59: CE | P59: Solution
A60: Water_score:0.5 | C60: Water_score:1.0 | I60: 8482658.8 | J60: 0.69103065 | N60: 8187132.3 | O60: 0.69488875
A61: Waste_score:0.5 | C61: Waste_score:0.5 | I61: 8482658.8 | J61: 0.69103065 | N61: 8187132.3 | O61: 0.69488875
A62: Subs_score:0.0 | C62: Subs_score:0.0 | I62: 8482658.8 | J62: 0.69103065 | N62: 8187132.3 | O62: 0.69488875
I63: 8482658.8 | J63: 0.69103065 | N63: 8187132.3 | O63: 0.69488875
I64: 8482658.8 | J64: 0.69103065 | N64: 8187132.3 | O64: 0.69488875
I65: 8482658.8 | J65: 0.69103065 | N65: 8187132.3 | O65: 0.69488875
I66: 8482658.8 | J66: 0.69103065 | K66: st1(evoh ethylene glycol)+st2(PE tetra)+we | N66: 8187132.3 | O66: 0.69488875 | P66: st1(evoh pyri)+st2(Pe tetra)+we
I67: 8447550.4 | J67: 0.70124508 | K67: st1(evoh pyri)+st2(pe tetra)+we | N67: 7876773.9 | O67: 0.71068069
I68: 8137192 | J68: 0.71710403 | K68: st1(evoh pyri)+st2(pe tetra)+lf | N68: 7876773.9 | O68: 0.71068069 | P68: st1(EVOH pyri)+st2(Pe tetra)+lf
I69: 6733710.9 | J69: 0.72281709 | K69: st1(pe tetra)+st2(evoh pyri)+lf | N69: 4476300.1 | O69: 0.7236345 | P69: st1(Pe tetra)+st2(evoh pyri)+lf
H72: Original Emissions vs CE | N72: Original Emissions vs CE
I74: Emissions | J74: CE | K74: Solution | O74: Emissions | P74: CE | Q74: Solution
I75: 2357.9782 | J75: 0.65855012 | K75: st1(evoh pyri)+lf | O75: 2747.173 | P75: 0.66453099
I76: 2357.9782 | J76: 0.65855012 | O76: 2747.173 | P76: 0.66453099
I77: 2357.9782 | J77: 0.65855012 | O77: 2747.173 | P77: 0.66453099
I78: 2357.9782 | J78: 0.65855012 | O78: 2747.173 | P78: 0.66453099
I79: 2357.9782 | J79: 0.65855012 | O79: 2747.173 | P79: 0.66453099 | Q79: st1(EVOH pyri)+lf
I80: 5937.7687 | J80: 0.72281709 | K80: st1(pe tetra)+st2(evoh pyri)+lf | O80: 6607.9422 | P80: 0.72363451
I81: 5937.7687 | J81: 0.72281709 | O81: 6607.9422 | P81: 0.72363451
I82: 5937.7687 | J82: 0.72281709 | O82: 6607.9422 | P82: 0.72363451
I83: 5937.7687 | J83: 0.72281709 | O83: 6607.9422 | P83: 0.72363451
I84: 5937.7687 | J84: 0.72281709 | O84: 6607.9422 | P84: 0.72363451 | Q84: st1(Pe tetra)+st2(evoh pyri)+lf
B93: Max Profit | C93: Min Emissions | D93: Max CE
A94: Profit | B94: 7453663.4 | C94: -62687.92 | D94: 7162118.4 | I94: Profit | J94: Emissions | K94: CE | L94: Human Toxicity Cancer[CTUh]: | M94: Human Toxicity Non-Cancer[CTUh]: | N94: Ecotoxicity[CTUe]:
A95: Emissions | B95: 14871.767 | C95: 652.8 | D95: 9031.0549 | H95: Max Profit | I95: 7453663.4 | J95: 14871.767 | K95: 0.54640051 | L95: 0.35612396 | M95: 1.0587002 | N95: 1.1584845e+08
A96: CE | B96: 0.54640051 | C96: 0.60668302 | D96: 0.67486237 | H96: Min Emissions | I96: -62687.92 | J96: 652.8 | K96: 0.60668302 | L96: 0.04896 | M96: 6.464 | N96: 360000000
A97: Human Toxicity Cancer[CTUh]: | B97: 0.35612396 | C97: 0.04896 | D97: 0.17471795 | H97: Max CE | I97: 7162118.4 | J97: 9031.0549 | K97: 0.67486237 | L97: 0.17471795 | M97: 2.1224547 | N97: 1.1708396e+08
A98: Human Toxicity Non-Cancer[CTUh]: | B98: 1.0587002 | C98: 6.464 | D98: 2.1224547
A99: Ecotoxicity[CTUe]: | B99: 1.1584845e+08 | C99: 360000000 | D99: 1.1708396e+08
A100: solution | B100: Strap1(EVOH Ethylene Glycol)+Strap2(PE Tetrachloroethylene) +Incineration | C100: landfill | D100: Strap1(EVOH Pyridazine)+Strap2(PE Tetrachloroethylene) +Landfill
D101: evoh pyri
D102: PE tetra
D103: lf
B107: it could be gas_h2 but emissions too high and gas_h2cc ce too low
B108: evoh ethylene glycol
B109: pe tetrachloroethylene

Sheet Results OPT
B1: 45958 | V1: case 1 | AF1: case 1
B2: CASE 1 | I2: CASE 2 | O2: CASE 3
B3: Max Profit | C3: Min Emissions | D3: Max CE | I3: Max Profit | J3: Min Emissions | K3: Max CE (w Emissions and Profit) | O3: Max Profit | P3: Min Emissions | Q3: Max CE (w Emissions and Profit) | W3: Max Profit | X3: Min Emissions | Y3: Min CE | AG3: Max Profit | AH3: Min Emissions | AI3: Max CE
A4: Profit | B4: 7481215.4 | C4: -62687.92 | D4: 7162118.4 | E4: New values with 1.5* mean for UB | H4: Profit | I4: 8482658.8 | J4: -62687.92 | K4: 6733710.9 | N4: Profit | O4: 8187130 | P4: -62687.92 | Q4: 4476300.1 | V4: Profit | W4: 2860480 | X4: -53190402 | Y4: 971840 | AB4: =Y4/8000 | AF4: Profit | AG4: 971840 | AH4: -53190402 | AI4: 971840
A5: Emissions | B5: 14871.767 | C5: 652.8 | D5: 9031.0549 | E5: obtained using: Final model with circularity-Modified scenarios-Copy1_Scenario1w_Circularity | H5: Emissions | I5: 11702.977 | J5: 652.8 | K5: 5937.7687 | N5: Emissions | O5: 12913.304 | P5: 652.8 | Q5: 6607.9422 | V5: Emissions | W5: 78022.007 | X5: 74620.523 | Y5: 87362.661 | AF5: Emissions | AG5: 87362.661 | AH5: 74620.523 | AI5: 87362.661
A6: CE | B6: 0.65085974 | C6: 0.60602305 | D6: 0.67486237 | E6: I used fixed UB defined by worst of 3 cases | H6: CE | I6: 0.69103065 | J6: 0.60668297 | K6: 0.72281709 | N6: CE | O6: 0.69488875 | P6: 0.60668297 | Q6: 0.72363451 | V6: CE | W6: 0.41780527 | X6: 0.39975089 | Y6: 0.72104468 | AF6: CE | AG6: 0.72104468 | AH6: 0.39975089 | AI6: 0.72104468
B7: Strap1+2 +we | C7: landfill | D7: st1+st2+lf | I7: Strap1+2 +we | J7: landfill | K7: st1+St2+lf | O7: Strap1+2 +we | P7: landfill | Q7: st1+st2+lf | W7: Stage 1: Gas_H2cc | X7: stage 3: strap1+2+gas_er | Y7: stage 1: we | AG7: Stage 1: we | AH7: stage 3: strap1+2+gas_er | AI7: stage 1: we
D8: evoh pyri
B9: evoh ethylene glycol | D9: PE tetra | I9: evoh ethylene glycol | K9: pe tetra | O9: evoh pyrid | Q9: PE tetra
B10: pe tetrachloroethylene | D10: lf | I10: pe tetrachloroethylene | K10: evoh pyri | O10: PE tetra | Q10: evoh pyri | V10: emissions/ton | W10: =W5/8000 | X10: =X5/8000 | Y10: =Y5/8000 | AB10: even with 100362.6607 , it starts with emission value of 81106 | AF10: emissions/ton | AG10: we | AH10: =AH5/8000 | AI10: =AI5/8000
K11: lf | P11: 0.6060231
AD12: =81106/8000
V13: case 2 | AD13: -15092562
AD14: =AD13/8000
W15: Max Profit | X15: Min Emissions | Y15: Min CE | AD15: strap 1+gash2cc
V16: Profit
J17: works | V17: Emissions
J18: evoh pyri,lf | V18: CE
I20: Pareto: emissions vs cost | O20: Pareto: emissions vs cost
C22: cost | D22: emis_arr | I22: Cost | J22: Emissions | K22: Solutions | L22: Calculated circularity | O22: Cost | P22: Emissions | Q22: Solutions | R22: Calculated circularity | V22: case 3
C23: 7472476.8 | D23: 14547.215 | E23: st1(evoh pyri)+st2(PE tetra)+we | I23: 8482658.8 | J23: 11702.977 | K23: st1 (evoh, ethyle gly)+st2 (Pe tetra) +we | L23: 0.69040811 | O23: 8187132.3 | P23: 12913.304 | Q23: st1(evoh pyri)+st2(pe tetra)+we | R23: 0.69556882 | AD23: if the price for post-consumer ldpe film is around $0.109/lb, do you think is a good assumption for us to say the mixed waste is $0.05 (this is said to be price for grade b film) ?
C24: 7453663.4 | D24: 12069.571 | E24: st1(evoh ethylene glycol)+strap 2( PE tetra)+gas_h2cc | I24: 8455106.8 | J24: 8900.7807 | K24: =K25 | L24: 0.53042298 | O24: 8159580.3 | P24: 10111.108 | W24: Max Profit | X24: Min Emissions | Y24: Min CE
C25: 7170857 | D25: 9355.6074 | E25: st1(evoh ethylene glycol)+strap 2( PE tetra)+lf | I25: 8455106.8 | J25: 8900.7807 | K25: st1 (evoh, ethyle gly)+st2 (Pe tetra) +gas_h2cc | O25: 8159580.3 | P25: 10111.108 | Q25: st1(evoh pyri)+st2(pe tetra)+gas_h2cc | R25: 0.53473913 | V25: Profit | AD25: =0.05*2.2*1000 | AE25: given 5 cents/lb | AF25: https://resource-recycling.com/plastics/2025/09/17/plastic-bale-prices-continue-to-fall/
C26: 7170857 | D26: 9355.6074 | I26: 8172300.4 | J26: 6186.8168 | K26: =K27 | L26: 0.70713473 | O26: 7876773.9 | P26: 7397.1438 | V26: Emissions
C27: 3459497.4 | D27: 4641.9354 | E27: st1(evoh ethylene glycol)+lf | I27: 8172300.4 | J27: 6186.8168 | K27: st1 (evoh, ethyle gly)+st2 (Pe tetra) +lf | O27: 7876773.9 | P27: 7397.1438 | Q27: st1(evoh pyri)+st2(pe tetra)+lf | R27: 0.71032814 | V27: CE
C28: 3459497.4 | D28: 4641.9354 | I28: 3847686.2 | J28: 2531.8185 | K28: =K29 | L28: 0.64836853 | O28: 3749373.5 | P28: 2747.173
C29: 3459497.4 | D29: 4641.9354 | I29: 3847686.2 | J29: 2531.8185 | K29: =K30 | O29: 3749373.5 | P29: 2747.173
C30: -62687.92 | D30: 652.8 | E30: lf | I30: 3847686.2 | J30: 2531.8185 | K30: st1 (evoh, ethyle gly) +lf | O30: 3749373.5 | P30: 2747.173 | Q30: st1(evoh pyri)+lf | R30: 0.66453099
C31: -62687.92 | D31: 652.8 | I31: -62687.92 | J31: 652.8 | K31: lf | L31: 0.6060231 | O31: -62687.92 | P31: 652.8 | Q31: lf
C32: -62687.92 | D32: 652.8 | I32: -62687.92 | J32: 652.8 | K32: lf | O32: -62687.92 | P32: 652.8 | R32: 0.6060231
C35: cost | D35: CE | U35: Scenario 1 | V35: Scenario 2 | W35: Scenario 3
C36: 7481215.4 | D36: 0.65085974 | T36: UB_energy | U36: 59042878 | V36: 62345860 | W36: 54868324
C37: 7481215.4 | D37: 0.65085974 | T37: UB_ghg | U37: 20157.841 | V37: 16149.482 | W37: 17297.112
C38: 7481215.4 | D38: 0.65085974 | T38: UB_withdrawal | U38: 12843.796 | V38: 12259.545 | W38: 12369.209
C39: 7481215.4 | D39: 0.65085974 | T39: UB_waste | U39: 1916345.7 | V39: 1916345.7 | W39: 1916345.7
C40: 7481215.4 | D40: 0.65085974
C41: 7481215.4 | D41: 0.65085974 | E41: st1(evoh ethylene glycol)+st2(Pe tetra)+we
C42: 7472476.8 | D42: 0.65889512 | E42: st1(evoh pyridazine)+st2(Pe tetra)+we
C43: 7170857 | D43: 0.66682888 | E43: st1(evoh ethylene glycol)+st2(Pe tetra)+lf
C44: 7162118.4 | D44: 0.67486237
C45: 7162118.4 | D45: 0.67486237 | E45: st1(evoh pyridazine)+st2(Pe tetra)+lf
C49: emissions | D49: ce
C50: 652.8 | D50: 0.60668302
C51: 4317.3828 | D51: 0.63803225
C52: 4317.3828 | D52: 0.63803225
C53: 4317.3828 | D53: 0.63803225
C54: 4317.3828 | D54: 0.63803225
C55: 9031.0549 | D55: 0.67486237
C56: 9031.0549 | D56: 0.67486237
C57: 9031.0549 | D57: 0.67486237 | H57: Original Profit vs CE Pareto front | N57: Original Profit vs CE Pareto front
C58: 9031.0549 | D58: 0.67486237
C59: 9031.0549 | D59: 0.67486237 | I59: Cost | J59: CE | K59: Solution | N59: Cost | O59: CE | P59: Solution
I60: 8482658.8 | J60: 0.69103065 | N60: 8187132.3 | O60: 0.69488875
I61: 8482658.8 | J61: 0.69103065 | N61: 8187132.3 | O61: 0.69488875
I62: 8482658.8 | J62: 0.69103065 | N62: 8187132.3 | O62: 0.69488875
I63: 8482658.8 | J63: 0.69103065 | N63: 8187132.3 | O63: 0.69488875
I64: 8482658.8 | J64: 0.69103065 | N64: 8187132.3 | O64: 0.69488875
I65: 8482658.8 | J65: 0.69103065 | N65: 8187132.3 | O65: 0.69488875
I66: 8482658.8 | J66: 0.69103065 | K66: st1(evoh ethylene glycol)+st2(PE tetra)+we | N66: 8187132.3 | O66: 0.69488875 | P66: st1(evoh pyri)+st2(Pe tetra)+we
I67: 8447550.4 | J67: 0.70124508 | K67: st1(evoh pyri)+st2(pe tetra)+we | N67: 7876773.9 | O67: 0.71068069
I68: 8137192 | J68: 0.71710403 | K68: st1(evoh pyri)+st2(pe tetra)+lf | N68: 7876773.9 | O68: 0.71068069 | P68: st1(EVOH pyri)+st2(Pe tetra)+lf
I69: 6733710.9 | J69: 0.72281709 | K69: st1(pe tetra)+st2(evoh pyri)+lf | N69: 4476300.1 | O69: 0.7236345 | P69: st1(Pe tetra)+st2(evoh pyri)+lf
H72: Original Emissions vs CE | N72: Original Emissions vs CE
I74: Emissions | J74: CE | K74: Solution | O74: Emissions | P74: CE | Q74: Solution
I75: 2357.9782 | J75: 0.65855012 | K75: st1(evoh pyri)+lf | O75: 2747.173 | P75: 0.66453099
I76: 2357.9782 | J76: 0.65855012 | O76: 2747.173 | P76: 0.66453099
I77: 2357.9782 | J77: 0.65855012 | O77: 2747.173 | P77: 0.66453099
I78: 2357.9782 | J78: 0.65855012 | O78: 2747.173 | P78: 0.66453099
I79: 2357.9782 | J79: 0.65855012 | O79: 2747.173 | P79: 0.66453099 | Q79: st1(EVOH pyri)+lf
I80: 5937.7687 | J80: 0.72281709 | K80: st1(pe tetra)+st2(evoh pyri)+lf | O80: 6607.9422 | P80: 0.72363451
I81: 5937.7687 | J81: 0.72281709 | O81: 6607.9422 | P81: 0.72363451
I82: 5937.7687 | J82: 0.72281709 | O82: 6607.9422 | P82: 0.72363451
I83: 5937.7687 | J83: 0.72281709 | O83: 6607.9422 | P83: 0.72363451
I84: 5937.7687 | J84: 0.72281709 | O84: 6607.9422 | P84: 0.72363451 | Q84: st1(Pe tetra)+st2(evoh pyri)+lf

Sheet Old Results
B1: 45958 | V1: case 1 | AF1: case 1
B2: CASE 1 | I2: CASE 2 | O2: CASE 3
B3: Max Profit | C3: Min Emissions | D3: Max CE | I3: Max Profit | J3: Min Emissions | K3: Max CE (w Emissions and Profit) | O3: Max Profit | P3: Min Emissions | Q3: Max CE (w Emissions and Profit) | W3: Max Profit | X3: Min Emissions | Y3: Min CE | AG3: Max Profit | AH3: Min Emissions | AI3: Max CE
A4: Profit | B4: 7481215.4 | C4: -62687.92 | D4: 4381834 | H4: Profit | I4: 8482658.8 | J4: -62687.92 | K4: 6733710.9 | N4: Profit | O4: 8187130 | P4: -62687.92 | Q4: 4476300.1 | V4: Profit | W4: 2860480 | X4: -53190402 | Y4: 971840 | AB4: =Y4/8000 | AF4: Profit | AG4: 971840 | AH4: -53190402 | AI4: 971840
A5: Emissions | B5: 14871.767 | C5: 652.8 | D5: 20865.863 | H5: Emissions | I5: 11702.977 | J5: 652.8 | K5: 5937.7687 | N5: Emissions | O5: 12913.304 | P5: 652.8 | Q5: 6607.9422 | V5: Emissions | W5: 78022.007 | X5: 74620.523 | Y5: 87362.661 | AF5: Emissions | AG5: 87362.661 | AH5: 74620.523 | AI5: 87362.661
A6: CE | B6: 0.55596391 | C6: 0.49945057 | D6: 0.58483111 | H6: CE | I6: 0.69103065 | J6: 0.60668297 | K6: 0.72281709 | N6: CE | O6: 0.69488875 | P6: 0.60668297 | Q6: 0.72363451 | V6: CE | W6: 0.41780527 | X6: 0.39975089 | Y6: 0.72104468 | AF6: CE | AG6: 0.72104468 | AH6: 0.39975089 | AI6: 0.72104468
B7: Strap1+2 +we | C7: landfill | D7: st1+we | I7: Strap1+2 +we | J7: landfill | K7: st1+St2+lf | O7: Strap1+2 +we | P7: landfill | Q7: st1+st2+lf | W7: Stage 1: Gas_H2cc | X7: stage 3: strap1+2+gas_er | Y7: stage 1: we | AG7: Stage 1: we | AH7: stage 3: strap1+2+gas_er | AI7: stage 1: we
B9: evoh ethylene glycol | D9: evoh pyrydazine | I9: evoh ethylene glycol | K9: pe tetra | O9: evoh pyrid | Q9: PE tetra
B10: pe tetrachloroethylene | I10: pe tetrachloroethylene | K10: evoh pyri | O10: PE tetra | Q10: evoh pyri | V10: emissions/ton | W10: =W5/8000 | X10: =X5/8000 | Y10: =Y5/8000 | AB10: even with 100362.6607 , it starts with emission value of 81106 | AF10: emissions/ton | AG10: we | AH10: =AH5/8000 | AI10: =AI5/8000
K11: lf | P11: 0.6060231
D12: 7162118.4 | AD12: =81106/8000
D13: 9031.0549 | V13: case 2 | AD13: -15092562
A14: CE | B14: 0.65085974 | C14: 0.60602305 | D14: 0.67486237 | E14: New values with 1.5* mean for UB | AD14: =AD13/8000
B15: =B7 | C15: =C7 | D15: st1+st2+lf | W15: Max Profit | X15: Min Emissions | Y15: Min CE | AD15: strap 1+gash2cc
D16: evoh pyri | F16: obtained using: Final model with circularity-Modified scenarios-Copy1_Scenario1w_Circularity | V16: Profit
B17: =B9 | D17: PE tetra | F17: I used fixed UB defined by worst of 3 cases | J17: works | V17: Emissions
B18: =B10 | D18: lf | J18: evoh pyri,lf | V18: CE
I20: Pareto: emissions vs cost | O20: Pareto: emissions vs cost
C22: cost | D22: emis_arr | I22: Cost | J22: Emissions | K22: Solutions | L22: Calculated circularity | O22: Cost | P22: Emissions | Q22: Solutions | R22: Calculated circularity | V22: case 3
C23: 7472476.8 | D23: 14547.215 | E23: st1(evoh pyri)+st2(PE tetra)+we | I23: 8482658.8 | J23: 11702.977 | K23: st1 (evoh, ethyle gly)+st2 (Pe tetra) +we | L23: 0.69040811 | O23: 8187132.3 | P23: 12913.304 | Q23: st1(evoh pyri)+st2(pe tetra)+we | R23: 0.69556882 | AD23: if the price for post-consumer ldpe film is around $0.109/lb, do you think is a good assumption for us to say the mixed waste is $0.05 (this is said to be price for grade b film) ?
C24: 7453663.4 | D24: 12069.571 | E24: st1(evoh ethylene glycol)+strap 2( PE tetra)+gas_h2cc | I24: 8455106.8 | J24: 8900.7807 | K24: =K25 | L24: 0.53042298 | O24: 8159580.3 | P24: 10111.108 | W24: Max Profit | X24: Min Emissions | Y24: Min CE
C25: 7170857 | D25: 9355.6074 | E25: st1(evoh ethylene glycol)+strap 2( PE tetra)+lf | I25: 8455106.8 | J25: 8900.7807 | K25: st1 (evoh, ethyle gly)+st2 (Pe tetra) +gas_h2cc | O25: 8159580.3 | P25: 10111.108 | Q25: st1(evoh pyri)+st2(pe tetra)+gas_h2cc | R25: 0.53473913 | V25: Profit | AD25: =0.05*2.2*1000 | AE25: given 5 cents/lb | AF25: https://resource-recycling.com/plastics/2025/09/17/plastic-bale-prices-continue-to-fall/
C26: 7170857 | D26: 9355.6074 | I26: 8172300.4 | J26: 6186.8168 | K26: =K27 | L26: 0.70713473 | O26: 7876773.9 | P26: 7397.1438 | V26: Emissions
C27: 3459497.4 | D27: 4641.9354 | E27: st1(evoh ethylene glycol)+lf | I27: 8172300.4 | J27: 6186.8168 | K27: st1 (evoh, ethyle gly)+st2 (Pe tetra) +lf | O27: 7876773.9 | P27: 7397.1438 | Q27: st1(evoh pyri)+st2(pe tetra)+lf | R27: 0.71032814 | V27: CE
C28: 3459497.4 | D28: 4641.9354 | I28: 3847686.2 | J28: 2531.8185 | K28: =K29 | L28: 0.64836853 | O28: 3749373.5 | P28: 2747.173
C29: 3459497.4 | D29: 4641.9354 | I29: 3847686.2 | J29: 2531.8185 | K29: =K30 | O29: 3749373.5 | P29: 2747.173
C30: -62687.92 | D30: 652.8 | E30: lf | I30: 3847686.2 | J30: 2531.8185 | K30: st1 (evoh, ethyle gly) +lf | O30: 3749373.5 | P30: 2747.173 | Q30: st1(evoh pyri)+lf | R30: 0.66453099
C31: -62687.92 | D31: 652.8 | I31: -62687.92 | J31: 652.8 | K31: lf | L31: 0.6060231 | O31: -62687.92 | P31: 652.8 | Q31: lf
C32: -62687.92 | D32: 652.8 | I32: -62687.92 | J32: 652.8 | K32: lf | O32: -62687.92 | P32: 652.8 | R32: 0.6060231
U35: Scenario 1 | V35: Scenario 2 | W35: Scenario 3
T36: UB_energy | U36: 59042878 | V36: 62345860 | W36: 54868324
T37: UB_ghg | U37: 20157.841 | V37: 16149.482 | W37: 17297.112
T38: UB_withdrawal | U38: 12843.796 | V38: 12259.545 | W38: 12369.209
T39: UB_waste | U39: 1916345.7 | V39: 1916345.7 | W39: 1916345.7
C44: solutions | D44: emissions | E44: Cost | G44: pe tetra
C45: lf | D45: 652.8 | E45: -62687.92 | G45: pe tetra
C46: lf
C47: st1+lf | D47: 4641.93 | E47: 3459497.4
C48: st1+lf | G48: evoh pirydaze
C49: st1+st2+lf | D49: 9355.6 | E49: 7170857 | G49: evoh ethylene glycol
C50: st1+st2+h2cc | D50: 11745 | E50: 7444924.8
C51: st1+st2+h2cc | D51: 12069 | E51: 7453663.4
C52: st1+st2+we | G52: more emissions and lower profit
C53: st1+st2+we | D53: 14871 | E53: 7481215.4
C54: st1+st2+we
D55: 20867 | E55: add? | F55: no because this does not improve the profit therefore is not part of the pareto
H57: Original Profit vs CE Pareto front | N57: Original Profit vs CE Pareto front
I59: Cost | J59: CE | K59: Solution | N59: Cost | O59: CE | P59: Solution | T59: cost and CE
I60: 8482658.8 | J60: 0.69103065 | N60: 8187132.3 | O60: 0.69488875 | T60: =O32 | V60: =P6
I61: 8482658.8 | J61: 0.69103065 | N61: 8187132.3 | O61: 0.69488875
I62: 8482658.8 | J62: 0.69103065 | N62: 8187132.3 | O62: 0.69488875
I63: 8482658.8 | J63: 0.69103065 | N63: 8187132.3 | O63: 0.69488875
I64: 8482658.8 | J64: 0.69103065 | N64: 8187132.3 | O64: 0.69488875
I65: 8482658.8 | J65: 0.69103065 | N65: 8187132.3 | O65: 0.69488875
I66: 8482658.8 | J66: 0.69103065 | K66: st1(evoh ethylene glycol)+st2(PE tetra)+we | N66: 8187132.3 | O66: 0.69488875 | P66: st1(evoh pyri)+st2(Pe tetra)+we
B67: I should add | G67: no because lowest CE and lowest profit. Not part of Pareto | I67: 8447550.4 | J67: 0.70124508 | K67: st1(evoh pyri)+st2(pe tetra)+we | N67: 7876773.9 | O67: 0.71068069
G68: pe tetra | I68: 8137192 | J68: 0.71710403 | K68: st1(evoh pyri)+st2(pe tetra)+lf | N68: 7876773.9 | O68: 0.71068069 | P68: st1(EVOH pyri)+st2(Pe tetra)+lf
G69: pe tetra | I69: 6733710.9 | J69: 0.72281709 | K69: st1(pe tetra)+st2(evoh pyri)+lf | N69: 4476300.1 | O69: 0.7236345 | P69: st1(Pe tetra)+st2(evoh pyri)+lf
T70: =O4 | U70: =Q6
H72: Original Emissions vs CE | N72: Original Emissions vs CE
I74: Emissions | J74: CE | K74: Solution | O74: Emissions | P74: CE | Q74: Solution
I75: 2357.9782 | J75: 0.65855012 | K75: st1(evoh pyri)+lf | O75: 2747.173 | P75: 0.66453099
I76: 2357.9782 | J76: 0.65855012 | O76: 2747.173 | P76: 0.66453099
I77: 2357.9782 | J77: 0.65855012 | O77: 2747.173 | P77: 0.66453099
I78: 2357.9782 | J78: 0.65855012 | O78: 2747.173 | P78: 0.66453099
I79: 2357.9782 | J79: 0.65855012 | O79: 2747.173 | P79: 0.66453099 | Q79: st1(EVOH pyri)+lf
I80: 5937.7687 | J80: 0.72281709 | K80: st1(pe tetra)+st2(evoh pyri)+lf | O80: 6607.9422 | P80: 0.72363451
I81: 5937.7687 | J81: 0.72281709 | O81: 6607.9422 | P81: 0.72363451
I82: 5937.7687 | J82: 0.72281709 | O82: 6607.9422 | P82: 0.72363451
I83: 5937.7687 | J83: 0.72281709 | O83: 6607.9422 | P83: 0.72363451
I84: 5937.7687 | J84: 0.72281709 | O84: 6607.9422 | P84: 0.72363451 | Q84: st1(Pe tetra)+st2(evoh pyri)+lf
C86: lf | D86: =C6
C87: st1+st2+we | D87: 0.55 | F87: evoh ethyle
C88: st1+st2+we | D88: 0.563 | F88: evohpyridaze
C89: st1+we | D89: 0.57749 | F89: evoh ethyle
C90: st1+we | D90: 0.5848 | F90: =F88
D92: ce | E92: profit | F92: solutions
D93: 0.65085974 | E93: 7481215.4
D94: 0.65085974 | E94: 7481215.4
D95: 0.65085974 | E95: 7481215.4
D96: 0.65085974 | E96: 7481215.4
D97: 0.65085974 | E97: 7481215.4
D98: 0.65085974 | E98: 7481215.4 | F98: st1(evoh ethylene glycol)+st2(pe tetra)+we
D99: 0.65889512 | E99: 7472476.8 | F99: st1(evoh pyri)+st2(pe tetra)+we
D100: 0.66682888 | E100: 7170857 | F100: st1(evoh ethylene glycol)+st2(pe tetra)+lf
D101: 0.67486237 | E101: 7162118.4
D102: 0.67486237 | E102: 7162118.4 | F102: st1(evoh pyri)+st2(pe tetra)+lf
B112: evoh pyr, pe tetra
B118: pe tetr, evoh pyridazine
B119: evoh pyri,
C129: solution | D129: ce | E129: e
C130: lf | D130: 0.49945057 | E130: 652.8
C131: st1+st2+we | D131: 0.56324263 | E131: 14547.215
D132: 0.56324263 | E132: 14547.215
D133: 0.56324263 | E133: 14547.215
D134: 0.56324263 | E134: 14547.215
D135: 0.56324263 | E135: 14547.215
D136: 0.56324263 | E136: 14547.215
C137: st1+st2+we | D137: 0.57102739 | E137: 15679.686
C138: st1+we | D138: 0.58483111 | E138: 20865.863
...

Sheet Shredder
B1: Total Energy Consumed [MJ/ton resin] | C1: Total Renewable Energy Consumed [MJ/ton resin] | D1: Total Direct GHG emissions [Scope 1] [metric tons CO2 equivalent [tCO2e/ton]] | E1: Total Energy indirect GHG emissions (Scope 2) [metric tons CO2 equivalent (t CO2e)] | F1: Nitrogen oxides [NOX], sulfur oxides [SOX] and other significant air emissions* [ton or multiples] | G1: Water consumed/discarded [m3/ton] | H1: Water Recycled or Reused [m3/ton] | I1: Waste generated - Non Hazardous [kg/ton] | J1: Waste to Disposal[ton/ton] | K1: GWP [tonCO2e/ton resin] | L1: Human toxicity cancer [CTUh/ton resin] | M1: Human toxicity non-cancer [CTUh/ton resin] | N1: Ecotoxicity [CTUe/ton resin] | O1: CAPEX [USD] | P1: OPEX [USD/ton]
A2: Scenario 1 | B2: 0.66 | C2: 0 | D2: 0.55746315 | K2: =[14]Process_results_shredderC1!$C$2 | L2: =[14]Process_results_shredderC1!$D$2 | M2: =[14]Process_results_shredderC1!$E$2 | N2: =[14]Process_results_shredderC1!$F$2 | O2: =[14]Process_results_shredderC1!$G$2 | P2: =[14]Process_results_shredderC1!$H$2
A3: Scenario 2 | B3: 0.66 | C3: =[10]Process_results_shredderC2!$C$2 | D3: =K3 | K3: 0.12977225 | L3: 2.0552763e-09 | M3: 1.6073315e-07 | N3: 3.4518102 | O3: 2938053.5 | P3: 1051212.1
A4: Scenario 3 | B4: =[15]Process_results_shredderC3!$B$2 | C4: =[15]Process_results_shredderC3!$C$2 | D4: =K4 | K4: 0.17975046 | L4: 2.0552763e-09 | M4: 1.6073315e-07 | N4: 3.4518102 | O4: 2424468 | P4: 1003656.2

Sheet StrapScenario3
A1: Wash number | B1: ='[1]Final Data (use this)'!C11 | C1: ='[1]Final Data (use this)'!D11 | D1: Total Energy Consumed [MJ/kg resin produced ] | E1: Total Electricity [MJ/kg resin] | F1: Total Direct GHG emissions [Scope 1] [metric tons CO2 equivalent [tCO2e/ton]] | G1: Total Energy indirect GHG emissions (Scope 2) [metric tons CO2 equivalent (t CO2e)] | H1: Water consumed/discarded [m3/yr] | I1: Water Recycled or Reused [m3/yr] | J1: Waste generated - Non Hazardous [kg/yr] | K1: Waste to Disposal[ton/ton] | L1: GWP [tonCO2e/ton resin] | M1: Human toxicity cancer [CTUh/kg resin] | N1: Human toxicity non-cancer [CTUh/kg resin] | O1: Ecotoxicity [CTUe/kg resin] | P1: CAPEX [USD] | Q1: OPEX [USD/yr]
A2: Wash 1 | B2: PE | C2: sec-Butyl Acetate | D2: =[16]Process_results_C3_P1!B2+[15]Process_results_shredderC3!$B$2 | E2: =[16]Process_results_C3_P1!C2+[15]Process_results_shredderC3!$C$2 | F2: =L2 | G2: 0 | H2: 607.57 | I2: 52120.53 | J2: 7403.53 | K2: 0 | L2: =[16]Process_results_C3_P1!D2+[15]Process_results_shredderC3!$D$2 | M2: =[16]Process_results_C3_P1!I2+[15]Process_results_shredderC3!$E$2 | N2: =[16]Process_results_C3_P1!J2+[15]Process_results_shredderC3!$F$2 | O2: =[16]Process_results_C3_P1!K2+[15]Process_results_shredderC3!$G$2 | P2: =[16]Process_results_C3_P1!L2+[15]Process_results_shredderC3!$H$2 | Q2: =[16]Process_results_C3_P1!M2+[15]Process_results_shredderC3!$I$2
A3: Wash 1 | B3: PE | C3: Isobutyl Acetate | D3: =[16]Process_results_C3_P1!B3+[15]Process_results_shredderC3!$B$2 | E3: =[16]Process_results_C3_P1!C3+[15]Process_results_shredderC3!$C$2 | F3: =L3 | G3: 0 | H3: 596.37 | I3: 51205.64 | J3: 7463.47 | K3: 0 | L3: =[16]Process_results_C3_P1!D3+[15]Process_results_shredderC3!$D$2 | M3: =[16]Process_results_C3_P1!I3+[15]Process_results_shredderC3!$E$2 | N3: =[16]Process_results_C3_P1!J3+[15]Process_results_shredderC3!$F$2 | O3: =[16]Process_results_C3_P1!K3+[15]Process_results_shredderC3!$G$2 | P3: =[16]Process_results_C3_P1!L3+[15]Process_results_shredderC3!$H$2 | Q3: =[16]Process_results_C3_P1!M3+[15]Process_results_shredderC3!$I$2
A4: Wash 1 | B4: PE | C4: Tetrachloroethylene | D4: =[16]Process_results_C3_P1!B4+[15]Process_results_shredderC3!$B$2 | E4: =[16]Process_results_C3_P1!C4+[15]Process_results_shredderC3!$C$2 | F4: =L4 | G4: 0 | H4: 299.61 | I4: 25637.89 | J4: 4419.13 | K4: 0 | L4: =[16]Process_results_C3_P1!D4+[15]Process_results_shredderC3!$D$2 | M4: =[16]Process_results_C3_P1!I4+[15]Process_results_shredderC3!$E$2 | N4: =[16]Process_results_C3_P1!J4+[15]Process_results_shredderC3!$F$2 | O4: =[16]Process_results_C3_P1!K4+[15]Process_results_shredderC3!$G$2 | P4: =[16]Process_results_C3_P1!L4+[15]Process_results_shredderC3!$H$2 | Q4: =[16]Process_results_C3_P1!M4+[15]Process_results_shredderC3!$I$2
A5: Wash 1 | B5: PE | C5: o-Chlorotoluene | D5: =[16]Process_results_C3_P1!B5+[15]Process_results_shredderC3!$B$2 | E5: =[16]Process_results_C3_P1!C5+[15]Process_results_shredderC3!$C$2 | F5: =L5 | G5: 0 | H5: 741.85 | I5: 63368.91 | J5: 6319.81 | K5: 0 | L5: =[16]Process_results_C3_P1!D5+[15]Process_results_shredderC3!$D$2 | M5: =[16]Process_results_C3_P1!I5+[15]Process_results_shredderC3!$E$2 | N5: =[16]Process_results_C3_P1!J5+[15]Process_results_shredderC3!$F$2 | O5: =[16]Process_results_C3_P1!K5+[15]Process_results_shredderC3!$G$2 | P5: =[16]Process_results_C3_P1!L5+[15]Process_results_shredderC3!$H$2 | Q5: =[16]Process_results_C3_P1!M5+[15]Process_results_shredderC3!$I$2
A6: Wash 1 | B6: PE | C6: Methylcyclohexane | D6: =[16]Process_results_C3_P1!B6+[15]Process_results_shredderC3!$B$2 | E6: =[16]Process_results_C3_P1!C6+[15]Process_results_shredderC3!$C$2 | F6: =L6 | G6: 0 | H6: 489.2 | I6: 42251.83 | J6: 8129.51 | K6: 0 | L6: =[16]Process_results_C3_P1!D6+[15]Process_results_shredderC3!$D$2 | M6: =[16]Process_results_C3_P1!I6+[15]Process_results_shredderC3!$E$2 | N6: =[16]Process_results_C3_P1!J6+[15]Process_results_shredderC3!$F$2 | O6: =[16]Process_results_C3_P1!K6+[15]Process_results_shredderC3!$G$2 | P6: =[16]Process_results_C3_P1!L6+[15]Process_results_shredderC3!$H$2 | Q6: =[16]Process_results_C3_P1!M6+[15]Process_results_shredderC3!$I$2
A7: Wash 1 | B7: PE | C7: Dodecanol | D7: =[16]Process_results_C3_P1!B7+[15]Process_results_shredderC3!$B$2 | E7: =[16]Process_results_C3_P1!C7+[15]Process_results_shredderC3!$C$2 | F7: =L7 | G7: 0 | H7: 2058.3 | I7: 173624.6 | J7: 8514.94 | K7: 0 | L7: =[16]Process_results_C3_P1!D7+[15]Process_results_shredderC3!$D$2 | M7: =[16]Process_results_C3_P1!I7+[15]Process_results_shredderC3!$E$2 | N7: =[16]Process_results_C3_P1!J7+[15]Process_results_shredderC3!$F$2 | O7: =[16]Process_results_C3_P1!K7+[15]Process_results_shredderC3!$G$2 | P7: =[16]Process_results_C3_P1!L7+[15]Process_results_shredderC3!$H$2 | Q7: =[16]Process_results_C3_P1!M7+[15]Process_results_shredderC3!$I$2
A8: Wash 1 | B8: PE | C8: Heptane | D8: =[16]Process_results_C3_P1!B8+[15]Process_results_shredderC3!$B$2 | E8: =[16]Process_results_C3_P1!C8+[15]Process_results_shredderC3!$C$2 | F8: =L8 | G8: 0 | H8: 519.2 | I8: 44810.07 | J8: 9006.42 | K8: 0 | L8: =[16]Process_results_C3_P1!D8+[15]Process_results_shredderC3!$D$2 | M8: =[16]Process_results_C3_P1!I8+[15]Process_results_shredderC3!$E$2 | N8: =[16]Process_results_C3_P1!J8+[15]Process_results_shredderC3!$F$2 | O8: =[16]Process_results_C3_P1!K8+[15]Process_results_shredderC3!$G$2 | P8: =[16]Process_results_C3_P1!L8+[15]Process_results_shredderC3!$H$2 | Q8: =[16]Process_results_C3_P1!M8+[15]Process_results_shredderC3!$I$2
A9: Wash 1 | B9: PE | C9: Toluene | D9: =[16]Process_results_C3_P1!B9+[15]Process_results_shredderC3!$B$2 | E9: =[16]Process_results_C3_P1!C9+[15]Process_results_shredderC3!$C$2 | F9: =L9 | G9: 0 | H9: 627.32 | I9: 54056.42 | J9: 11871.24 | K9: 0 | L9: =[16]Process_results_C3_P1!D9+[15]Process_results_shredderC3!$D$2 | M9: =[16]Process_results_C3_P1!I9+[15]Process_results_shredderC3!$E$2 | N9: =[16]Process_results_C3_P1!J9+[15]Process_results_shredderC3!$F$2 | O9: =[16]Process_results_C3_P1!K9+[15]Process_results_shredderC3!$G$2 | P9: =[16]Process_results_C3_P1!L9+[15]Process_results_shredderC3!$H$2 | Q9: =[16]Process_results_C3_P1!M9+[15]Process_results_shredderC3!$I$2
A10: Wash 1 | B10: PE | C10: Xylene | D10: =[16]Process_results_C3_P1!B10+[15]Process_results_shredderC3!$B$2 | E10: =[16]Process_results_C3_P1!C10+[15]Process_results_shredderC3!$C$2 | F10: =L10 | G10: 0 | H10: 758.24 | I10: 64966.4 | J10: 7294.56 | K10: 0 | L10: =[16]Process_results_C3_P1!D10+[15]Process_results_shredderC3!$D$2 | M10: =[16]Process_results_C3_P1!I10+[15]Process_results_shredderC3!$E$2 | N10: =[16]Process_results_C3_P1!J10+[15]Process_results_shredderC3!$F$2 | O10: =[16]Process_results_C3_P1!K10+[15]Process_results_shredderC3!$G$2 | P10: =[16]Process_results_C3_P1!L10+[15]Process_results_shredderC3!$H$2 | Q10: =[16]Process_results_C3_P1!M10+[15]Process_results_shredderC3!$I$2
A11: Wash 1 | B11: EVOH | C11: Ethylene Glycol | D11: =[17]Process_results_C3_E1!B2+[15]Process_results_shredderC3!$B$2 | E11: =[17]Process_results_C3_E1!C2+[15]Process_results_shredderC3!$C$2 | F11: =L11 | G11: 0 | H11: 1364.7 | I11: 120119.92 | J11: 2426.35 | K11: 0 | L11: =[17]Process_results_C3_E1!D2+[15]Process_results_shredderC3!$D$2 | M11: =[17]Process_results_C3_E1!I2+[15]Process_results_shredderC3!$E$2 | N11: =[17]Process_results_C3_E1!J2+[15]Process_results_shredderC3!$F$2 | O11: =[17]Process_results_C3_E1!K2+[15]Process_results_shredderC3!$G$2 | P11: =[17]Process_results_C3_E1!L2+[15]Process_results_shredderC3!$H$2 | Q11: =[17]Process_results_C3_E1!M2+[15]Process_results_shredderC3!$I$2
A12: Wash 1 | B12: EVOH | C12: Pyridazine | D12: =[17]Process_results_C3_E1!B3+[15]Process_results_shredderC3!$B$2 | E12: =[17]Process_results_C3_E1!C3+[15]Process_results_shredderC3!$C$2 | F12: =L12 | G12: 0 | H12: 819.92 | I12: 71782.02 | J12: 2837.85 | K12: 0 | L12: =[17]Process_results_C3_E1!D3+[15]Process_results_shredderC3!$D$2 | M12: =[17]Process_results_C3_E1!I3+[15]Process_results_shredderC3!$E$2 | N12: =[17]Process_results_C3_E1!J3+[15]Process_results_shredderC3!$F$2 | O12: =[17]Process_results_C3_E1!K3+[15]Process_results_shredderC3!$G$2 | P12: =[17]Process_results_C3_E1!L3+[15]Process_results_shredderC3!$H$2 | Q12: =[17]Process_results_C3_E1!M3+[15]Process_results_shredderC3!$I$2
A13: Wash 2 | B13: PE | C13: sec-Butyl Acetate | D13: =[18]Process_results_C3_P2!B2+[15]Process_results_shredderC3!$B$2 | E13: =[18]Process_results_C3_P2!C2+[15]Process_results_shredderC3!$C$2 | F13: =L13 | G13: 0 | H13: 574.99 | I13: 49212.73 | J13: 7303.6 | K13: 0 | L13: =[18]Process_results_C3_P2!D2+[15]Process_results_shredderC3!$D$2 | M13: =[18]Process_results_C3_P2!I2+[15]Process_results_shredderC3!$E$2 | N13: =[18]Process_results_C3_P2!J2+[15]Process_results_shredderC3!$F$2 | O13: =[18]Process_results_C3_P2!K2+[15]Process_results_shredderC3!$G$2 | P13: =[18]Process_results_C3_P2!L2+[15]Process_results_shredderC3!$H$2 | Q13: =[18]Process_results_C3_P2!M2+[15]Process_results_shredderC3!$I$2
A14: Wash 2 | B14: PE | C14: Isobutyl Acetate | D14: =[18]Process_results_C3_P2!B3+[15]Process_results_shredderC3!$B$2 | E14: =[18]Process_results_C3_P2!C3+[15]Process_results_shredderC3!$C$2 | F14: =L14 | G14: 0 | H14: 566.31 | I14: 48512.56 | J14: 7363.19 | K14: 0 | L14: =[18]Process_results_C3_P2!D3+[15]Process_results_shredderC3!$D$2 | M14: =[18]Process_results_C3_P2!I3+[15]Process_results_shredderC3!$E$2 | N14: =[18]Process_results_C3_P2!J3+[15]Process_results_shredderC3!$F$2 | O14: =[18]Process_results_C3_P2!K3+[15]Process_results_shredderC3!$G$2 | P14: =[18]Process_results_C3_P2!L3+[15]Process_results_shredderC3!$H$2 | Q14: =[18]Process_results_C3_P2!M3+[15]Process_results_shredderC3!$I$2
A15: Wash 2 | B15: PE | C15: Tetrachloroethylene | D15: =[18]Process_results_C3_P2!B4+[15]Process_results_shredderC3!$B$2 | E15: =[18]Process_results_C3_P2!C4+[15]Process_results_shredderC3!$C$2 | F15: =L15 | G15: 0 | H15: 278.69 | I15: 23781.35 | J15: 4341.89 | K15: 0 | L15: =[18]Process_results_C3_P2!D4+[15]Process_results_shredderC3!$D$2 | M15: =[18]Process_results_C3_P2!I4+[15]Process_results_shredderC3!$E$2 | N15: =[18]Process_results_C3_P2!J4+[15]Process_results_shredderC3!$F$2 | O15: =[18]Process_results_C3_P2!K4+[15]Process_results_shredderC3!$G$2 | P15: =[18]Process_results_C3_P2!L4+[15]Process_results_shredderC3!$H$2 | Q15: =[18]Process_results_C3_P2!M4+[15]Process_results_shredderC3!$I$2
A16: Wash 2 | B16: PE | C16: o-Chlorotoluene | D16: =[18]Process_results_C3_P2!B5+[15]Process_results_shredderC3!$B$2 | E16: =[18]Process_results_C3_P2!C5+[15]Process_results_shredderC3!$C$2 | F16: =L16 | G16: 0 | H16: 707.51 | I16: 60319.06 | J16: 6226.9 | K16: 0 | L16: =[18]Process_results_C3_P2!D5+[15]Process_results_shredderC3!$D$2 | M16: =[18]Process_results_C3_P2!I5+[15]Process_results_shredderC3!$E$2 | N16: =[18]Process_results_C3_P2!J5+[15]Process_results_shredderC3!$F$2 | O16: =[18]Process_results_C3_P2!K5+[15]Process_results_shredderC3!$G$2 | P16: =[18]Process_results_C3_P2!L5+[15]Process_results_shredderC3!$H$2 | Q16: =[18]Process_results_C3_P2!M5+[15]Process_results_shredderC3!$I$2
A17: Wash 2 | B17: PE | C17: Methylcyclohexane | D17: =[18]Process_results_C3_P2!B6+[15]Process_results_shredderC3!$B$2 | E17: =[18]Process_results_C3_P2!C6+[15]Process_results_shredderC3!$C$2 | F17: =L17 | G17: 0 | H17: 455.45 | I17: 39219.93 | J17: 8025.78 | K17: 0 | L17: =[18]Process_results_C3_P2!D6+[15]Process_results_shredderC3!$D$2 | M17: =[18]Process_results_C3_P2!I6+[15]Process_results_shredderC3!$E$2 | N17: =[18]Process_results_C3_P2!J6+[15]Process_results_shredderC3!$F$2 | O17: =[18]Process_results_C3_P2!K6+[15]Process_results_shredderC3!$G$2 | P17: =[18]Process_results_C3_P2!L6+[15]Process_results_shredderC3!$H$2 | Q17: =[18]Process_results_C3_P2!M6+[15]Process_results_shredderC3!$I$2
A18: Wash 2 | B18: PE | C18: Dodecanol | D18: =[18]Process_results_C3_P2!B7+[15]Process_results_shredderC3!$B$2 | E18: =[18]Process_results_C3_P2!C7+[15]Process_results_shredderC3!$C$2 | F18: =L18 | G18: 0 | H18: 1998.05 | I18: 168466.47 | J18: 8405.55 | K18: 0 | L18: =[18]Process_results_C3_P2!D7+[15]Process_results_shredderC3!$D$2 | M18: =[18]Process_results_C3_P2!I7+[15]Process_results_shredderC3!$E$2 | N18: =[18]Process_results_C3_P2!J7+[15]Process_results_shredderC3!$F$2 | O18: =[18]Process_results_C3_P2!K7+[15]Process_results_shredderC3!$G$2 | P18: =[18]Process_results_C3_P2!L7+[15]Process_results_shredderC3!$H$2 | Q18: =[18]Process_results_C3_P2!M7+[15]Process_results_shredderC3!$I$2
A19: Wash 2 | B19: PE | C19: Heptane | D19: =[18]Process_results_C3_P2!B8+[15]Process_results_shredderC3!$B$2 | E19: =[18]Process_results_C3_P2!C8+[15]Process_results_shredderC3!$C$2 | F19: =L19 | G19: 0 | H19: 485.82 | I19: 41810.72 | J19: 8897.14 | K19: 0 | L19: =[18]Process_results_C3_P2!D8+[15]Process_results_shredderC3!$D$2 | M19: =[18]Process_results_C3_P2!I8+[15]Process_results_shredderC3!$E$2 | N19: =[18]Process_results_C3_P2!J8+[15]Process_results_shredderC3!$F$2 | O19: =[18]Process_results_C3_P2!K8+[15]Process_results_shredderC3!$G$2 | P19: =[18]Process_results_C3_P2!L8+[15]Process_results_shredderC3!$H$2 | Q19: =[18]Process_results_C3_P2!M8+[15]Process_results_shredderC3!$I$2
A20: Wash 2 | B20: PE | C20: Toluene | D20: =[18]Process_results_C3_P2!B9+[15]Process_results_shredderC3!$B$2 | E20: =[18]Process_results_C3_P2!C9+[15]Process_results_shredderC3!$C$2 | F20: =L20 | G20: 0 | H20: 588.12 | I20: 50538.24 | J20: 11716.23 | K20: 0 | L20: =[18]Process_results_C3_P2!D9+[15]Process_results_shredderC3!$D$2 | M20: =[18]Process_results_C3_P2!I9+[15]Process_results_shredderC3!$E$2 | N20: =[18]Process_results_C3_P2!J9+[15]Process_results_shredderC3!$F$2 | O20: =[18]Process_results_C3_P2!K9+[15]Process_results_shredderC3!$G$2 | P20: =[18]Process_results_C3_P2!L9+[15]Process_results_shredderC3!$H$2 | Q20: =[18]Process_results_C3_P2!M9+[15]Process_results_shredderC3!$I$2
A21: Wash 2 | B21: PE | C21: Xylene | D21: =[18]Process_results_C3_P2!B10+[15]Process_results_shredderC3!$B$2 | E21: =[18]Process_results_C3_P2!C10+[15]Process_results_shredderC3!$C$2 | F21: =L21 | G21: 0 | H21: 723.9 | I21: 61892.36 | J21: 7194.85 | K21: 0 | L21: =[18]Process_results_C3_P2!D10+[15]Process_results_shredderC3!$D$2 | M21: =[18]Process_results_C3_P2!I10+[15]Process_results_shredderC3!$E$2 | N21: =[18]Process_results_C3_P2!J10+[15]Process_results_shredderC3!$F$2 | O21: =[18]Process_results_C3_P2!K10+[15]Process_results_shredderC3!$G$2 | P21: =[18]Process_results_C3_P2!L10+[15]Process_results_shredderC3!$H$2 | Q21: =[18]Process_results_C3_P2!M10+[15]Process_results_shredderC3!$I$2
A22: Wash 2 | B22: EVOH | C22: butane-1,4-diol | D22: =[19]Process_results_C3_E2!B2+[15]Process_results_shredderC3!$B$2 | E22: =[19]Process_results_C3_E2!C2+[15]Process_results_shredderC3!$C$2 | F22: =L22 | G22: 0 | H22: 481.94 | I22: 41610.4 | J22: 1300.32 | K22: 0 | L22: =[19]Process_results_C3_E2!D2+[15]Process_results_shredderC3!$D$2 | M22: =[19]Process_results_C3_E2!I2+[15]Process_results_shredderC3!$E$2 | N22: =[19]Process_results_C3_E2!J2+[15]Process_results_shredderC3!$F$2 | O22: =[19]Process_results_C3_E2!K2+[15]Process_results_shredderC3!$G$2 | P22: =[19]Process_results_C3_E2!L2+[15]Process_results_shredderC3!$H$2 | Q22: =[19]Process_results_C3_E2!M2+[15]Process_results_shredderC3!$I$2
A23: Wash 2 | B23: EVOH | C23: Diethanolamine | D23: =[19]Process_results_C3_E2!B3+[15]Process_results_shredderC3!$B$2 | E23: =[19]Process_results_C3_E2!C3+[15]Process_results_shredderC3!$C$2 | F23: =L23 | G23: 0 | H23: 634.14 | I23: 54352.05 | J23: 1159.6 | K23: 0 | L23: =[19]Process_results_C3_E2!D3+[15]Process_results_shredderC3!$D$2 | M23: =[19]Process_results_C3_E2!I3+[15]Process_results_shredderC3!$E$2 | N23: =[19]Process_results_C3_E2!J3+[15]Process_results_shredderC3!$F$2 | O23: =[19]Process_results_C3_E2!K3+[15]Process_results_shredderC3!$G$2 | P23: =[19]Process_results_C3_E2!L3+[15]Process_results_shredderC3!$H$2 | Q23: =[19]Process_results_C3_E2!M3+[15]Process_results_shredderC3!$I$2
A24: Wash 2 | B24: EVOH | C24: Diethylene glycol | D24: =[19]Process_results_C3_E2!B4+[15]Process_results_shredderC3!$B$2 | E24: =[19]Process_results_C3_E2!C4+[15]Process_results_shredderC3!$C$2 | F24: =L24 | G24: 0 | H24: 517.25 | I24: 44366.54 | J24: 1138.81 | K24: 0 | L24: =[19]Process_results_C3_E2!D4+[15]Process_results_shredderC3!$D$2 | M24: =[19]Process_results_C3_E2!I4+[15]Process_results_shredderC3!$E$2 | N24: =[19]Process_results_C3_E2!J4+[15]Process_results_shredderC3!$F$2 | O24: =[19]Process_results_C3_E2!K4+[15]Process_results_shredderC3!$G$2 | P24: =[19]Process_results_C3_E2!L4+[15]Process_results_shredderC3!$H$2 | Q24: =[19]Process_results_C3_E2!M4+[15]Process_results_shredderC3!$I$2
A25: Wash 2 | B25: EVOH | C25: Ethylene Glycol | D25: =[19]Process_results_C3_E2!B5+[15]Process_results_shredderC3!$B$2 | E25: =[19]Process_results_C3_E2!C5+[15]Process_results_shredderC3!$C$2 | F25: =L25 | G25: 0 | H25: 565 | I25: 49348.09 | J25: 1132.86 | K25: 0 | L25: =[19]Process_results_C3_E2!D5+[15]Process_results_shredderC3!$D$2 | M25: =[19]Process_results_C3_E2!I5+[15]Process_results_shredderC3!$E$2 | N25: =[19]Process_results_C3_E2!J5+[15]Process_results_shredderC3!$F$2 | O25: =[19]Process_results_C3_E2!K5+[15]Process_results_shredderC3!$G$2 | P25: =[19]Process_results_C3_E2!L5+[15]Process_results_shredderC3!$H$2 | Q25: =[19]Process_results_C3_E2!M5+[15]Process_results_shredderC3!$I$2
A26: Wash 2 | B26: EVOH | C26: Propylene Glycol | D26: =[19]Process_results_C3_E2!B6+[15]Process_results_shredderC3!$B$2 | E26: =[19]Process_results_C3_E2!C6+[15]Process_results_shredderC3!$C$2 | F26: =L26 | G26: 0 | H26: 510.74 | I26: 44465.78 | J26: 1202.77 | K26: 0 | L26: =[19]Process_results_C3_E2!D6+[15]Process_results_shredderC3!$D$2 | M26: =[19]Process_results_C3_E2!I6+[15]Process_results_shredderC3!$E$2 | N26: =[19]Process_results_C3_E2!J6+[15]Process_results_shredderC3!$F$2 | O26: =[19]Process_results_C3_E2!K6+[15]Process_results_shredderC3!$G$2 | P26: =[19]Process_results_C3_E2!L6+[15]Process_results_shredderC3!$H$2 | Q26: =[19]Process_results_C3_E2!M6+[15]Process_results_shredderC3!$I$2
A27: Wash 2 | B27: EVOH | C27: Pyridazine | D27: =[19]Process_results_C3_E2!B7+[15]Process_results_shredderC3!$B$2 | E27: =[19]Process_results_C3_E2!C7+[15]Process_results_shredderC3!$C$2 | F27: =L27 | G27: 0 | H27: 342.82 | I27: 29775.3 | J27: 1332.07 | K27: 0 | L27: =[19]Process_results_C3_E2!D7+[15]Process_results_shredderC3!$D$2 | M27: =[19]Process_results_C3_E2!I7+[15]Process_results_shredderC3!$E$2 | N27: =[19]Process_results_C3_E2!J7+[15]Process_results_shredderC3!$F$2 | O27: =[19]Process_results_C3_E2!K7+[15]Process_results_shredderC3!$G$2 | P27: =[19]Process_results_C3_E2!L7+[15]Process_results_shredderC3!$H$2 | Q27: =[19]Process_results_C3_E2!M7+[15]Process_results_shredderC3!$I$2
A28: Wash 2 | B28: EVOH | C28: gamma-butyrolactone | D28: =[19]Process_results_C3_E2!B8+[15]Process_results_shredderC3!$B$2 | E28: =[19]Process_results_C3_E2!C8+[15]Process_results_shredderC3!$C$2 | F28: =L28 | G28: 0 | H28: 354.13 | I28: 30701.09 | J28: 1154.61 | K28: 0 | L28: =[19]Process_results_C3_E2!D8+[15]Process_results_shredderC3!$D$2 | M28: =[19]Process_results_C3_E2!I8+[15]Process_results_shredderC3!$E$2 | N28: =[19]Process_results_C3_E2!J8+[15]Process_results_shredderC3!$F$2 | O28: =[19]Process_results_C3_E2!K8+[15]Process_results_shredderC3!$G$2 | P28: =[19]Process_results_C3_E2!L8+[15]Process_results_shredderC3!$H$2 | Q28: =[19]Process_results_C3_E2!M8+[15]Process_results_shredderC3!$I$2

Sheet Sheet1
A2: New
A3: Waste generated - Non Hazardous [kg/ton]
A4: 1000 | E4: 4
A5: 0.1 | E5: 1.81
A6: 250 | E6: 0.6
A7: =E7*1000 | E7: =(387.663)/1000
A8: 820.91503 | E8: =2.512*1000/(3.06*1000)
A9: 1046.4052 | E9: =3.202*1000/(3.06*1000)
G16: PE | H16: sec-Butyl Acetate | I16: 2212872.3 | J16: 2119984.8 | K16: =I16+J16
G17: PE | H17: Isobutyl Acetate | I17: 2218620.4 | J17: 2121724.5 | K17: =I17+J17
G18: PE | H18: Tetrachloroethylene | I18: 1954380.3 | J18: 2010549.2 | K18: =I18+J18
G19: PE | H19: o-Chlorotoluene | I19: 2144665.2 | J19: 2098248.3 | K19: =I19+J19
G20: PE | H20: Methylcyclohexane | I20: 2253826.7 | J20: 2131438 | K20: =I20+J20 | L20: =MIN(K16:K26)
G21: PE | H21: Dodecanol | I21: 2416191.4 | J21: 2258339.1 | K21: =I21+J21 | L21: =MIN(K36:K42)
G22: PE | H22: Heptane | I22: 2326295.9 | J22: 2160852.4 | K22: =I22+J22 | M22: =K29+K25
G23: PE | H23: Toluene | I23: 2517981.6 | J23: 2252782.3 | K23: =I23+J23
G24: PE | H24: Xylene | I24: 2221161.3 | J24: 2127790.4 | K24: =I24+J24
G25: EVOH | H25: Ethylene Glycol | I25: 1125121.6 | J25: 1644561.8 | K25: =I25+J25
G26: EVOH | H26: Pyridazine | I26: 1134875.6 | J26: 1643546.5 | K26: =I26+J26
G27: PE | H27: sec-Butyl Acetate | I27: 2046560.8 | J27: 1047740.1 | K27: =I27+J27 | M27: =K18+K42
G28: PE | H28: Isobutyl Acetate | I28: 2059268.1 | J28: 1052268.2 | K28: =I28+J28
G29: PE | H29: Tetrachloroethylene | I29: 1787741.2 | J29: 938269.24 | K29: =I29+J29
G30: PE | H30: o-Chlorotoluene | I30: 1984860.2 | J30: 1028423.1 | K30: =I30+J30
G31: PE | H31: Methylcyclohexane | I31: 2087787 | J31: 1059416.7 | K31: =I31+J31
G32: PE | H32: Dodecanol | I32: 2254718.2 | J32: 1186252 | K32: =I32+J32
G33: PE | H33: Heptane | I33: 2160401.7 | J33: 1088889.2 | K33: =I33+J33
G34: PE | H34: Toluene | I34: 2349306.3 | J34: 1179441.8 | K34: =I34+J34
G35: PE | H35: Xylene | I35: 2061733.2 | J35: 1058246.1 | K35: =I35+J35
G36: EVOH | H36: butane-1,4-diol | I36: 918722.54 | J36: 1564162.3 | K36: =I36+J36
G37: EVOH | H37: Diethanolamine | I37: 923194.27 | J37: 1569675 | K37: =I37+J37
G38: EVOH | H38: Diethylene glycol | I38: 917187.54 | J38: 1565126.2 | K38: =I38+J38
G39: EVOH | H39: Ethylene Glycol | I39: 906491.33 | J39: 1558743.9 | K39: =I39+J39
... G42: EVOH | H42: gamma-butyrolactone | I42: 884387.12 | J42: 1548701.7 | K42: =I42+J42

Sheet Final Results December
A2: For Scenario 1 | C2: max CE | D2: 0.32 | J2: try | AO2: location scenarios | AP2: energy | AQ2: ghg | AR2: w-withdrawal | AS2: waste
D3: if constraint >= 0.6 then 0.67 | J3: CE*1000 | V3: Scenario A | AB3: Scenario B | AI3: Scenario C | AO3: Scenario 1 | AP3: 55420195 | AQ3: 21303.36 | AR3: 14468.809 | AS3: 1917727.2
L4: Max Profit | V4: Max Profit | W4: Min Emissions | X4: Max CE | AC4: Max Profit | AD4: Min Emissions | AE4: Max CE | AJ4: Max Profit | AK4: Min Emissions | AL4: Max CE | AO4: Scenario 2 | AP4: 49562225 | AQ4: 17569.948 | AR4: 14468.809 | AS4: 1916439.8
D5: wash 2 | L5: 6515394.2 | M5: 7551142 | N5: 6310471.8 | U5: Profit | V5: 6244167.8 | W5: -91919.92 | X5: 5960966.7 | AB5: Profit | AC5: 6256751 | AD5: -91919.92 | AE5: 5960966.7 | AI5: Profit | AJ5: 8869140 | AK5: -91919.92 | AL5: 8493618.4 | AO5: Scenario 3 | AP5: 62608505 | AQ5: 20100.179 | AR5: 14359.144 | AS5: 1917727.2
A6: Scenario 2 | D6: EVOH pyridazine | F6: infeasible for case 3 | L6: =C12 | U6: Emissions | V6: 12330.065 | W6: 691.65086 | X6: 6619.5974 | AB6: Emissions | AC6: 16351.199 | AD6: 691.65086 | AE6: 6619.5974 | AI6: Emissions | AJ6: 11841.354 | AK6: 691.65086 | AL6: 5898.3157
L7: =C14 | U7: CE | V7: =577774.940750356/1000000 | W7: =606548.261207768/1000000 | X7: =727766.667951268/1000000 | AB7: CE | AC7: =499368.792474627/1000000 | AD7: =606548.261207768/1000000 | AE7: =727766.667951277/1000000 | AI7: CE | AJ7: =562792.446017788/1000000 | AK7: =606548.261207768/1000000 | AL7: =727529.107687184/1000000
A8: Scenario 3 | D8: EVOH gammabuty | L8: Max CE | V8: Pe tetra+EVOH gamma+we | W8: lf | X8: p tetra+Evoh pyri+lf | AC8: Pe tetra+EVOH gamma+gash2 | AD8: lf | AE8: p tetra+Evoh pyri+lf | AJ8: Strap 1 (EVOH, ethylene glycol)+Strap 2 (PE tetrachloroethylene)+incineration | AK8: landfill | AL8: pe tetra+evoh pyri+lf
L9: =D15 | M9: =K15 | N9: =Q15 | U9: Energy | V9: 0.36327882 | W9: 0.56070069 | X9: 0.36093183 | AB9: Energy | AC9: 0.26194867 | AD9: 0.56520806 | AE9: 0.39362898
U10: GHG | V10: 0.42121503 | W10: 0.96753325 | X10: 0.68926979 | AB10: GHG | AC10: 0.23245913 | AD10: 0.96753325 | AE10: 0.68926979 | AJ10: E_score:0.32920838627245796 | AL10: E_score:0.35678925046736343
A11: Scenario 1 | H11: Scenario 2 | U11: Water | V11: 0.30544154 | W11: 1 | X11: 0.97499066 | AB11: Water | AC11: 0.75640585 | AD11: 1 | AE11: 0.97779949 | AJ11: GHG_score:0.44415554825079806 | AL11: GHG_score:0.7231274437096047
B12: Max Profit | C12: Min Emissions | D12: Max CE (w Emissions and Profit) | I12: Max Profit | J12: Min Emissions | K12: Max CE (w Emissions and Profit) | N12: Scenario 3 | O12: Max Profit | P12: Min Emissions | Q12: Max CE | U12: Waste | V12: 0.99848312 | W12: 0.5 | X12: 0.84849944 | AB12: Waste | AC12: 0.5 | AD12: 0.5 | AE12: 0.84850229 | AJ12: Water_score:0.2963930485485831 | AL12: Water_score:0.9795937586028809
A13: Profit | B13: 6515394.2 | C13: -62687.92 | D13: 6223849.2 | H13: Profit | I13: 7551142 | J13: -62687.92 | K13: 7240041.2 | N13: Profit | O13: 6310471.8 | P13: -62687.92 | Q13: 6003448.3 | U13: Subs | V13: 0.74603031 | W13: 0 | X13: 0.7296328 | AB13: Subs | AC13: 0.74603031 | AD13: 0 | AE13: 0.7296328 | AJ13: Waste_score:0.998174936458095 | AL13: Waste_score:0.8485022906250156
A14: Emissions | B14: 18963.689 | C14: 652.8 | D14: 9031.0549 | H14: Emissions | I14: 15548.586 | J14: 652.8 | K14: 5937.7687 | N14: Emissions | O14: 16230.688 | P14: 652.8 | Q14: 6607.9422 | AJ14: Subs_score:0.7460303105590064 | AL14: Subs_score:0.7296327950310559
A15: CE | B15: =432.038474617195/1000 | C15: =606.683018608157/1000 | D15: =674.862365213812/1000 | H15: CE | I15: =485.133832758975/1000 | J15: =606.683018608157/1000 | K15: =72281.7092241185/100000 | N15: CE | O15: =485771.265239585/1000000 | P15: =606.683018608157/1000 | Q15: =723634.505269942/1000000
A16: Solution | B16: st1(EVOH, ethylene)+st2(PE tetra) +gas_h2 | C16: lf | D16: st1(EVOH Pyri)+st2(PE tetra)+lf | H16: Solution | I16: st1(Pe tetra)+st2(EVOH gamma) +gas_h2 | J16: lf | K16: st1(PE tetra)+st2(EVOH pyri)+lf | N16: Solution | O16: st1(Pe tetra)+st2(EVOH gamma) +gas_h2 | P16: lf | Q16: st1(PE tetra)+st2(EVOH pyri)+lf
V17: 777.49383 | W17: 12315.4 | X17: pe tetra+evoh pyri+we | Y17: UB_just for scenario B | Z17: 49562225 | AC17: Profit | AD17: Emissions | AJ17: Profit | AK17: Emissions | AL17: Profit | AM17: Emissions
V18: Profit | W18: Emissions | Z18: 17569.948 | AC18: 782.09387 | AD18: =9457.08174979932/8000 | AE18: pe tetra+EVOH gamma+gas_h2cc | AJ18: 8869135.8 | AK18: 11841.354 | AL18: =AJ18/8000 | AM18: =AK18/8000 | AN18: st1(evoh ethylene glycol)+st2(Pe tetra)+we
J19: =A11 | M19: =H11 | P19: =N12 | V19: 780.52097 | W19: =12330.06452/8000 | X19: Pe tetra+EVOH gamma+we | AC19: 748.14798 | AD19: =6634.26150889812/8000 | AE19: pe tetra+EVOH gamma+lf | AJ19: 8771959.8 | AK19: 11596.898 | AL19: =AJ19/8000 | AM19: =AK19/8000 | AN19: st1(pe tetra)+st2(evoh gamma)+we
A20: Profit | B20: 5613000 | D20: 5330000 | J20: Max Profit | K20: Min Emissions | L20: Max CE | M20: Max Profit | N20: Min Emissions | O20: Max CE | P20: Max Profit | Q20: Min Emissions | R20: Max CE | V20: 748.14798 | W20: =6634.26150889811/8000 | X20: PE tetra+Evoh Gamma+lf | AC20: 745.12084 | AD20: =6619.59742778145/8000 | AE20: pe tetra+Evoh pyri+lf | AJ20: 8610151.9 | AK20: 6145.5514 | AL20: =AJ20/8000 | AM20: =AK20/8000 | AN20: st1(evoh ethylene glycol)+st2(Pe tetra)+lf
A21: Emissions | B21: 12892.17 | D21: 10178.206 | I21: Solution | J21: st1(EVOH, ethylene)+st2(PE tetra) +gas_h2 | K21: lf | L21: st1(EVOH Pyri)+st2(PE tetra)+lf | M21: st1(Pe tetra)+st2(EVOH gamma) +gas_h2 | N21: lf | O21: st1(PE tetra)+st2(EVOH pyri)+lf | P21: st1(Pe tetra)+st2(EVOH gamma) +gas_h2 | Q21: lf | R21: st1(PE tetra)+st2(EVOH pyri)+lf | V21: 745.12084 | W21: =6619.59742778145/8000 | X21: pe tetra+evoh pyri+lf | AC21: 462.37308 | AD21: =2782.13874184287/8000 | AE21: evoh pyri+lf | AJ21: 8512975.9 | AK21: 5901.0953 | AL21: =AJ21/8000 | AM21: =AK21/8000 | AN21: st1(pe tetra)+st2(evoh gamma)+lf
V22: 462.37308 | W22: =2782.13874184287/8000 | X22: evoh pyri+lf | AC22: -11.48999 | AD22: =691.650863654724/8000 | AE22: lf | AJ22: 4805389 | AK22: 2540.9421 | AL22: =AJ22/8000 | AM22: =AK22/8000 | AN22: st1(evoh ethylene glycol)+lf
B23: PE tetra, EVOH gamma+gas_h2cc | D23: PE tetra, EVOH gamma+lf | I23: Max Profit | J23: Min Emissions | K23: Max CE | O23: Max profit | P23: Min Emissions | Q23: Max CE | V23: -11.48999 | W23: =691.650863654724/8000 | X23: lf | AJ23: 4786863.4 | AK23: 2366.852 | AL23: =AJ23/8000 | AM23: =AK23/8000 | AN23: st1 (evoh pyridazine)+lf
H24: Energy | I24: 0.22330564 | J24: 0.56579958 | K24: 0.35350568 | N24: Energy | O24: 0.26242141 | P24: 0.56579958 | Q24: 0.39286032 | AJ24: -91919.92 | AK24: 691.65086 | AL24: =AJ24/8000 | AM24: =AK24/8000 | AN24: lf
H25: GHG | I25: 0.2286566 | J25: 0.96761551 | K25: 0.70543568 | N25: GHG | O25: 0.19481849 | P25: 0.96761551 | Q25: 0.67218932
H26: Water | I26: 0.72767662 | J26: 1 | K26: 0.97701187 | N26: Water | O26: 0.72558611 | P26: 1 | Q26: 0.97499066
H27: Waste | I27: 0.5 | J27: 0.5 | K27: 0.84849944 | N27: Waste | O27: 0.5 | P27: 0.5 | Q27: 0.84849944
B28: 5613069.7 | H28: Subs | I28: 0.74603031 | J28: 0 | K28: 0.7296328 | N28: Subs | O28: 0.74603031 | P28: 0 | Q28: 0.7296328 | V28: Profit | W28: CE | AC28: profit | AD28: CE | AJ28: profit | AK28: CE | AL28: =AJ28 | AM28: =AK28
B29: 19786.288 | V29: =6244167.791/8000 | W29: 0.67777494 | X29: pe tetra+evoh gamma+we | AC29: =6256750.991/8000 | AD29: =499368.792474626/1000000 | AE29: pe tetra+evoh gamma+gash2 | AJ29: 8869135.8 | AK29: 0.66279245 | AL29: =AJ29/8000 | AM29: =AK29 | AN29: st1(evoh ethylene glycol)+st2(Pe tetra_+we
B30: =333781.351262238/1000000 | V30: =5985183.815/8000 | W30: 0.72758959 | X30: pe tetra+evoh gamma+lf | AC30: 782.09387 | AD30: =556857.586632455/1000000 | AE30: pe tetra+evoh gamma+gash2cc | AJ30: 8850610.2 | AK30: 0.67243307 | AL30: =AJ30/8000 | AM30: =AK30 | AN30: st1(evoh pyridazine)+st2(Pe tetra)+we
B31: PE tetra+EVOH gamma+gas_h2 | V31: =5960966.6875/8000 | W31: 0.72776667 | X31: p tetra+Evoh pyri+lf | AC31: 780.52097 | AD31: =677774.940750278/1000000 | AE31: pe tetra+evoh gamma+we | AJ31: 8771959.8 | AK31: 0.67730889 | AL31: =AJ31/8000 | AM31: =AK31 | AN31: st1(pe tetra)+st2(evoh gamma)_+we
AC32: 748.14798 | AD32: =727589.589986921/1000000 | AE32: pe tetra+evoh gamma+lf | AJ32: 8610151.9 | AK32: 0.71265823 | AL32: =AJ32/8000 | AM32: =AK32 | AN32: st1(evoh ethylene glycol)+st2(Pe tetra_+lf
AC33: 745.12084 | AD33: =727766.667951269/1000000 | AE33: pe tetra+evoh pyri+lf | AJ33: 8591626.3 | AK33: 0.72228376 | AL33: =AJ33/8000 | AM33: =AK33 | AN33: st1(evoh pyridazine)+st2(Pe tetra)+lf
A34: $/ton | B34: kg/ton | G34: =A34 | H34: =B34 | N34: =H34 | O34: kg/ton | AJ34: 8512975.9 | AK34: 0.72715562 | AL34: =AJ34/8000 | AM34: =AK34 | AN34: st1(pe tetra)+st2(evoh gamma)_+lf
A35: cost | B35: emissions | G35: Cost | H35: emissions | N35: Cost | O35: emissions | V35: CE | W35: Emissions | X35: slns | AC35: CE | AD35: Emissions | AJ35: 8493618.4 | AK35: 0.72752911 | AL35: =AJ35/8000 | AM35: =AK35 | AN35: st1(pe tetra)+st2(evoh pyridazine)_+lf
A36: =B13/8000 | B36: =B14/8000 | C36: =B16 | G36: 943.89275 | H36: 1.4320831 | I36: st1(Pe tetra)+st2(EVOH gamma) +we | V36: 0.60654826 | W36: =691.650863654724/8000 | X36: lf | AC36: 0.60654826 | AD36: 0.086456358 | AE36: lf
A37: 814.42427 | B37: 1.5086964 | C37: evoh ethylene glycol+PE tetra+gas_h2cc | G37: =G36 | H37: 1.0818085 | I37: st1(Pe tetra)+st2(EVOH gamma) +gas_h2cc | N37: 788.80897 | O37: 1.1670713 | P37: st1(Pe tetra)+st2(EVOH gamma) +gas_h2cc | V37: 0.66626859 | W37: =2782.13874184288/8000 | X37: evoh pyri+lf | AC37: 0.66626859 | AD37: 0.34776734 | AE37: evoh pyri+lf | AJ37: CE | AK37: Emissions
A38: 779.07347 | B38: 1.1694509 | C38: evoh ethylene glycol+PE tetra+lf | G38: 908.54195 | H38: 0.74256306 | I38: st1(Pe tetra)+st2(EVOH gamma) +lf | N38: 753.45818 | O38: 0.82782578 | P38: st1(Pe tetra)+st2(EVOH gamma) +lf | V38: 0.72776667 | W38: =6619.59742778135/8000 | X38: pe tetra+EVOH pyri+lf | AC38: 0.72776667 | AD38: 0.82744968 | AE38: pe tetra+EVOH pyri+lf | AJ38: 0.60654826 | AK38: 691.65086 | AL38: lf | AN38: =AK38/8000
A39: 777.98115 | B39: 1.1288819 | C39: evoh pyri+pe tetra+lf | G39: 480.96077 | H39: 0.31647732 | I39: evoh ethylene glycol+lf | N39: 468.67168 | O39: 0.34339662 | P39: evoh pyri+lf | AJ39: 0.66053437 | AK39: 2366.852 | AL39: st1(evoh pyri)+lf | AN39: =AK39/8000
A40: 432.43718 | B40: 0.58024192 | C40: evoh ethylene glycol+lf | G40: 476.57222 | H40: 0.29474727 | I40: evoh pyri+lf | N40: -7.83599 | O40: 0.0816 | P40: lf | AJ40: 0.72752911 | AK40: 5898.3157 | AL40: st1(pe tetra)+st2(evoh pyri)+lf | AN40: =AK40/8000
A41: 431.34485 | B41: 0.53967285 | C41: evoh pyridazine+lf | G41: -7.83599 | H41: 0.0816 | I41: lf
A42: -7.83599 | B42: 0.0816 | C42: lf
G44: cost | H44: CE | N44: cost | O44: CE
A45: cost | B45: CE | C45: solution | G45: =I13/8000 | H45: =I15 | I45: =I16 | N45: 788.80897 | O45: 0.48577127 | P45: st1(Pe tetra)+st2(EVOH gamma) +gas_h2
A46: =B13/8000 | B46: =B15 | C46: st1(EVOH, ethylene)+st2(PE tetra) +gas_h2 | G46: 943.89275 | H46: 0.66830378 | I46: pe tetra+evoh gamma+we | N46: 788.80897 | O46: 0.66937814 | P46: pe tetra+evoh gamma+we
A47: 814.42427 | B47: 0.61257875 | C47: evoh ethylene glycol+pe tetra+we | G47: 908.54195 | H47: 0.72243093 | I47: pe tetra+evoh gamma+lf | N47: 753.45818 | O47: 0.72343986 | P47: st1(Pe tetra)+st2(EVOH gamma) +lf
A48: 779.07347 | B48: 0.66682888 | C48: evoh ethylene glycol+Pe tetra+lf | G48: 905.00515 | H48: 0.72281709 | I48: =K16 | N48: 750.43104 | O48: 0.72363451 | P48: PE tetra+EVOH pyri+lf
A49: 777.98115 | B49: 0.67486236 | C49: st1(EVOH Pyri)+st2(PE tetra)+lf
A52: CE | B52: Emissions | G52: CE | H52: Emissions | N52: CE | O52: Emissions
A53: 0.60668302 | B53: 0.0816 | C53: =C16 | G53: 0.60668302 | H53: 0.0816 | I53: lf | N53: 0.60668302 | O53: 0.0816 | P53: 652.8 | Q53: lf
A54: 0.63803225 | B54: 0.53967285 | C54: st1(EVOH Pyri)+lf | G54: 0.65855012 | H54: 0.29474727 | I54: EVOH pyri+lf | N54: 0.66453099 | O54: 0.34339662 | P54: 2747.173 | Q54: evoh pyri+lf
A55: 0.67486237 | B55: 1.1288819 | C55: =D16 | G55: 0.72281709 | H55: 0.74222109 | I55: =K16 | N55: 0.72363451 | O55: 0.82599277 | P55: 6607.9422 | Q55: st1(PE tetra)+st2(EVOH pyri)+lf
K70: Energy | L70: GHG | M70: Water | N70: Waste | O70: Subs
J71: Max Profit | K71: 0.22330564 | L71: 0.2286566 | M71: 0.72767662 | N71: 0.5 | O71: 0.74603031
J72: Min Emissions | K72: 0.56579958 | L72: 0.96761551 | M72: 1 | N72: 0.5 | O72: 0
J73: Max CE | K73: 0.35350568 | L73: 0.70543568 | M73: 0.97701187 | N73: 0.84849944 | O73: 0.7296328
F93: Max Profit | G93: Min Emissions | H93: Max Circularity
E94: Energy Scenario 1 | F94: 0.43203847 | G94: 0.60668302 | H94: 0.67486236
E95: Energy Scenario 2 | F95: 0.48513383 | G95: 0.60668302 | H95: 0.72281709

Sheet Interpolation
A2: Substitutability
A5: STRAP all | B5: 1 | G5: strap PE
D6: lf | F6: PE | G6: 5461488
F7: EVOH | G7: 6285600 | J7: $/ton
F8: PET | G8: 2141760 | I8: Pet price | J8: 1380 | K8: https://businessanalytiq.com/procurementanalytics/index/pet-price-index/
F9: N6 | G9: 2172800 | I9: Nylon 6 | J9: 2800 | K9: https://businessanalytiq.com/procurementanalytics/index/pa6-price-index/
F10: total | G10: =SUM(G6:G9) | H10: 1
G17: 0 | H17: 0
A20: Landfill | B20: 0
